Workbook

Sheet ReadMe
B3: Tab Coloring Legend
C4: Biz Case Inputs
C5: Control Panel
C6: Analysis
C7: Summary

Sheet Gross-to-Net Process
B1: Initial Data
B4: The Gross-to-Net Planning approach - Wholesale
B5: The Sales planning function uses a building block approach to forecasting final net sales
B7: OrderType | C7: Definition
B8: Pre-Orders | C8: The Orders on books taken approx. 6 months before the season begins
B9: Cancellations | C9: The Pre-Orders that cannot be fulfilled or customers are permitted to cancel before delivery
B10: Re-Orders | C10: Additional In-Season orders placed by customers fufilled from available free stock in warehouse
B11: Stock Clearance | C11: Any old season stock the business is willing to sell to a customer
B12: Returns | C12: Any stock the business agreees to take back to the warehouse from a customer
B14: Net Sales FC (forecast) = | C14: Pre-Orders on Book - Forecast Cancellation + Forecast Re-Order + Forecast Stock Clearance - Forecast Returns
B15: Actual Net Sales = | C15: Pre-Orders Invoiced + Re-Orders Invoiced + Stock Clearance Invoiced - Returns Processed
B17: KPI | C17: Definition
B18: Cancellation % Mix | C18: The proportion of the total pre-orderbook that was cancelled for a given time period
B19: % Rate | C19: Re-Order, Stock Clearance or Return volume vs Total Invoiced Pre-Orders for a given time period

Sheet Account Information
A1: Initial Data
A2: Key Account Descriptions
A3: Name | B3: Product Vertical | C3: Description | F3: Product Vertical | G3: Name | H3: Description
A4: Hanover & Hearth | B4: Lifestyle / Sport | C4: Precise, premium department store | F4: Lifestyle | G4: Scale | H4: The "King of Tiers" in sports lifestyle
A5: Vanguard Wilds | B5: Sport | C5: Tech-wear for the Great Outdoors | G5: Swift-Pulse | H5: Experimental street-culture labs
A6: Swift-Pulse | B6: Lifestyle | C6: Experimental street-culture labs | G6: Vault | H6: Staple sneaker archives
A7: Velocity Labs | B7: Sport | C7: Biometric-focused sprinting gear | G7: Velvet & Vice | H7: Elite luxury
A8: Velvet & Vice | B8: Lifestyle | C8: Elite luxury | F8: Lifestyle / Sport | G8: Aurelian & Co. | H8: Prestigious, multi-level luxury spire
A9: Titan Sport | B9: Sport | C9: Mass-market muscle | G9: Axiom Street | H9: Endless digital fashion scroll
A10: Nordic Nord | B10: Sport | C10: Urban-armor optimized for the crumbling wild | G10: Hanover & Hearth | H10: Precise, premium department store
A11: Omni-Arena | B11: Sport | C11: Massive multi-sport hubs | F11: Sport | G11: Agora Athletics | H11: Digital-first performance gear
A12: Aurelian & Co. | B12: Lifestyle / Sport | C12: Prestigious, multi-level luxury spire | G12: Nordic Nord | H12: Urban-armor optimized for the crumbling wild
A13: Agora Athletics | B13: Sport | C13: Digital-first performance gear | G13: Omni-Arena | H13: Massive multi-sport hubs
A14: Axiom Street | B14: Lifestyle / Sport | C14: Endless digital fashion scroll | G14: Strike-Point | H14: Pinicle sporting aesthetics
A15: Vault | B15: Lifestyle | C15: Staple sneaker archives | G15: Titan Sport | H15: Mass-market muscle
A16: Strike-Point | B16: Sport | C16: Pinicle sporting aesthetics | G16: Vanguard Wilds | H16: Tech-wear for the Great Outdoors
A17: Scale | B17: Lifestyle | C17: The "King of Tiers" in sports lifestyle | G17: Velocity Labs | H17: Biometric-focused sprinting gear
A18: Field Accounts | B18: Field Accounts | C18: Generalist

Sheet Hypotesis Panel
B1: Hypotesis
B3: 1) EMEA Spring/Summer Lenghtin Weeks = 26 weeks | F3: 26 | G3: modify in case of different lenght
B5: Fase | C5: Period | D5: Exp SellOut | E5: What's appening
B6: Launch | C6: WK1–4 | D6: 0.05 | E6: First deliveries, floor set
B7: Build | C7: WK5–10 | D7: 0.35 | E7: Peak sell-in, replenishment start
B8: Peak | C8: WK10–18 | D8: 0.5 | E8: Max sell-out velocity | F8: we are in WK | G8: 14 | H8: scroll to choose the week
B9: Markdown Risk | C9: WK19–22 | D9: 0.08 | E9: Inventory correction
B10: Exit | C10: WK22–26 | D10: 0.02 | E10: Clearance / transition FW
B13: 2) Hypotetical Sell-out Distribution x week - Seasonality
B15: Sell-out % x week | C15: WK | D15: Fase % | E15: Cumulated | F15: Quarter
B16: =$D$16/COUNT($C$16:$C$19) -> 0.0125 | C16: 1 | D16: =D6 -> 0.05 | E16: =B16 -> 0.0125 | F16: =E28 -> 0.5875
B17: =$D$16/COUNT($C$16:$C$19) -> 0.0125 | C17: 2 | E17: =B17+E16 -> 0.025
B18: =$D$16/COUNT($C$16:$C$19) -> 0.0125 | C18: 3 | E18: =B18+E17 -> 0.0375
B19: =$D$16/COUNT($C$16:$C$19) -> 0.0125 | C19: 4 | E19: =B19+E18 -> 0.05
B20: =$D$20/COUNT($C$20:$C$25) -> 0.058333333 | C20: 5 | D20: =D7 -> 0.35 | E20: =B20+E19 -> 0.10833333
B21: =$D$20/COUNT($C$20:$C$25) -> 0.058333333 | C21: 6 | E21: =B21+E20 -> 0.16666667
B22: =$D$20/COUNT($C$20:$C$25) -> 0.058333333 | C22: 7 | E22: =B22+E21 -> 0.225 | G22: Q1
B23: =$D$20/COUNT($C$20:$C$25) -> 0.058333333 | C23: 8 | E23: =B23+E22 -> 0.28333333
B24: =$D$20/COUNT($C$20:$C$25) -> 0.058333333 | C24: 9 | E24: =B24+E23 -> 0.34166667
B25: =$D$20/COUNT($C$20:$C$25) -> 0.058333333 | C25: 10 | E25: =B25+E24 -> 0.4
B26: =$D$26/COUNT($C$26:$C$33) -> 0.0625 | C26: 11 | D26: =D8 -> 0.5 | E26: =B26+E25 -> 0.4625
B27: =$D$26/COUNT($C$26:$C$33) -> 0.0625 | C27: 12 | E27: =B27+E26 -> 0.525
B28: =$D$26/COUNT($C$26:$C$33) -> 0.0625 | C28: 13 | E28: =B28+E27 -> 0.5875
B29: =$D$26/COUNT($C$26:$C$33) -> 0.0625 | C29: 14 | E29: =B29+E28 -> 0.65 | F29: =E41-F16 -> 0.4425 | G29: We are here
B30: =$D$26/COUNT($C$26:$C$33) -> 0.0625 | C30: 15 | E30: =B30+E29 -> 0.7125
B31: =$D$26/COUNT($C$26:$C$33) -> 0.0625 | C31: 16 | E31: =B31+E30 -> 0.775
B32: =$D$26/COUNT($C$26:$C$33) -> 0.0625 | C32: 17 | E32: =B32+E31 -> 0.8375
B33: =$D$26/COUNT($C$26:$C$33) -> 0.0625 | C33: 18 | E33: =B33+E32 -> 0.9
B34: =$D$34/COUNT($C$34:$C$37) -> 0.02 | C34: 19 | D34: =D9 -> 0.08 | E34: =B34+E33 -> 0.92
B35: =$D$34/COUNT($C$34:$C$37) -> 0.02 | C35: 20 | E35: =B35+E34 -> 0.94 | G35: Q2
B36: =$D$34/COUNT($C$34:$C$37) -> 0.02 | C36: 21 | E36: =B36+E35 -> 0.96
B37: =$D$34/COUNT($C$34:$C$37) -> 0.02 | C37: 22 | E37: =B37+E36 -> 0.98
B38: =$D$38/COUNT($C$38:$C$41) -> 0.0125 | C38: 23 | D38: 0.05 | E38: =B38+E37 -> 0.9925
B39: =$D$38/COUNT($C$38:$C$41) -> 0.0125 | C39: 24 | E39: =B39+E38 -> 1.005
B40: =$D$38/COUNT($C$38:$C$41) -> 0.0125 | C40: 25 | E40: =B40+E39 -> 1.0175
B41: =$D$38/COUNT($C$38:$C$41) -> 0.0125 | C41: 26 | E41: =B41+E40 -> 1.03
B44: 3) Apparel/Shoes Split
B46: I will assume that the Apparel/Shoes sales split to be 8.22% as LY Q2 (calculation in "SS24 Q2 Data") | F46: ='SS24 Q2 Data'!AB5 -> 0.082166497
B51: 3) Revertig "Actual Net Sales" formula to Extract "Pre-Order Invoiced"
B53: IF | C53: Actual Net Sales = | D53: Pre-Orders Invoiced + Re-Orders Invoiced + Stock Clearance Invoiced - Returns Processed
B54: Then | C54: Pre-Orders Invoiced = | D54: Net Sales Invoiced / ( 1 + Re-Orders % + Stock Clearance % - Returns %)
B57: 4) Stock Clearance Revenue at 20% of Wholesale ASP price | E57: Clearance Discount | F57: 0.2
B59: Weighted ASP (Shoes) | C59: ='Actual vs Budget '!I2 -> 60.745906 | D59: Clearance ASP | E59: =C59*(1-$F$57) -> 48.596725
B60: Weighted ASP (Apparel) | C60: ='Actual vs Budget '!Z2 -> 45.24228 | D60: Clearance ASP | E60: =C60*(1-$F$57) -> 36.193824
B62: 5) SS25 Q2 PreOrdering Hypotesis
C65: SS25 - Targets
B66: Cancellations % | C66: ='SS24 Q2 Data'!AL5 -> 0.072669573 | E66: I will assume an approx 10% Cancellation % for Field accounts
B67: Re-Order Rate % | C67: ='SS24 Q2 Data'!AM5 -> 0.13121821 | E67: I will assume an approx 3% Cancellation % for Core Tier 1 Clients (Stable and reliable)
B68: Stock Clearance% | C68: ='Pivot SS24Q2 Summary'!M9 -> 0.011346493 | E68: I will assume 10% ReOrder on Core Stable Clients, a 15% for all the rest, while leaving a buffer up to 30% for Opportunity fast growing accounts
B69: Returns% | C69: ='SS24 Q2 Data'!AO5 -> 0.03 | E69: I will assume that Titan Sport Cancellation issue to be fixed in the yaer +1 and vault to have introduced apparel
B72: 5) WOS Thresholds Control Panel
B74: WOS Thresholds Buckets | C74: Lower Bound | D74: Action
B75: ="-∞<WOS@WK26<0" -> -∞<WOS@WK26<0 | C75: -1000000000 | D75: Stock Out Risk
B76: ="0<WOS@WK26<1" -> 0<WOS@WK26<1 | C76: 0 | D76: Monitor
B77: ="4<WOS@WK26<6" -> 4<WOS@WK26<6 | C77: 4 | D77: Overstock
B80: 6) Current SS25 Q2 Warehouse Stock
B82: As there is not any indication of the SKU Stock, I will assume the allocation of stock as per SS25 Budget

Sheet Available Stock
B2: Initial Data | G2: Stock Assesment
B3: Available SS25 Q2 Stock in Warehouse | G3: No visibility on Model SKU.
B5: WAREHOUSE STOCK | G5: Category | H5: Current Season | I5: Old Season | J5: Total | K5: Q2 Orderbook | L5: Coverage Ratio
B6: Shoes | D6: Apparel | G6: Shoes | H6: 973440 | I6: 584064 | J6: =SUM(H6:I6) -> 1557504 | K6: =SUM(Table3[[Actual Order Book Shoes ]]) -> 748800 | L6: =J6/K6 -> 2.08
B7: Current season | C7: Old Season | D7: Current Season | E7: Old Season | G7: Apparel | H7: 145552 | I7: 40755 | J7: =SUM(H7:I7) -> 186307 | K7: =SUM(Table3[[Actual Order Book Apparel ]]) -> 100381 | L7: =J7/K7 -> 1.8559986
B8: 973440 | C8: 584064 | D8: 145552.45 | E8: 40754.686 | G8: Total | H8: =SUM(H6:H7) -> 1118992 | I8: =SUM(I6:I7) -> 624819 | J8: =SUM(J6:J7) -> 1743811 | K8: 849181 | L8: =J8/K8 -> 2.053521
G10: Current Shoe stock vs Q2 OB: | J10: =H6-K6 -> 224640 | K10: surplus units available for re-orders
G11: Current Apparel stock vs Q2 OB: | J11: =H7-K7 -> 45171
G12: Potential Clearence Revenuee: | J12: =I6*M12 -> 28383598 | K12: Shoe | L12: Clearance ASP | M12: ='Hypotesis Panel'!E59 -> 48.596725
G13: Potential Clearence Revenuee: | J13: =I7*M13 -> 1475079.3 | K13: Apparel | L13: Clearance ASP | M13: ='Hypotesis Panel'!E60 -> 36.193824
J14: =SUM(J12:J13) -> 29858677

Sheet SS24 Q2 Data
A1: Initial Data | P1: Analysis | AP1: LY Growth Apparel | AQ1: 0.68 | AR1: external sources
A2: SS24 Q2 Net Sales, Cancellation Mix % and Rates % | R2: I've reverted the formulat to extract the Old PreOrder booked value | AD2: Weighted % avg | AP2: LY Growth Shoes | AQ2: 0.25
E4: LY Q2 Shoes | J4: LY Q2 Apparel | P4: LY Q2 Total (Shoes+Apparel) | T4: LY Q2 Shoes (units) | X4: LY Q2 Apparel (units) | AL4: Text in blue is my hypotesis if conditions are met, conditions in the document
C5: Totals | E5: =SUM('SS24 Q2 Data'!$E$7:$E$29) -> 785600 | F5: =SUMPRODUCT('SS24 Q2 Data'!$F$7:$F$29,'SS24 Q2 Data'!$P$7:$P$29)/SUM('SS24 Q2 Data'!$P$7:$P$29) -> 0.13712505 | G5: =SUMPRODUCT($G$7:$G$29,'SS24 Q2 Data'!$P$7:$P$29)/SUM('SS24 Q2 Data'!$P$7:$P$29) -> 0.14914765 | H5: =SUMPRODUCT($H$7:$H$29,'SS24 Q2 Data'!$P$7:$P$29)/SUM('SS24 Q2 Data'!$P$7:$P$29) -> 0.011346493 | I5: =SUMPRODUCT($I$7:$I$29,'SS24 Q2 Data'!$P$7:$P$29)/SUM('SS24 Q2 Data'!$P$7:$P$29) -> 0.033306571 | J5: =SUM('SS24 Q2 Data'!$J$7:$J$29) -> 64550 | K5: =SUMPRODUCT('SS24 Q2 Data'!$K$7:$K$29,'SS24 Q2 Data'!$Q$7:$Q$29)/SUM('SS24 Q2 Data'!$Q$7:$Q$29) -> 0.17246251 | L5: =SUMPRODUCT($L$7:$L$29,'SS24 Q2 Data'!$Q$7:$Q$29)/SUM('SS24 Q2 Data'!$Q$7:$Q$29) -> 0.14708894 | M5: =SUMPRODUCT($M$7:$M$29,'SS24 Q2 Data'!$Q$7:$Q$29)/SUM('SS24 Q2 Data'!$Q$7:$Q$29) -> 0.0021136871 | N5: =SUMPRODUCT($N$7:$N$29,'SS24 Q2 Data'!$Q$7:$Q$29)/SUM('SS24 Q2 Data'!$Q$7:$Q$29) -> 0.042690528 | P5: =SUM('SS24 Q2 Data'!$P$7:$P$29) -> 793485.24 | Q5: =SUM('SS24 Q2 Data'!$Q$7:$Q$29) -> 69107.68 | R5: =SUM('SS24 Q2 Data'!$R$7:$R$29) -> 850150 | S5: =SUM('SS24 Q2 Data'!$S$7:$S$29) -> 862592.92 | T5: =SUM('SS24 Q2 Data'!$T$7:$T$29) -> 108808 | U5: =SUM('SS24 Q2 Data'!$U$7:$U$29) -> 118347 | V5: =SUM('SS24 Q2 Data'!$V$7:$V$29) -> 9003 | W5: =SUM('SS24 Q2 Data'!$W$7:$W$29) -> 26430 | X5: =SUM('SS24 Q2 Data'!$X$7:$X$29) -> 11917 | Y5: =SUM('SS24 Q2 Data'!$Y$7:$Y$29) -> 10165 | Z5: =SUM('SS24 Q2 Data'!$Z$7:$Z$29) -> 146 | AA5: =SUM('SS24 Q2 Data'!$AA$7:$AA$29) -> 146 | AB5: =SUMPRODUCT($AB$7:$AB$29,$E$7:$E$29)/SUM($E$7:$E$29) -> 0.082166497 | AD5: =SUM('SS24 Q2 Data'!$AD$7:$AD$29) -> 120725 | AE5: =SUMPRODUCT('SS24 Q2 Data'!$AE$7:$AE$29,'SS24 Q2 Data'!$S$7:$S$29)/SUM('SS24 Q2 Data'!$S$7:$S$29) -> 0.13995594 | AF5: =SUM('SS24 Q2 Data'!$AF$7:$AF$29) -> 128512 | AG5: =SUMPRODUCT('SS24 Q2 Data'!$AG$7:$AG$29,'SS24 Q2 Data'!$R$7:$R$29)/SUM('SS24 Q2 Data'!$R$7:$R$29) -> 0.15116391 | AH5: =SUM(AH7:AH29) -> 9149 | AI5: =SUMPRODUCT(AI7:AI29,'SS24 Q2 Data'!$S$7:$S$29)/SUM('SS24 Q2 Data'!$S$7:$S$29) -> 0.010606394 | AJ5: =SUM(AJ7:AJ29) -> 26576 | AK5: =SUMPRODUCT(AK7:AK29,'SS24 Q2 Data'!$S$7:$S$29)/SUM('SS24 Q2 Data'!$S$7:$S$29) -> 0.030809434 | AL5: =SUMPRODUCT(Table3[FC Cancellation Mix %Shoes],Table3[Tommaso''s FC Q2 SS5 Net Sales FC Shoes])/SUM(Table3[Tommaso''s FC Q2 SS5 Net Sales FC Shoes]) -> 0.072669573 | AM5: =SUMPRODUCT(Table3[Re-Order Rate % FC],Table3[Tommaso''s FC Q2 SS5 Net Sales FC Shoes])/SUM(Table3[Tommaso''s FC Q2 SS5 Net Sales FC Shoes]) -> 0.13121821 | AN5: =SUMPRODUCT(Table3[Stock Clearance Rate %2],Table3[Tommaso''s FC Q2 SS5 Net Sales FC Shoes])/SUM(Table3[Tommaso''s FC Q2 SS5 Net Sales FC Shoes]) -> 0.01 | AO5: =SUMPRODUCT(Table3[Returns Rate %2],Table3[Tommaso''s FC Q2 SS5 Net Sales FC Shoes])/SUM(Table3[Tommaso''s FC Q2 SS5 Net Sales FC Shoes]) -> 0.03
A6: Sub Region | B6: Market | C6: Account | D6: Client Tier | E6: Net Sales Invoiced Shoes | F6: Pre-Order Cancellations Mix % | G6: Re-Order Rate % | H6: Stock Clearance Rate % | I6: Returns Rate % | J6: Net Sales Invoiced Apparel | K6: Pre-Order Cancellations Mix %2 | L6: Re-Order Rate %4 | M6: Stock Clearance Rate %5 | N6: Returns Rate %6 | O6: Returns Rate %7 | P6: Pre-Orders Booked LYQ2 (shoes) | Q6: Pre-Orders Booked LYQ2 (apparel) | R6: Tot Net Sales Invoiced (units) | S6: Tot PreOrder Invoiced (units) | T6: Pre-Order Cancellations Mix Shoes | U6: Re-Order Rate %7 | V6: Stock Clearance Rate %8 | W6: Returns Rate %9 | X6: Pre-Order Cancellations Mix %Apparel | Y6: Re-Order Rate %11 | Z6: Stock Clearance Rate %12 | AA6: Returns Rate %13 | AB6: Apparel vs Shoes Sell/Out | AC6: Column1 | AD6: Tot Cancellation | AE6: Cancellation % | AF6: ToT Reorders | AG6: Reorder % | AH6: ToT Stock Clearance | AI6: Tot Stock Clearance % | AJ6: ToT Retruns | AK6: Tot Returns % | AL6: FC Cancellation Mix %Shoes | AM6: Re-Order Rate % FC | AN6: Stock Clearance Rate %2 | AO6: Returns Rate %2 | AP6: Exp Shoes PreOrder Growth Rate | AQ6: Exp Apparel PreOrder Growth Rate | AR6: Tommaso's FC Q2 SS5 Net Sales FC Shoes | AS6: Exp YoY Shoes | AT6: Tommaso's FC Q2 SS5 Net Sales FC Apparel | AU6: Exp YoY Apparel | AV6: Actual Order Book Shoes | AW6: Actual Order Book Apparel | AX6: Deviation from Tommaso's suggestion Shoes | AY6: Deviation from Tommaso's suggestion Apparel | AZ6: YoY on Net Sales Shoes | BA6: YoY on Net Sales Apparel
A7: North | B7: BeNeLux | C7: Field Accounts | D7: Monitor | E7: 34800 | F7: 0.208 | G7: 0.264 | H7: 0.104 | I7: 0.055 | J7: 1500 | K7: 0.142 | L7: 6.481 | M7: 0 | N7: 0.144 | P7: =IFERROR(E7/(1-F7+G7+H7-I7),0) -> 31493.213 | Q7: =IFERROR(J7/(1+L7+M7-N7-K7),0) -> 208.47811 | R7: =E7+J7 -> 36300 | S7: ='SS24 Q2 Data'!$P13+Q7 -> 6489.0085 | T7: =ROUND(P7*F7,0) -> 6551 | U7: =ROUND(P7*G7,0) -> 8314 | V7: =ROUND(P7*H7,0) -> 3275 | W7: =ROUND(P7*I7,0) -> 1732 | X7: =ROUND(Q7*K7,0) -> 30 | Y7: =ROUND(Q7*L7,0) -> 1351 | Z7: =ROUND(Q7*M7,0) -> 0 | AA7: =ROUND(Q7*M7,0) -> 0 | AB7: =J7/E7 -> 0.043103448 | AD7: =Table3[[#This Row],[Pre-Order Cancellations Mix Shoes]]+Table3[[#This Row],[Pre-Order Cancellations Mix %Apparel]] -> 6581 | AE7: =Table3[[#This Row],[Tot Cancellation]]/Table3[[#This Row],[Tot PreOrder Invoiced (units)]] -> 1.0141765 | AF7: =Table3[[#This Row],[Re-Order Rate %7]]+Table3[[#This Row],[Re-Order Rate %11]] -> 9665 | AG7: =Table3[[#This Row],[ToT Reorders]]/Table3[[#This Row],[Tot Net Sales Invoiced (units)]] -> 0.26625344 | AH7: =Table3[[#This Row],[Stock Clearance Rate %8]]+Table3[[#This Row],[Stock Clearance Rate %12]] -> 3275 | AI7: =Table3[[#This Row],[ToT Stock Clearance]]/Table3[[#This Row],[Tot PreOrder Invoiced (units)]] -> 0.5046996 | AJ7: =Table3[[#This Row],[Returns Rate %13]]+Table3[[#This Row],[Returns Rate %9]] -> 1732 | AK7: =Table3[[#This Row],[ToT Retruns]]/Table3[[#This Row],[Tot PreOrder Invoiced (units)]] -> 0.26691289 | AL7: 0.1 | AM7: 0.15 | AN7: 0.01 | AO7: 0.03 | AP7: 0.1 | AQ7: =IF(Table3[[#This Row],[Re-Order Rate %4]]-Table3[[#This Row],[Pre-Order Cancellations Mix %2]]-Table3[[#This Row],[Returns Rate %6]]<$AQ$1,$AQ$1,Table3[[#This Row],[Re-Order Rate %4]]-Table3[[#This Row],[Pre-Order Cancellations Mix %2]]-Table3[[#This Row],[Returns Rate %6]]) -> 6.195 | AR7: =Table3[[#This Row],[Pre-Orders Booked LYQ2 (shoes)]]*(1+Table3[[#This Row],[Re-Order Rate % FC]]+Table3[[#This Row],[Stock Clearance Rate %2]]+Table3[[#This Row],[Returns Rate %2]]-Table3[[#This Row],[FC Cancellation Mix %Shoes]]+Table3[[#This Row],[Exp Shoes PreOrder Growth Rate]]) -> 37476.923 | AS7: =Table3[[#This Row],[Tommaso''s FC Q2 SS5 Net Sales FC Shoes]]/Table3[[#This Row],[Net Sales Invoiced Shoes]]-1 -> 0.076923077 | AT7: =Table3[[#This Row],[Pre-Orders Booked LYQ2 (apparel)]]*(1+Table3[[#This Row],[Re-Order Rate % FC]]+Table3[[#This Row],[Stock Clearance Rate %2]]+Table3[[#This Row],[Returns Rate %2]]-Table3[[#This Row],[FC Cancellation Mix %Shoes]]+Table3[[#This Row],[Exp Apparel PreOrder Growth Rate]]) -> 1518.763 | AU7: =Table3[[#This Row],[Tommaso''s FC Q2 SS5 Net Sales FC Apparel]]/Table3[[#This Row],[Net Sales Invoiced Apparel]]-1 -> 0.012508687 | AV7: 33600 | AW7: 3564 | AX7: =Table3[[#This Row],[Actual Order Book Shoes ]]/Table3[[#This Row],[Tommaso''s FC Q2 SS5 Net Sales FC Shoes]]-1 -> -0.10344828 | AY7: =Table3[[#This Row],[Actual Order Book Apparel ]]/Table3[[#This Row],[Tommaso''s FC Q2 SS5 Net Sales FC Apparel]]-1 -> 1.3466465 | AZ7: =Table3[[#This Row],[Actual Order Book Shoes ]]/Table3[[#This Row],[Net Sales Invoiced Shoes]]-1 -> -0.034482759 | BA7: =IFERROR(Table3[[#This Row],[Actual Order Book Apparel ]]/Table3[[#This Row],[Net Sales Invoiced Apparel]]-1,"") -> 1.376
A8: Central | B8: Germany | C8: Field Accounts | E8: 171000 | F8: 0.103 | G8: 0.392 | H8: 0.02 | I8: 0.019 | J8: 6500 | K8: 0.174 | L8: 0.333 | M8: 0 | N8: 0.103 | P8: =IFERROR(E8/(1-F8+G8+H8-I8),0) -> 132558.14 | Q8: =IFERROR(J8/(1+L8+M8-N8-K8),0) -> 6155.303 | R8: =E8+J8 -> 177500 | S8: ='SS24 Q2 Data'!$P8+Q8 -> 138713.44 | T8: =ROUND(P8*F8,0) -> 13653 | U8: =ROUND(P8*G8,0) -> 51963 | V8: =ROUND(P8*H8,0) -> 2651 | W8: =ROUND(P8*I8,0) -> 2519 | X8: =ROUND(Q8*K8,0) -> 1071 | Y8: =ROUND(Q8*L8,0) -> 2050 | Z8: =ROUND(Q8*M8,0) -> 0 | AA8: =ROUND(Q8*M8,0) -> 0 | AB8: =J8/E8 -> 0.038011696 | AD8: =Table3[[#This Row],[Pre-Order Cancellations Mix Shoes]]+Table3[[#This Row],[Pre-Order Cancellations Mix %Apparel]] -> 14724 | AE8: =Table3[[#This Row],[Tot Cancellation]]/Table3[[#This Row],[Tot PreOrder Invoiced (units)]] -> 0.10614689 | AF8: =Table3[[#This Row],[Re-Order Rate %7]]+Table3[[#This Row],[Re-Order Rate %11]] -> 54013 | AG8: =Table3[[#This Row],[ToT Reorders]]/Table3[[#This Row],[Tot Net Sales Invoiced (units)]] -> 0.30429859 | AH8: =Table3[[#This Row],[Stock Clearance Rate %8]]+Table3[[#This Row],[Stock Clearance Rate %12]] -> 2651 | AI8: =Table3[[#This Row],[ToT Stock Clearance]]/Table3[[#This Row],[Tot PreOrder Invoiced (units)]] -> 0.019111342 | AJ8: =Table3[[#This Row],[Returns Rate %13]]+Table3[[#This Row],[Returns Rate %9]] -> 2519 | AK8: =Table3[[#This Row],[ToT Retruns]]/Table3[[#This Row],[Tot PreOrder Invoiced (units)]] -> 0.01815974 | AL8: 0.1 | AM8: 0.15 | AN8: 0.01 | AO8: 0.03 | AP8: =$AQ$2 -> 0.25 | AQ8: =IF(Table3[[#This Row],[Re-Order Rate %4]]-Table3[[#This Row],[Pre-Order Cancellations Mix %2]]-Table3[[#This Row],[Returns Rate %6]]<$AQ$1,$AQ$1,Table3[[#This Row],[Re-Order Rate %4]]-Table3[[#This Row],[Pre-Order Cancellations Mix %2]]-Table3[[#This Row],[Returns Rate %6]]) -> 0.68 | AR8: =Table3[[#This Row],[Pre-Orders Booked LYQ2 (shoes)]]*(1+Table3[[#This Row],[Re-Order Rate % FC]]+Table3[[#This Row],[Stock Clearance Rate %2]]+Table3[[#This Row],[Returns Rate %2]]-Table3[[#This Row],[FC Cancellation Mix %Shoes]]+Table3[[#This Row],[Exp Shoes PreOrder Growth Rate]]) -> 177627.91 | AS8: =Table3[[#This Row],[Tommaso''s FC Q2 SS5 Net Sales FC Shoes]]/Table3[[#This Row],[Net Sales Invoiced Shoes]]-1 -> 0.03875969 | AT8: =Table3[[#This Row],[Pre-Orders Booked LYQ2 (apparel)]]*(1+Table3[[#This Row],[Re-Order Rate % FC]]+Table3[[#This Row],[Stock Clearance Rate %2]]+Table3[[#This Row],[Returns Rate %2]]-Table3[[#This Row],[FC Cancellation Mix %Shoes]]+Table3[[#This Row],[Exp Apparel PreOrder Growth Rate]]) -> 10894.886 | AU8: =Table3[[#This Row],[Tommaso''s FC Q2 SS5 Net Sales FC Apparel]]/Table3[[#This Row],[Net Sales Invoiced Apparel]]-1 -> 0.67613636 | AV8: 115000 | AW8: 20342 | AX8: =Table3[[#This Row],[Actual Order Book Shoes ]]/Table3[[#This Row],[Tommaso''s FC Q2 SS5 Net Sales FC Shoes]]-1 -> -0.35257921 | AY8: =Table3[[#This Row],[Actual Order Book Apparel ]]/Table3[[#This Row],[Tommaso''s FC Q2 SS5 Net Sales FC Apparel]]-1 -> 0.86711447 | AZ8: =Table3[[#This Row],[Actual Order Book Shoes ]]/Table3[[#This Row],[Net Sales Invoiced Shoes]]-1 -> -0.32748538 | BA8: =IFERROR(Table3[[#This Row],[Actual Order Book Apparel ]]/Table3[[#This Row],[Net Sales Invoiced Apparel]]-1,"") -> 2.1295385
A9: North | B9: United Kingdom | C9: Field Accounts | E9: 53300 | F9: 0.107 | G9: 0.189 | H9: 0 | I9: 0.094 | J9: 6100 | K9: 0.081 | L9: 0.15 | M9: 0 | N9: 0.033 | P9: =IFERROR(E9/(1-F9+G9+H9-I9),0) -> 53947.368 | Q9: =IFERROR(J9/(1+L9+M9-N9-K9),0) -> 5888.0309 | R9: =E9+J9 -> 59400 | S9: ='SS24 Q2 Data'!$P10+Q9 -> 35152.625 | T9: =ROUND(P9*F9,0) -> 5772 | U9: =ROUND(P9*G9,0) -> 10196 | V9: =ROUND(P9*H9,0) -> 0 | W9: =ROUND(P9*I9,0) -> 5071 | X9: =ROUND(Q9*K9,0) -> 477 | Y9: =ROUND(Q9*L9,0) -> 883 | Z9: =ROUND(Q9*M9,0) -> 0 | AA9: =ROUND(Q9*M9,0) -> 0 | AB9: =J9/E9 -> 0.11444653 | AD9: =Table3[[#This Row],[Pre-Order Cancellations Mix Shoes]]+Table3[[#This Row],[Pre-Order Cancellations Mix %Apparel]] -> 6249 | AE9: =Table3[[#This Row],[Tot Cancellation]]/Table3[[#This Row],[Tot PreOrder Invoiced (units)]] -> 0.17776766 | AF9: =Table3[[#This Row],[Re-Order Rate %7]]+Table3[[#This Row],[Re-Order Rate %11]] -> 11079 | AG9: =Table3[[#This Row],[ToT Reorders]]/Table3[[#This Row],[Tot Net Sales Invoiced (units)]] -> 0.18651515 | AH9: =Table3[[#This Row],[Stock Clearance Rate %8]]+Table3[[#This Row],[Stock Clearance Rate %12]] -> 0 | AI9: =Table3[[#This Row],[ToT Stock Clearance]]/Table3[[#This Row],[Tot PreOrder Invoiced (units)]] -> 0 | AJ9: =Table3[[#This Row],[Returns Rate %13]]+Table3[[#This Row],[Returns Rate %9]] -> 5071 | AK9: =Table3[[#This Row],[ToT Retruns]]/Table3[[#This Row],[Tot PreOrder Invoiced (units)]] -> 0.14425665 | AL9: 0.1 | AM9: 0.15 | AN9: 0.01 | AO9: 0.03 | AP9: =$AQ$2 -> 0.25 | AQ9: =IF(Table3[[#This Row],[Re-Order Rate %4]]-Table3[[#This Row],[Pre-Order Cancellations Mix %2]]-Table3[[#This Row],[Returns Rate %6]]<$AQ$1,$AQ$1,Table3[[#This Row],[Re-Order Rate %4]]-Table3[[#This Row],[Pre-Order Cancellations Mix %2]]-Table3[[#This Row],[Returns Rate %6]]) -> 0.68 | AR9: =Table3[[#This Row],[Pre-Orders Booked LYQ2 (shoes)]]*(1+Table3[[#This Row],[Re-Order Rate % FC]]+Table3[[#This Row],[Stock Clearance Rate %2]]+Table3[[#This Row],[Returns Rate %2]]-Table3[[#This Row],[FC Cancellation Mix %Shoes]]+Table3[[#This Row],[Exp Shoes PreOrder Growth Rate]]) -> 72289.474 | AS9: =Table3[[#This Row],[Tommaso''s FC Q2 SS5 Net Sales FC Shoes]]/Table3[[#This Row],[Net Sales Invoiced Shoes]]-1 -> 0.3562753 | AT9: =Table3[[#This Row],[Pre-Orders Booked LYQ2 (apparel)]]*(1+Table3[[#This Row],[Re-Order Rate % FC]]+Table3[[#This Row],[Stock Clearance Rate %2]]+Table3[[#This Row],[Returns Rate %2]]-Table3[[#This Row],[FC Cancellation Mix %Shoes]]+Table3[[#This Row],[Exp Apparel PreOrder Growth Rate]]) -> 10421.815 | AU9: =Table3[[#This Row],[Tommaso''s FC Q2 SS5 Net Sales FC Apparel]]/Table3[[#This Row],[Net Sales Invoiced Apparel]]-1 -> 0.70849421 | AV9: 30700 | AW9: 1231 | AX9: =Table3[[#This Row],[Actual Order Book Shoes ]]/Table3[[#This Row],[Tommaso''s FC Q2 SS5 Net Sales FC Shoes]]-1 -> -0.57531853 | AY9: =Table3[[#This Row],[Actual Order Book Apparel ]]/Table3[[#This Row],[Tommaso''s FC Q2 SS5 Net Sales FC Apparel]]-1 -> -0.88188237 | AZ9: =Table3[[#This Row],[Actual Order Book Shoes ]]/Table3[[#This Row],[Net Sales Invoiced Shoes]]-1 -> -0.42401501 | BA9: =IFERROR(Table3[[#This Row],[Actual Order Book Apparel ]]/Table3[[#This Row],[Net Sales Invoiced Apparel]]-1,"") -> -0.79819672
A10: Central | B10: Austria | C10: Field Accounts | E10: 38600 | F10: 0.035 | G10: 0.363 | H10: 0.004 | I10: 0.013 | J10: 3500 | K10: 0.059 | L10: 0.259 | M10: 0.051 | N10: 0.029 | P10: =IFERROR(E10/(1-F10+G10+H10-I10),0) -> 29264.594 | Q10: =IFERROR(J10/(1+L10+M10-N10-K10),0) -> 2864.1571 | R10: =E10+J10 -> 42100 | S10: ='SS24 Q2 Data'!$P11+Q10 -> 29099.251 | T10: =ROUND(P10*F10,0) -> 1024 | U10: =ROUND(P10*G10,0) -> 10623 | V10: =ROUND(P10*H10,0) -> 117 | W10: =ROUND(P10*I10,0) -> 380 | X10: =ROUND(Q10*K10,0) -> 169 | Y10: =ROUND(Q10*L10,0) -> 742 | Z10: =ROUND(Q10*M10,0) -> 146 | AA10: =ROUND(Q10*M10,0) -> 146 | AB10: =J10/E10 -> 0.090673575 | AD10: =Table3[[#This Row],[Pre-Order Cancellations Mix Shoes]]+Table3[[#This Row],[Pre-Order Cancellations Mix %Apparel]] -> 1193 | AE10: =Table3[[#This Row],[Tot Cancellation]]/Table3[[#This Row],[Tot PreOrder Invoiced (units)]] -> 0.040997619 | AF10: =Table3[[#This Row],[Re-Order Rate %7]]+Table3[[#This Row],[Re-Order Rate %11]] -> 11365 | AG10: =Table3[[#This Row],[ToT Reorders]]/Table3[[#This Row],[Tot Net Sales Invoiced (units)]] -> 0.26995249 | AH10: =Table3[[#This Row],[Stock Clearance Rate %8]]+Table3[[#This Row],[Stock Clearance Rate %12]] -> 263 | AI10: =Table3[[#This Row],[ToT Stock Clearance]]/Table3[[#This Row],[Tot PreOrder Invoiced (units)]] -> 0.0090380334 | AJ10: =Table3[[#This Row],[Returns Rate %13]]+Table3[[#This Row],[Returns Rate %9]] -> 526 | AK10: =Table3[[#This Row],[ToT Retruns]]/Table3[[#This Row],[Tot PreOrder Invoiced (units)]] -> 0.018076067 | AL10: 0.1 | AM10: 0.15 | AN10: 0.01 | AO10: 0.03 | AP10: =$AQ$2 -> 0.25 | AQ10: =IF(Table3[[#This Row],[Re-Order Rate %4]]-Table3[[#This Row],[Pre-Order Cancellations Mix %2]]-Table3[[#This Row],[Returns Rate %6]]<$AQ$1,$AQ$1,Table3[[#This Row],[Re-Order Rate %4]]-Table3[[#This Row],[Pre-Order Cancellations Mix %2]]-Table3[[#This Row],[Returns Rate %6]]) -> 0.68 | AR10: =Table3[[#This Row],[Pre-Orders Booked LYQ2 (shoes)]]*(1+Table3[[#This Row],[Re-Order Rate % FC]]+Table3[[#This Row],[Stock Clearance Rate %2]]+Table3[[#This Row],[Returns Rate %2]]-Table3[[#This Row],[FC Cancellation Mix %Shoes]]+Table3[[#This Row],[Exp Shoes PreOrder Growth Rate]]) -> 39214.556 | AS10: =Table3[[#This Row],[Tommaso''s FC Q2 SS5 Net Sales FC Shoes]]/Table3[[#This Row],[Net Sales Invoiced Shoes]]-1 -> 0.015921152 | AT10: =Table3[[#This Row],[Pre-Orders Booked LYQ2 (apparel)]]*(1+Table3[[#This Row],[Re-Order Rate % FC]]+Table3[[#This Row],[Stock Clearance Rate %2]]+Table3[[#This Row],[Returns Rate %2]]-Table3[[#This Row],[FC Cancellation Mix %Shoes]]+Table3[[#This Row],[Exp Apparel PreOrder Growth Rate]]) -> 5069.5581 | AU10: =Table3[[#This Row],[Tommaso''s FC Q2 SS5 Net Sales FC Apparel]]/Table3[[#This Row],[Net Sales Invoiced Apparel]]-1 -> 0.44844517 | AV10: 24900 | AW10: 2435 | AX10: =Table3[[#This Row],[Actual Order Book Shoes ]]/Table3[[#This Row],[Tommaso''s FC Q2 SS5 Net Sales FC Shoes]]-1 -> -0.36503171 | AY10: =Table3[[#This Row],[Actual Order Book Apparel ]]/Table3[[#This Row],[Tommaso''s FC Q2 SS5 Net Sales FC Apparel]]-1 -> -0.519682 | AZ10: =Table3[[#This Row],[Actual Order Book Shoes ]]/Table3[[#This Row],[Net Sales Invoiced Shoes]]-1 -> -0.35492228 | BA10: =IFERROR(Table3[[#This Row],[Actual Order Book Apparel ]]/Table3[[#This Row],[Net Sales Invoiced Apparel]]-1,"") -> -0.30428571
A11: South | B11: Spain | C11: Field Accounts | E11: 30800 | F11: 0.092 | G11: 0.308 | H11: 0 | I11: 0.042 | J11: 2500 | K11: 0.042 | L11: 0.615 | M11: 0 | N11: 0.017 | P11: =IFERROR(E11/(1-F11+G11+H11-I11),0) -> 26235.094 | Q11: =IFERROR(J11/(1+L11+M11-N11-K11),0) -> 1606.6838 | R11: =E11+J11 -> 33300 | S11: ='SS24 Q2 Data'!$P14+Q11 -> 5391.6952 | T11: =ROUND(P11*F11,0) -> 2414 | U11: =ROUND(P11*G11,0) -> 8080 | V11: =ROUND(P11*H11,0) -> 0 | W11: =ROUND(P11*I11,0) -> 1102 | X11: =ROUND(Q11*K11,0) -> 67 | Y11: =ROUND(Q11*L11,0) -> 988 | Z11: =ROUND(Q11*M11,0) -> 0 | AA11: =ROUND(Q11*M11,0) -> 0 | AB11: =J11/E11 -> 0.081168831 | AD11: =Table3[[#This Row],[Pre-Order Cancellations Mix Shoes]]+Table3[[#This Row],[Pre-Order Cancellations Mix %Apparel]] -> 2481 | AE11: =Table3[[#This Row],[Tot Cancellation]]/Table3[[#This Row],[Tot PreOrder Invoiced (units)]] -> 0.46015213 | AF11: =Table3[[#This Row],[Re-Order Rate %7]]+Table3[[#This Row],[Re-Order Rate %11]] -> 9068 | AG11: =Table3[[#This Row],[ToT Reorders]]/Table3[[#This Row],[Tot Net Sales Invoiced (units)]] -> 0.27231231 | AH11: =Table3[[#This Row],[Stock Clearance Rate %8]]+Table3[[#This Row],[Stock Clearance Rate %12]] -> 0 | AI11: =Table3[[#This Row],[ToT Stock Clearance]]/Table3[[#This Row],[Tot PreOrder Invoiced (units)]] -> 0 | AJ11: =Table3[[#This Row],[Returns Rate %13]]+Table3[[#This Row],[Returns Rate %9]] -> 1102 | AK11: =Table3[[#This Row],[ToT Retruns]]/Table3[[#This Row],[Tot PreOrder Invoiced (units)]] -> 0.20438841 | AL11: 0.1 | AM11: 0.15 | AN11: 0.01 | AO11: 0.03 | AP11: =$AQ$2 -> 0.25 | AQ11: =IF(Table3[[#This Row],[Re-Order Rate %4]]-Table3[[#This Row],[Pre-Order Cancellations Mix %2]]-Table3[[#This Row],[Returns Rate %6]]<$AQ$1,$AQ$1,Table3[[#This Row],[Re-Order Rate %4]]-Table3[[#This Row],[Pre-Order Cancellations Mix %2]]-Table3[[#This Row],[Returns Rate %6]]) -> 0.68 | AR11: =Table3[[#This Row],[Pre-Orders Booked LYQ2 (shoes)]]*(1+Table3[[#This Row],[Re-Order Rate % FC]]+Table3[[#This Row],[Stock Clearance Rate %2]]+Table3[[#This Row],[Returns Rate %2]]-Table3[[#This Row],[FC Cancellation Mix %Shoes]]+Table3[[#This Row],[Exp Shoes PreOrder Growth Rate]]) -> 35155.026 | AS11: =Table3[[#This Row],[Tommaso''s FC Q2 SS5 Net Sales FC Shoes]]/Table3[[#This Row],[Net Sales Invoiced Shoes]]-1 -> 0.14139693 | AT11: =Table3[[#This Row],[Pre-Orders Booked LYQ2 (apparel)]]*(1+Table3[[#This Row],[Re-Order Rate % FC]]+Table3[[#This Row],[Stock Clearance Rate %2]]+Table3[[#This Row],[Returns Rate %2]]-Table3[[#This Row],[FC Cancellation Mix %Shoes]]+Table3[[#This Row],[Exp Apparel PreOrder Growth Rate]]) -> 2843.8303 | AU11: =Table3[[#This Row],[Tommaso''s FC Q2 SS5 Net Sales FC Apparel]]/Table3[[#This Row],[Net Sales Invoiced Apparel]]-1 -> 0.13753213 | AV11: 20200 | AW11: 1675 | AX11: =Table3[[#This Row],[Actual Order Book Shoes ]]/Table3[[#This Row],[Tommaso''s FC Q2 SS5 Net Sales FC Shoes]]-1 -> -0.42540221 | AY11: =Table3[[#This Row],[Actual Order Book Apparel ]]/Table3[[#This Row],[Tommaso''s FC Q2 SS5 Net Sales FC Apparel]]-1 -> -0.41100565 | AZ11: =Table3[[#This Row],[Actual Order Book Shoes ]]/Table3[[#This Row],[Net Sales Invoiced Shoes]]-1 -> -0.34415584 | BA11: =IFERROR(Table3[[#This Row],[Actual Order Book Apparel ]]/Table3[[#This Row],[Net Sales Invoiced Apparel]]-1,"") -> -0.33
A12: North | B12: France | C12: Field Accounts | E12: 22800 | F12: 0.134 | G12: 0.451 | H12: 0 | I12: 0.064 | J12: 3800 | K12: 0.105 | L12: 0.159 | M12: 0 | N12: 0.04 | P12: =IFERROR(E12/(1-F12+G12+H12-I12),0) -> 18196.329 | Q12: =IFERROR(J12/(1+L12+M12-N12-K12),0) -> 3747.5345 | R12: =E12+J12 -> 26600 | S12: ='SS24 Q2 Data'!$P16+Q12 -> 93973.098 | T12: =ROUND(P12*F12,0) -> 2438 | U12: =ROUND(P12*G12,0) -> 8207 | V12: =ROUND(P12*H12,0) -> 0 | W12: =ROUND(P12*I12,0) -> 1165 | X12: =ROUND(Q12*K12,0) -> 393 | Y12: =ROUND(Q12*L12,0) -> 596 | Z12: =ROUND(Q12*M12,0) -> 0 | AA12: =ROUND(Q12*M12,0) -> 0 | AB12: =J12/E12 -> 0.16666667 | AD12: =Table3[[#This Row],[Pre-Order Cancellations Mix Shoes]]+Table3[[#This Row],[Pre-Order Cancellations Mix %Apparel]] -> 2831 | AE12: =Table3[[#This Row],[Tot Cancellation]]/Table3[[#This Row],[Tot PreOrder Invoiced (units)]] -> 0.030125643 | AF12: =Table3[[#This Row],[Re-Order Rate %7]]+Table3[[#This Row],[Re-Order Rate %11]] -> 8803 | AG12: =Table3[[#This Row],[ToT Reorders]]/Table3[[#This Row],[Tot Net Sales Invoiced (units)]] -> 0.33093985 | AH12: =Table3[[#This Row],[Stock Clearance Rate %8]]+Table3[[#This Row],[Stock Clearance Rate %12]] -> 0 | AI12: =Table3[[#This Row],[ToT Stock Clearance]]/Table3[[#This Row],[Tot PreOrder Invoiced (units)]] -> 0 | AJ12: =Table3[[#This Row],[Returns Rate %13]]+Table3[[#This Row],[Returns Rate %9]] -> 1165 | AK12: =Table3[[#This Row],[ToT Retruns]]/Table3[[#This Row],[Tot PreOrder Invoiced (units)]] -> 0.012397165 | AL12: 0.1 | AM12: 0.15 | AN12: 0.01 | AO12: 0.03 | AP12: =$AQ$2 -> 0.25 | AQ12: =IF(Table3[[#This Row],[Re-Order Rate %4]]-Table3[[#This Row],[Pre-Order Cancellations Mix %2]]-Table3[[#This Row],[Returns Rate %6]]<$AQ$1,$AQ$1,Table3[[#This Row],[Re-Order Rate %4]]-Table3[[#This Row],[Pre-Order Cancellations Mix %2]]-Table3[[#This Row],[Returns Rate %6]]) -> 0.68 | AR12: =Table3[[#This Row],[Pre-Orders Booked LYQ2 (shoes)]]*(1+Table3[[#This Row],[Re-Order Rate % FC]]+Table3[[#This Row],[Stock Clearance Rate %2]]+Table3[[#This Row],[Returns Rate %2]]-Table3[[#This Row],[FC Cancellation Mix %Shoes]]+Table3[[#This Row],[Exp Shoes PreOrder Growth Rate]]) -> 24383.081 | AS12: =Table3[[#This Row],[Tommaso''s FC Q2 SS5 Net Sales FC Shoes]]/Table3[[#This Row],[Net Sales Invoiced Shoes]]-1 -> 0.06943336 | AT12: =Table3[[#This Row],[Pre-Orders Booked LYQ2 (apparel)]]*(1+Table3[[#This Row],[Re-Order Rate % FC]]+Table3[[#This Row],[Stock Clearance Rate %2]]+Table3[[#This Row],[Returns Rate %2]]-Table3[[#This Row],[FC Cancellation Mix %Shoes]]+Table3[[#This Row],[Exp Apparel PreOrder Growth Rate]]) -> 6633.1361 | AU12: =Table3[[#This Row],[Tommaso''s FC Q2 SS5 Net Sales FC Apparel]]/Table3[[#This Row],[Net Sales Invoiced Apparel]]-1 -> 0.74556213 | AV12: 21000 | AW12: 1238 | AX12: =Table3[[#This Row],[Actual Order Book Shoes ]]/Table3[[#This Row],[Tommaso''s FC Q2 SS5 Net Sales FC Shoes]]-1 -> -0.13874705 | AY12: =Table3[[#This Row],[Actual Order Book Apparel ]]/Table3[[#This Row],[Tommaso''s FC Q2 SS5 Net Sales FC Apparel]]-1 -> -0.81336128 | AZ12: =Table3[[#This Row],[Actual Order Book Shoes ]]/Table3[[#This Row],[Net Sales Invoiced Shoes]]-1 -> -0.078947368 | BA12: =IFERROR(Table3[[#This Row],[Actual Order Book Apparel ]]/Table3[[#This Row],[Net Sales Invoiced Apparel]]-1,"") -> -0.67421053
A13: Central | B13: Switzerland | C13: Field Accounts | E13: 9000 | F13: 0.138 | G13: 0.689 | H13: 0 | I13: 0.118 | J13: 3600 | K13: 0.071 | L13: 0.963 | M13: 0 | N13: 0.111 | P13: =IFERROR(E13/(1-F13+G13+H13-I13),0) -> 6280.5304 | Q13: =IFERROR(J13/(1+L13+M13-N13-K13),0) -> 2021.3363 | R13: =E13+J13 -> 12600 | S13: ='SS24 Q2 Data'!$P19+Q13 -> 8814.5431 | T13: =ROUND(P13*F13,0) -> 867 | U13: =ROUND(P13*G13,0) -> 4327 | V13: =ROUND(P13*H13,0) -> 0 | W13: =ROUND(P13*I13,0) -> 741 | X13: =ROUND(Q13*K13,0) -> 144 | Y13: =ROUND(Q13*L13,0) -> 1947 | Z13: =ROUND(Q13*M13,0) -> 0 | AA13: =ROUND(Q13*M13,0) -> 0 | AB13: =J13/E13 -> 0.4 | AD13: =Table3[[#This Row],[Pre-Order Cancellations Mix Shoes]]+Table3[[#This Row],[Pre-Order Cancellations Mix %Apparel]] -> 1011 | AE13: =Table3[[#This Row],[Tot Cancellation]]/Table3[[#This Row],[Tot PreOrder Invoiced (units)]] -> 0.11469681 | AF13: =Table3[[#This Row],[Re-Order Rate %7]]+Table3[[#This Row],[Re-Order Rate %11]] -> 6274 | AG13: =Table3[[#This Row],[ToT Reorders]]/Table3[[#This Row],[Tot Net Sales Invoiced (units)]] -> 0.49793651 | AH13: =Table3[[#This Row],[Stock Clearance Rate %8]]+Table3[[#This Row],[Stock Clearance Rate %12]] -> 0 | AI13: =Table3[[#This Row],[ToT Stock Clearance]]/Table3[[#This Row],[Tot PreOrder Invoiced (units)]] -> 0 | AJ13: =Table3[[#This Row],[Returns Rate %13]]+Table3[[#This Row],[Returns Rate %9]] -> 741 | AK13: =Table3[[#This Row],[ToT Retruns]]/Table3[[#This Row],[Tot PreOrder Invoiced (units)]] -> 0.084065616 | AL13: 0.1 | AM13: 0.15 | AN13: 0.01 | AO13: 0.03 | AP13: =$AQ$2 -> 0.25 | AQ13: =IF(Table3[[#This Row],[Re-Order Rate %4]]-Table3[[#This Row],[Pre-Order Cancellations Mix %2]]-Table3[[#This Row],[Returns Rate %6]]<$AQ$1,$AQ$1,Table3[[#This Row],[Re-Order Rate %4]]-Table3[[#This Row],[Pre-Order Cancellations Mix %2]]-Table3[[#This Row],[Returns Rate %6]]) -> 0.781 | AR13: =Table3[[#This Row],[Pre-Orders Booked LYQ2 (shoes)]]*(1+Table3[[#This Row],[Re-Order Rate % FC]]+Table3[[#This Row],[Stock Clearance Rate %2]]+Table3[[#This Row],[Returns Rate %2]]-Table3[[#This Row],[FC Cancellation Mix %Shoes]]+Table3[[#This Row],[Exp Shoes PreOrder Growth Rate]]) -> 8415.9107 | AS13: =Table3[[#This Row],[Tommaso''s FC Q2 SS5 Net Sales FC Shoes]]/Table3[[#This Row],[Net Sales Invoiced Shoes]]-1 -> -0.064898814 | AT13: =Table3[[#This Row],[Pre-Orders Booked LYQ2 (apparel)]]*(1+Table3[[#This Row],[Re-Order Rate % FC]]+Table3[[#This Row],[Stock Clearance Rate %2]]+Table3[[#This Row],[Returns Rate %2]]-Table3[[#This Row],[FC Cancellation Mix %Shoes]]+Table3[[#This Row],[Exp Apparel PreOrder Growth Rate]]) -> 3781.9203 | AU13: =Table3[[#This Row],[Tommaso''s FC Q2 SS5 Net Sales FC Apparel]]/Table3[[#This Row],[Net Sales Invoiced Apparel]]-1 -> 0.050533408 | AV13: 8700 | AW13: 30324 | AX13: =Table3[[#This Row],[Actual Order Book Shoes ]]/Table3[[#This Row],[Tommaso''s FC Q2 SS5 Net Sales FC Shoes]]-1 -> 0.033756219 | AY13: =Table3[[#This Row],[Actual Order Book Apparel ]]/Table3[[#This Row],[Tommaso''s FC Q2 SS5 Net Sales FC Apparel]]-1 -> 7.0181489 | AZ13: =Table3[[#This Row],[Actual Order Book Shoes ]]/Table3[[#This Row],[Net Sales Invoiced Shoes]]-1 -> -0.033333333 | BA13: =IFERROR(Table3[[#This Row],[Actual Order Book Apparel ]]/Table3[[#This Row],[Net Sales Invoiced Apparel]]-1,"") -> 7.4233333
A14: North | B14: Nordics | C14: Field Accounts | E14: 5000 | F14: 0.13 | G14: 0.453 | H14: 0 | I14: 0.002 | J14: 400 | K14: 0.09 | L14: 0.106 | M14: 0 | N14: 0 | P14: =IFERROR(E14/(1-F14+G14+H14-I14),0) -> 3785.0114 | Q14: =IFERROR(J14/(1+L14+M14-N14-K14),0) -> 393.70079 | R14: =E14+J14 -> 5400 | S14: ='SS24 Q2 Data'!$P22+Q14 -> 1036.7876 | T14: =ROUND(P14*F14,0) -> 492 | U14: =ROUND(P14*G14,0) -> 1715 | V14: =ROUND(P14*H14,0) -> 0 | W14: =ROUND(P14*I14,0) -> 8 | X14: =ROUND(Q14*K14,0) -> 35 | Y14: =ROUND(Q14*L14,0) -> 42 | Z14: =ROUND(Q14*M14,0) -> 0 | AA14: =ROUND(Q14*M14,0) -> 0 | AB14: =J14/E14 -> 0.08 | AD14: =Table3[[#This Row],[Pre-Order Cancellations Mix Shoes]]+Table3[[#This Row],[Pre-Order Cancellations Mix %Apparel]] -> 527 | AE14: =Table3[[#This Row],[Tot Cancellation]]/Table3[[#This Row],[Tot PreOrder Invoiced (units)]] -> 0.50830083 | AF14: =Table3[[#This Row],[Re-Order Rate %7]]+Table3[[#This Row],[Re-Order Rate %11]] -> 1757 | AG14: =Table3[[#This Row],[ToT Reorders]]/Table3[[#This Row],[Tot Net Sales Invoiced (units)]] -> 0.32537037 | AH14: =Table3[[#This Row],[Stock Clearance Rate %8]]+Table3[[#This Row],[Stock Clearance Rate %12]] -> 0 | AI14: =Table3[[#This Row],[ToT Stock Clearance]]/Table3[[#This Row],[Tot PreOrder Invoiced (units)]] -> 0 | AJ14: =Table3[[#This Row],[Returns Rate %13]]+Table3[[#This Row],[Returns Rate %9]] -> 8 | AK14: =Table3[[#This Row],[ToT Retruns]]/Table3[[#This Row],[Tot PreOrder Invoiced (units)]] -> 0.0077161416 | AL14: 0.1 | AM14: 0.15 | AN14: 0.01 | AO14: 0.03 | AP14: =$AQ$2 -> 0.25 | AQ14: =IF(Table3[[#This Row],[Re-Order Rate %4]]-Table3[[#This Row],[Pre-Order Cancellations Mix %2]]-Table3[[#This Row],[Returns Rate %6]]<$AQ$1,$AQ$1,Table3[[#This Row],[Re-Order Rate %4]]-Table3[[#This Row],[Pre-Order Cancellations Mix %2]]-Table3[[#This Row],[Returns Rate %6]]) -> 0.68 | AR14: =Table3[[#This Row],[Pre-Orders Booked LYQ2 (shoes)]]*(1+Table3[[#This Row],[Re-Order Rate % FC]]+Table3[[#This Row],[Stock Clearance Rate %2]]+Table3[[#This Row],[Returns Rate %2]]-Table3[[#This Row],[FC Cancellation Mix %Shoes]]+Table3[[#This Row],[Exp Shoes PreOrder Growth Rate]]) -> 5071.9152 | AS14: =Table3[[#This Row],[Tommaso''s FC Q2 SS5 Net Sales FC Shoes]]/Table3[[#This Row],[Net Sales Invoiced Shoes]]-1 -> 0.014383043 | AT14: =Table3[[#This Row],[Pre-Orders Booked LYQ2 (apparel)]]*(1+Table3[[#This Row],[Re-Order Rate % FC]]+Table3[[#This Row],[Stock Clearance Rate %2]]+Table3[[#This Row],[Returns Rate %2]]-Table3[[#This Row],[FC Cancellation Mix %Shoes]]+Table3[[#This Row],[Exp Apparel PreOrder Growth Rate]]) -> 696.85039 | AU14: =Table3[[#This Row],[Tommaso''s FC Q2 SS5 Net Sales FC Apparel]]/Table3[[#This Row],[Net Sales Invoiced Apparel]]-1 -> 0.74212598 | AV14: 2200 | AW14: 2345 | AX14: =Table3[[#This Row],[Actual Order Book Shoes ]]/Table3[[#This Row],[Tommaso''s FC Q2 SS5 Net Sales FC Shoes]]-1 -> -0.56623881 | AY14: =Table3[[#This Row],[Actual Order Book Apparel ]]/Table3[[#This Row],[Tommaso''s FC Q2 SS5 Net Sales FC Apparel]]-1 -> 2.3651412 | AZ14: =Table3[[#This Row],[Actual Order Book Shoes ]]/Table3[[#This Row],[Net Sales Invoiced Shoes]]-1 -> -0.56 | BA14: =IFERROR(Table3[[#This Row],[Actual Order Book Apparel ]]/Table3[[#This Row],[Net Sales Invoiced Apparel]]-1,"") -> 4.8625
A15: South | B15: Italy | C15: Field Accounts | E15: 3000 | F15: 0.122 | G15: 1.892 | H15: 0 | I15: 1 | J15: 0 | K15: 1 | L15: 0 | M15: 0 | N15: 0 | P15: =IFERROR(E15/(1-F15+G15+H15-I15),0) -> 1694.9153 | Q15: =IFERROR(J15/(1+L15+M15-N15-K15),0) -> 0 | R15: =E15+J15 -> 3000 | S15: ='SS24 Q2 Data'!$P23+Q15 -> 417.05283 | T15: =ROUND(P15*F15,0) -> 207 | U15: =ROUND(P15*G15,0) -> 3207 | V15: =ROUND(P15*H15,0) -> 0 | W15: =ROUND(P15*I15,0) -> 1695 | X15: =ROUND(Q15*K15,0) -> 0 | Y15: =ROUND(Q15*L15,0) -> 0 | Z15: =ROUND(Q15*M15,0) -> 0 | AA15: =ROUND(Q15*M15,0) -> 0 | AB15: =J15/E15 -> 0 | AD15: =Table3[[#This Row],[Pre-Order Cancellations Mix Shoes]]+Table3[[#This Row],[Pre-Order Cancellations Mix %Apparel]] -> 207 | AE15: =Table3[[#This Row],[Tot Cancellation]]/Table3[[#This Row],[Tot PreOrder Invoiced (units)]] -> 0.49634 | AF15: =Table3[[#This Row],[Re-Order Rate %7]]+Table3[[#This Row],[Re-Order Rate %11]] -> 3207 | AG15: =Table3[[#This Row],[ToT Reorders]]/Table3[[#This Row],[Tot Net Sales Invoiced (units)]] -> 1.069 | AH15: =Table3[[#This Row],[Stock Clearance Rate %8]]+Table3[[#This Row],[Stock Clearance Rate %12]] -> 0 | AI15: =Table3[[#This Row],[ToT Stock Clearance]]/Table3[[#This Row],[Tot PreOrder Invoiced (units)]] -> 0 | AJ15: =Table3[[#This Row],[Returns Rate %13]]+Table3[[#This Row],[Returns Rate %9]] -> 1695 | AK15: =Table3[[#This Row],[ToT Retruns]]/Table3[[#This Row],[Tot PreOrder Invoiced (units)]] -> 4.0642333 | AL15: 0.1 | AM15: 0.15 | AN15: 0.01 | AO15: 0.03 | AP15: =$AQ$2 -> 0.25 | AQ15: NA | AR15: =Table3[[#This Row],[Pre-Orders Booked LYQ2 (shoes)]]*(1+Table3[[#This Row],[Re-Order Rate % FC]]+Table3[[#This Row],[Stock Clearance Rate %2]]+Table3[[#This Row],[Returns Rate %2]]-Table3[[#This Row],[FC Cancellation Mix %Shoes]]+Table3[[#This Row],[Exp Shoes PreOrder Growth Rate]]) -> 2271.1864 | AS15: =Table3[[#This Row],[Tommaso''s FC Q2 SS5 Net Sales FC Shoes]]/Table3[[#This Row],[Net Sales Invoiced Shoes]]-1 -> -0.24293785 | AT15: 500 | AU15: NA | AV15: 3300 | AW15: 345 | AX15: =Table3[[#This Row],[Actual Order Book Shoes ]]/Table3[[#This Row],[Tommaso''s FC Q2 SS5 Net Sales FC Shoes]]-1 -> 0.45298507 | AY15: =Table3[[#This Row],[Actual Order Book Apparel ]]/Table3[[#This Row],[Tommaso''s FC Q2 SS5 Net Sales FC Apparel]]-1 -> -0.31 | AZ15: =Table3[[#This Row],[Actual Order Book Shoes ]]/Table3[[#This Row],[Net Sales Invoiced Shoes]]-1 -> 0.1 | BA15: =IFERROR(Table3[[#This Row],[Actual Order Book Apparel ]]/Table3[[#This Row],[Net Sales Invoiced Apparel]]-1,"")
A16: North | B16: United Kingdom | C16: Titan Sport | D16: Monitor | E16: 36000 | F16: 0.553 | G16: 0 | H16: 0 | I16: 0.048 | J16: 2700 | K16: 0.655 | L16: 0 | M16: 0 | N16: 0.096 | P16: =IFERROR(E16/(1-F16+G16+H16-I16),0) -> 90225.564 | Q16: =IFERROR(J16/(1+L16+M16-N16-K16),0) -> 10843.373 | R16: =E16+J16 -> 38700 | S16: ='SS24 Q2 Data'!$P12+Q16 -> 29039.702 | T16: =ROUND(P16*F16,0) -> 49895 | U16: =ROUND(P16*G16,0) -> 0 | V16: =ROUND(P16*H16,0) -> 0 | W16: =ROUND(P16*I16,0) -> 4331 | X16: =ROUND(Q16*K16,0) -> 7102 | Y16: =ROUND(Q16*L16,0) -> 0 | Z16: =ROUND(Q16*M16,0) -> 0 | AA16: =ROUND(Q16*M16,0) -> 0 | AB16: =J16/E16 -> 0.075 | AD16: =Table3[[#This Row],[Pre-Order Cancellations Mix Shoes]]+Table3[[#This Row],[Pre-Order Cancellations Mix %Apparel]] -> 56997 | AE16: =Table3[[#This Row],[Tot Cancellation]]/Table3[[#This Row],[Tot PreOrder Invoiced (units)]] -> 1.9627267 | AF16: =Table3[[#This Row],[Re-Order Rate %7]]+Table3[[#This Row],[Re-Order Rate %11]] -> 0 | AG16: =Table3[[#This Row],[ToT Reorders]]/Table3[[#This Row],[Tot Net Sales Invoiced (units)]] -> 0 | AH16: =Table3[[#This Row],[Stock Clearance Rate %8]]+Table3[[#This Row],[Stock Clearance Rate %12]] -> 0 | AI16: =Table3[[#This Row],[ToT Stock Clearance]]/Table3[[#This Row],[Tot PreOrder Invoiced (units)]] -> 0 | AJ16: =Table3[[#This Row],[Returns Rate %13]]+Table3[[#This Row],[Returns Rate %9]] -> 4331 | AK16: =Table3[[#This Row],[ToT Retruns]]/Table3[[#This Row],[Tot PreOrder Invoiced (units)]] -> 0.14914065 | AL16: 0.06 | AM16: 0.15 | AN16: 0.01 | AO16: 0.03 | AP16: 0.1 | AQ16: 0.1 | AR16: =Table3[[#This Row],[Pre-Orders Booked LYQ2 (shoes)]]*(1+Table3[[#This Row],[Re-Order Rate % FC]]+Table3[[#This Row],[Stock Clearance Rate %2]]+Table3[[#This Row],[Returns Rate %2]]-Table3[[#This Row],[FC Cancellation Mix %Shoes]]+Table3[[#This Row],[Exp Shoes PreOrder Growth Rate]]) -> 110977.44 | AS16: =Table3[[#This Row],[Tommaso''s FC Q2 SS5 Net Sales FC Shoes]]/Table3[[#This Row],[Net Sales Invoiced Shoes]]-1 -> 2.0827068 | AT16: =Table3[[#This Row],[Pre-Orders Booked LYQ2 (apparel)]]*(1+Table3[[#This Row],[Re-Order Rate % FC]]+Table3[[#This Row],[Stock Clearance Rate %2]]+Table3[[#This Row],[Returns Rate %2]]-Table3[[#This Row],[FC Cancellation Mix %Shoes]]+Table3[[#This Row],[Exp Apparel PreOrder Growth Rate]]) -> 13337.349 | AU16: =Table3[[#This Row],[Tommaso''s FC Q2 SS5 Net Sales FC Apparel]]/Table3[[#This Row],[Net Sales Invoiced Apparel]]-1 -> 3.939759 | AV16: 24800 | AW16: 2345 | AX16: =Table3[[#This Row],[Actual Order Book Shoes ]]/Table3[[#This Row],[Tommaso''s FC Q2 SS5 Net Sales FC Shoes]]-1 -> -0.77653117 | AY16: =Table3[[#This Row],[Actual Order Book Apparel ]]/Table3[[#This Row],[Tommaso''s FC Q2 SS5 Net Sales FC Apparel]]-1 -> -0.82417796 | AZ16: =Table3[[#This Row],[Actual Order Book Shoes ]]/Table3[[#This Row],[Net Sales Invoiced Shoes]]-1 -> -0.31111111 | BA16: =IFERROR(Table3[[#This Row],[Actual Order Book Apparel ]]/Table3[[#This Row],[Net Sales Invoiced Apparel]]-1,"") -> -0.13148148
A17: Europe | B17: Europe | C17: Scale | D17: Core | E17: 213400 | F17: 0.061 | G17: 0 | H17: 0 | I17: 0.011 | J17: 24300 | K17: 0.073 | L17: 0.039 | M17: 0 | N17: 0.022 | P17: =IFERROR(E17/(1-F17+G17+H17-I17),0) -> 229956.9 | Q17: =IFERROR(J17/(1+L17+M17-N17-K17),0) -> 25741.525 | R17: =E17+J17 -> 237700 | S17: ='SS24 Q2 Data'!$P7+Q17 -> 57234.738 | T17: =ROUND(P17*F17,0) -> 14027 | U17: =ROUND(P17*G17,0) -> 0 | V17: =ROUND(P17*H17,0) -> 0 | W17: =ROUND(P17*I17,0) -> 2530 | X17: =ROUND(Q17*K17,0) -> 1879 | Y17: =ROUND(Q17*L17,0) -> 1004 | Z17: =ROUND(Q17*M17,0) -> 0 | AA17: =ROUND(Q17*M17,0) -> 0 | AB17: =J17/E17 -> 0.11387067 | AD17: =Table3[[#This Row],[Pre-Order Cancellations Mix Shoes]]+Table3[[#This Row],[Pre-Order Cancellations Mix %Apparel]] -> 15906 | AE17: =Table3[[#This Row],[Tot Cancellation]]/Table3[[#This Row],[Tot PreOrder Invoiced (units)]] -> 0.27790815 | AF17: =Table3[[#This Row],[Re-Order Rate %7]]+Table3[[#This Row],[Re-Order Rate %11]] -> 1004 | AG17: =Table3[[#This Row],[ToT Reorders]]/Table3[[#This Row],[Tot Net Sales Invoiced (units)]] -> 0.0042238115 | AH17: =Table3[[#This Row],[Stock Clearance Rate %8]]+Table3[[#This Row],[Stock Clearance Rate %12]] -> 0 | AI17: =Table3[[#This Row],[ToT Stock Clearance]]/Table3[[#This Row],[Tot PreOrder Invoiced (units)]] -> 0 | AJ17: =Table3[[#This Row],[Returns Rate %13]]+Table3[[#This Row],[Returns Rate %9]] -> 2530 | AK17: =Table3[[#This Row],[ToT Retruns]]/Table3[[#This Row],[Tot PreOrder Invoiced (units)]] -> 0.044203924 | AL17: 0.06 | AM17: 0.1 | AN17: 0.01 | AO17: 0.03 | AP17: =$AQ$2 -> 0.25 | AQ17: =IF(Table3[[#This Row],[Re-Order Rate %4]]-Table3[[#This Row],[Pre-Order Cancellations Mix %2]]-Table3[[#This Row],[Returns Rate %6]]<$AQ$1,$AQ$1,Table3[[#This Row],[Re-Order Rate %4]]-Table3[[#This Row],[Pre-Order Cancellations Mix %2]]-Table3[[#This Row],[Returns Rate %6]]) -> 0.68 | AR17: =Table3[[#This Row],[Pre-Orders Booked LYQ2 (shoes)]]*(1+Table3[[#This Row],[Re-Order Rate % FC]]+Table3[[#This Row],[Stock Clearance Rate %2]]+Table3[[#This Row],[Returns Rate %2]]-Table3[[#This Row],[FC Cancellation Mix %Shoes]]+Table3[[#This Row],[Exp Shoes PreOrder Growth Rate]]) -> 305842.67 | AS17: =Table3[[#This Row],[Tommaso''s FC Q2 SS5 Net Sales FC Shoes]]/Table3[[#This Row],[Net Sales Invoiced Shoes]]-1 -> 0.43318966 | AT17: =Table3[[#This Row],[Pre-Orders Booked LYQ2 (apparel)]]*(1+Table3[[#This Row],[Re-Order Rate % FC]]+Table3[[#This Row],[Stock Clearance Rate %2]]+Table3[[#This Row],[Returns Rate %2]]-Table3[[#This Row],[FC Cancellation Mix %Shoes]]+Table3[[#This Row],[Exp Apparel PreOrder Growth Rate]]) -> 45305.085 | AU17: =Table3[[#This Row],[Tommaso''s FC Q2 SS5 Net Sales FC Apparel]]/Table3[[#This Row],[Net Sales Invoiced Apparel]]-1 -> 0.86440678 | AV17: 256100 | AW17: 25435 | AX17: =Table3[[#This Row],[Actual Order Book Shoes ]]/Table3[[#This Row],[Tommaso''s FC Q2 SS5 Net Sales FC Shoes]]-1 -> -0.16264137 | AY17: =Table3[[#This Row],[Actual Order Book Apparel ]]/Table3[[#This Row],[Tommaso''s FC Q2 SS5 Net Sales FC Apparel]]-1 -> -0.43858399 | AZ17: =Table3[[#This Row],[Actual Order Book Shoes ]]/Table3[[#This Row],[Net Sales Invoiced Shoes]]-1 -> 0.20009372 | BA17: =IFERROR(Table3[[#This Row],[Actual Order Book Apparel ]]/Table3[[#This Row],[Net Sales Invoiced Apparel]]-1,"") -> 0.046707819
A18: Europe | B18: Europe | C18: Vault | D18: Core | E18: 95400 | F18: 0.093 | G18: 0.017 | H18: 0 | I18: 0.047 | J18: 0 | K18: 0 | L18: 0 | M18: 0 | N18: 0 | P18: =IFERROR(E18/(1-F18+G18+H18-I18),0) -> 108779.93 | Q18: =IFERROR(J18/(1+L18+M18-N18-K18),0) -> 0 | R18: =E18+J18 -> 95400 | S18: ='SS24 Q2 Data'!$P9+Q18 -> 53947.368 | T18: =ROUND(P18*F18,0) -> 10117 | U18: =ROUND(P18*G18,0) -> 1849 | V18: =ROUND(P18*H18,0) -> 0 | W18: =ROUND(P18*I18,0) -> 5113 | X18: =ROUND(Q18*K18,0) -> 0 | Y18: =ROUND(Q18*L18,0) -> 0 | Z18: =ROUND(Q18*M18,0) -> 0 | AA18: =ROUND(Q18*M18,0) -> 0 | AB18: =J18/E18 -> 0 | AD18: =Table3[[#This Row],[Pre-Order Cancellations Mix Shoes]]+Table3[[#This Row],[Pre-Order Cancellations Mix %Apparel]] -> 10117 | AE18: =Table3[[#This Row],[Tot Cancellation]]/Table3[[#This Row],[Tot PreOrder Invoiced (units)]] -> 0.18753463 | AF18: =Table3[[#This Row],[Re-Order Rate %7]]+Table3[[#This Row],[Re-Order Rate %11]] -> 1849 | AG18: =Table3[[#This Row],[ToT Reorders]]/Table3[[#This Row],[Tot Net Sales Invoiced (units)]] -> 0.019381551 | AH18: =Table3[[#This Row],[Stock Clearance Rate %8]]+Table3[[#This Row],[Stock Clearance Rate %12]] -> 0 | AI18: =Table3[[#This Row],[ToT Stock Clearance]]/Table3[[#This Row],[Tot PreOrder Invoiced (units)]] -> 0 | AJ18: =Table3[[#This Row],[Returns Rate %13]]+Table3[[#This Row],[Returns Rate %9]] -> 5113 | AK18: =Table3[[#This Row],[ToT Retruns]]/Table3[[#This Row],[Tot PreOrder Invoiced (units)]] -> 0.094777561 | AL18: 0.06 | AM18: 0.1 | AN18: 0.01 | AO18: 0.03 | AP18: =$AQ$2 -> 0.25 | AQ18: NA | AR18: =Table3[[#This Row],[Pre-Orders Booked LYQ2 (shoes)]]*(1+Table3[[#This Row],[Re-Order Rate % FC]]+Table3[[#This Row],[Stock Clearance Rate %2]]+Table3[[#This Row],[Returns Rate %2]]-Table3[[#This Row],[FC Cancellation Mix %Shoes]]+Table3[[#This Row],[Exp Shoes PreOrder Growth Rate]]) -> 144677.31 | AS18: =Table3[[#This Row],[Tommaso''s FC Q2 SS5 Net Sales FC Shoes]]/Table3[[#This Row],[Net Sales Invoiced Shoes]]-1 -> 0.51653364 | AT18: 10000 | AU18: NA | AV18: 124000 | AW18: 0 | AX18: =Table3[[#This Row],[Actual Order Book Shoes ]]/Table3[[#This Row],[Tommaso''s FC Q2 SS5 Net Sales FC Shoes]]-1 -> -0.14292019 | AY18: =Table3[[#This Row],[Actual Order Book Apparel ]]/Table3[[#This Row],[Tommaso''s FC Q2 SS5 Net Sales FC Apparel]]-1 -> -1 | AZ18: =Table3[[#This Row],[Actual Order Book Shoes ]]/Table3[[#This Row],[Net Sales Invoiced Shoes]]-1 -> 0.29979036 | BA18: =IFERROR(Table3[[#This Row],[Actual Order Book Apparel ]]/Table3[[#This Row],[Net Sales Invoiced Apparel]]-1,"")
A19: North | B19: France | C19: Swift-Pulse | D19: Opportunity | E19: 6800 | F19: 0.036 | G19: 0.037 | H19: 0 | I19: 0 | J19: 0 | K19: 0 | L19: 0 | M19: 0 | N19: 0 | P19: =IFERROR(E19/(1-F19+G19+H19-I19),0) -> 6793.2068 | Q19: =IFERROR(J19/(1+L19+M19-N19-K19),0) -> 0 | R19: =E19+J19 -> 6800 | S19: ='SS24 Q2 Data'!$P21+Q19 -> 1200 | T19: =ROUND(P19*F19,0) -> 245 | U19: =ROUND(P19*G19,0) -> 251 | V19: =ROUND(P19*H19,0) -> 0 | W19: =ROUND(P19*I19,0) -> 0 | X19: =ROUND(Q19*K19,0) -> 0 | Y19: =ROUND(Q19*L19,0) -> 0 | Z19: =ROUND(Q19*M19,0) -> 0 | AA19: =ROUND(Q19*M19,0) -> 0 | AB19: =J19/E19 -> 0 | AD19: =Table3[[#This Row],[Pre-Order Cancellations Mix Shoes]]+Table3[[#This Row],[Pre-Order Cancellations Mix %Apparel]] -> 245 | AE19: =Table3[[#This Row],[Tot Cancellation]]/Table3[[#This Row],[Tot PreOrder Invoiced (units)]] -> 0.20416667 | AF19: =Table3[[#This Row],[Re-Order Rate %7]]+Table3[[#This Row],[Re-Order Rate %11]] -> 251 | AG19: =Table3[[#This Row],[ToT Reorders]]/Table3[[#This Row],[Tot Net Sales Invoiced (units)]] -> 0.036911765 | AH19: =Table3[[#This Row],[Stock Clearance Rate %8]]+Table3[[#This Row],[Stock Clearance Rate %12]] -> 0 | AI19: =Table3[[#This Row],[ToT Stock Clearance]]/Table3[[#This Row],[Tot PreOrder Invoiced (units)]] -> 0 | AJ19: =Table3[[#This Row],[Returns Rate %13]]+Table3[[#This Row],[Returns Rate %9]] -> 0 | AK19: =Table3[[#This Row],[ToT Retruns]]/Table3[[#This Row],[Tot PreOrder Invoiced (units)]] -> 0 | AL19: 0.03 | AM19: 0.3 | AN19: 0.01 | AO19: 0.03 | AP19: =$AQ$2 -> 0.25 | AQ19: NA | AR19: =Table3[[#This Row],[Pre-Orders Booked LYQ2 (shoes)]]*(1+Table3[[#This Row],[Re-Order Rate % FC]]+Table3[[#This Row],[Stock Clearance Rate %2]]+Table3[[#This Row],[Returns Rate %2]]-Table3[[#This Row],[FC Cancellation Mix %Shoes]]+Table3[[#This Row],[Exp Shoes PreOrder Growth Rate]]) -> 10597.403 | AS19: =Table3[[#This Row],[Tommaso''s FC Q2 SS5 Net Sales FC Shoes]]/Table3[[#This Row],[Net Sales Invoiced Shoes]]-1 -> 0.55844156 | AT19: 1500 | AU19: NA | AV19: 2300 | AW19: 324 | AX19: =Table3[[#This Row],[Actual Order Book Shoes ]]/Table3[[#This Row],[Tommaso''s FC Q2 SS5 Net Sales FC Shoes]]-1 -> -0.78296569 | AY19: =Table3[[#This Row],[Actual Order Book Apparel ]]/Table3[[#This Row],[Tommaso''s FC Q2 SS5 Net Sales FC Apparel]]-1 -> -0.784 | AZ19: =Table3[[#This Row],[Actual Order Book Shoes ]]/Table3[[#This Row],[Net Sales Invoiced Shoes]]-1 -> -0.66176471 | BA19: =IFERROR(Table3[[#This Row],[Actual Order Book Apparel ]]/Table3[[#This Row],[Net Sales Invoiced Apparel]]-1,"")
A20: North | B20: BeNeLux | C20: Vanguard Wilds | D20: Opportunity | E20: 2000 | F20: 0 | G20: 0 | H20: 0 | I20: 0 | J20: 250 | K20: 0 | L20: 0 | M20: 0 | N20: 0 | P20: =IFERROR(E20/(1-F20+G20+H20-I20),0) -> 2000 | Q20: =IFERROR(J20/(1+L20+M20-N20-K20),0) -> 250 | R20: =E20+J20 -> 2250 | S20: ='SS24 Q2 Data'!$P24+Q20 -> 250 | T20: =ROUND(P20*F20,0) -> 0 | U20: =ROUND(P20*G20,0) -> 0 | V20: =ROUND(P20*H20,0) -> 0 | W20: =ROUND(P20*I20,0) -> 0 | X20: =ROUND(Q20*K20,0) -> 0 | Y20: =ROUND(Q20*L20,0) -> 0 | Z20: =ROUND(Q20*M20,0) -> 0 | AA20: =ROUND(Q20*M20,0) -> 0 | AB20: =J20/E20 -> 0.125 | AD20: =Table3[[#This Row],[Pre-Order Cancellations Mix Shoes]]+Table3[[#This Row],[Pre-Order Cancellations Mix %Apparel]] -> 0 | AE20: =Table3[[#This Row],[Tot Cancellation]]/Table3[[#This Row],[Tot PreOrder Invoiced (units)]] -> 0 | AF20: =Table3[[#This Row],[Re-Order Rate %7]]+Table3[[#This Row],[Re-Order Rate %11]] -> 0 | AG20: =Table3[[#This Row],[ToT Reorders]]/Table3[[#This Row],[Tot Net Sales Invoiced (units)]] -> 0 | AH20: =Table3[[#This Row],[Stock Clearance Rate %8]]+Table3[[#This Row],[Stock Clearance Rate %12]] -> 0 | AI20: =Table3[[#This Row],[ToT Stock Clearance]]/Table3[[#This Row],[Tot PreOrder Invoiced (units)]] -> 0 | AJ20: =Table3[[#This Row],[Returns Rate %13]]+Table3[[#This Row],[Returns Rate %9]] -> 0 | AK20: =Table3[[#This Row],[ToT Retruns]]/Table3[[#This Row],[Tot PreOrder Invoiced (units)]] -> 0 | AL20: 0.03 | AM20: 0.3 | AN20: 0.01 | AO20: 0.03 | AP20: =$AQ$2 -> 0.25 | AQ20: =IF(Table3[[#This Row],[Re-Order Rate %4]]-Table3[[#This Row],[Pre-Order Cancellations Mix %2]]-Table3[[#This Row],[Returns Rate %6]]<$AQ$1,$AQ$1,Table3[[#This Row],[Re-Order Rate %4]]-Table3[[#This Row],[Pre-Order Cancellations Mix %2]]-Table3[[#This Row],[Returns Rate %6]]) -> 0.68 | AR20: =Table3[[#This Row],[Pre-Orders Booked LYQ2 (shoes)]]*(1+Table3[[#This Row],[Re-Order Rate % FC]]+Table3[[#This Row],[Stock Clearance Rate %2]]+Table3[[#This Row],[Returns Rate %2]]-Table3[[#This Row],[FC Cancellation Mix %Shoes]]+Table3[[#This Row],[Exp Shoes PreOrder Growth Rate]]) -> 3120 | AS20: =Table3[[#This Row],[Tommaso''s FC Q2 SS5 Net Sales FC Shoes]]/Table3[[#This Row],[Net Sales Invoiced Shoes]]-1 -> 0.56 | AT20: =Table3[[#This Row],[Pre-Orders Booked LYQ2 (apparel)]]*(1+Table3[[#This Row],[Re-Order Rate % FC]]+Table3[[#This Row],[Stock Clearance Rate %2]]+Table3[[#This Row],[Returns Rate %2]]-Table3[[#This Row],[FC Cancellation Mix %Shoes]]+Table3[[#This Row],[Exp Apparel PreOrder Growth Rate]]) -> 497.5 | AU20: =Table3[[#This Row],[Tommaso''s FC Q2 SS5 Net Sales FC Apparel]]/Table3[[#This Row],[Net Sales Invoiced Apparel]]-1 -> 0.99 | AV20: 600 | AW20: 0 | AX20: =Table3[[#This Row],[Actual Order Book Shoes ]]/Table3[[#This Row],[Tommaso''s FC Q2 SS5 Net Sales FC Shoes]]-1 -> -0.80769231 | AY20: =Table3[[#This Row],[Actual Order Book Apparel ]]/Table3[[#This Row],[Tommaso''s FC Q2 SS5 Net Sales FC Apparel]]-1 -> -1 | AZ20: =Table3[[#This Row],[Actual Order Book Shoes ]]/Table3[[#This Row],[Net Sales Invoiced Shoes]]-1 -> -0.7 | BA20: =IFERROR(Table3[[#This Row],[Actual Order Book Apparel ]]/Table3[[#This Row],[Net Sales Invoiced Apparel]]-1,"") -> -1
A21: Europe | B21: Europe | C21: Strike-Point | D21: Opportunity | E21: 1200 | F21: 0 | G21: 0 | H21: 0 | I21: 0 | J21: 0 | K21: 0 | L21: 0 | M21: 0 | N21: 0 | P21: =IFERROR(E21/(1-F21+G21+H21-I21),0) -> 1200 | Q21: =IFERROR(J21/(1+L21+M21-N21-K21),0) -> 0 | R21: =E21+J21 -> 1200 | S21: ='SS24 Q2 Data'!$P25+Q21 -> 284.09091 | T21: =ROUND(P21*F21,0) -> 0 | U21: =ROUND(P21*G21,0) -> 0 | V21: =ROUND(P21*H21,0) -> 0 | W21: =ROUND(P21*I21,0) -> 0 | X21: =ROUND(Q21*K21,0) -> 0 | Y21: =ROUND(Q21*L21,0) -> 0 | Z21: =ROUND(Q21*M21,0) -> 0 | AA21: =ROUND(Q21*M21,0) -> 0 | AB21: =J21/E21 -> 0 | AD21: =Table3[[#This Row],[Pre-Order Cancellations Mix Shoes]]+Table3[[#This Row],[Pre-Order Cancellations Mix %Apparel]] -> 0 | AE21: =Table3[[#This Row],[Tot Cancellation]]/Table3[[#This Row],[Tot PreOrder Invoiced (units)]] -> 0 | AF21: =Table3[[#This Row],[Re-Order Rate %7]]+Table3[[#This Row],[Re-Order Rate %11]] -> 0 | AG21: =Table3[[#This Row],[ToT Reorders]]/Table3[[#This Row],[Tot Net Sales Invoiced (units)]] -> 0 | AH21: =Table3[[#This Row],[Stock Clearance Rate %8]]+Table3[[#This Row],[Stock Clearance Rate %12]] -> 0 | AI21: =Table3[[#This Row],[ToT Stock Clearance]]/Table3[[#This Row],[Tot PreOrder Invoiced (units)]] -> 0 | AJ21: =Table3[[#This Row],[Returns Rate %13]]+Table3[[#This Row],[Returns Rate %9]] -> 0 | AK21: =Table3[[#This Row],[ToT Retruns]]/Table3[[#This Row],[Tot PreOrder Invoiced (units)]] -> 0 | AL21: 0.03 | AM21: 0.3 | AN21: 0.01 | AO21: 0.03 | AP21: =$AQ$2 -> 0.25 | AQ21: NA | AR21: =Table3[[#This Row],[Pre-Orders Booked LYQ2 (shoes)]]*(1+Table3[[#This Row],[Re-Order Rate % FC]]+Table3[[#This Row],[Stock Clearance Rate %2]]+Table3[[#This Row],[Returns Rate %2]]-Table3[[#This Row],[FC Cancellation Mix %Shoes]]+Table3[[#This Row],[Exp Shoes PreOrder Growth Rate]]) -> 1872 | AS21: =Table3[[#This Row],[Tommaso''s FC Q2 SS5 Net Sales FC Shoes]]/Table3[[#This Row],[Net Sales Invoiced Shoes]]-1 -> 0.56 | AT21: 500 | AU21: NA | AV21: 2400 | AW21: 123 | AX21: =Table3[[#This Row],[Actual Order Book Shoes ]]/Table3[[#This Row],[Tommaso''s FC Q2 SS5 Net Sales FC Shoes]]-1 -> 0.28205128 | AY21: =Table3[[#This Row],[Actual Order Book Apparel ]]/Table3[[#This Row],[Tommaso''s FC Q2 SS5 Net Sales FC Apparel]]-1 -> -0.754 | AZ21: =Table3[[#This Row],[Actual Order Book Shoes ]]/Table3[[#This Row],[Net Sales Invoiced Shoes]]-1 -> 1 | BA21: =IFERROR(Table3[[#This Row],[Actual Order Book Apparel ]]/Table3[[#This Row],[Net Sales Invoiced Apparel]]-1,"")
A22: North | B22: Nordics | C22: Omni-Arena | D22: Opportunity | E22: 400 | F22: 0.765 | G22: 0.387 | H22: 0 | I22: 0 | J22: 100 | K22: 0 | L22: 0.429 | M22: 0 | N22: 0 | P22: =IFERROR(E22/(1-F22+G22+H22-I22),0) -> 643.08682 | Q22: =IFERROR(J22/(1+L22+M22-N22-K22),0) -> 69.979006 | R22: =E22+J22 -> 500 | S22: ='SS24 Q2 Data'!$P27+Q22 -> 4109.038 | T22: =ROUND(P22*F22,0) -> 492 | U22: =ROUND(P22*G22,0) -> 249 | V22: =ROUND(P22*H22,0) -> 0 | W22: =ROUND(P22*I22,0) -> 0 | X22: =ROUND(Q22*K22,0) -> 0 | Y22: =ROUND(Q22*L22,0) -> 30 | Z22: =ROUND(Q22*M22,0) -> 0 | AA22: =ROUND(Q22*M22,0) -> 0 | AB22: =J22/E22 -> 0.25 | AD22: =Table3[[#This Row],[Pre-Order Cancellations Mix Shoes]]+Table3[[#This Row],[Pre-Order Cancellations Mix %Apparel]] -> 492 | AE22: =Table3[[#This Row],[Tot Cancellation]]/Table3[[#This Row],[Tot PreOrder Invoiced (units)]] -> 0.11973605 | AF22: =Table3[[#This Row],[Re-Order Rate %7]]+Table3[[#This Row],[Re-Order Rate %11]] -> 279 | AG22: =Table3[[#This Row],[ToT Reorders]]/Table3[[#This Row],[Tot Net Sales Invoiced (units)]] -> 0.558 | AH22: =Table3[[#This Row],[Stock Clearance Rate %8]]+Table3[[#This Row],[Stock Clearance Rate %12]] -> 0 | AI22: =Table3[[#This Row],[ToT Stock Clearance]]/Table3[[#This Row],[Tot PreOrder Invoiced (units)]] -> 0 | AJ22: =Table3[[#This Row],[Returns Rate %13]]+Table3[[#This Row],[Returns Rate %9]] -> 0 | AK22: =Table3[[#This Row],[ToT Retruns]]/Table3[[#This Row],[Tot PreOrder Invoiced (units)]] -> 0 | AL22: 0.03 | AM22: 0.3 | AN22: 0.01 | AO22: 0.03 | AP22: =$AQ$2 -> 0.25 | AQ22: =IF(Table3[[#This Row],[Re-Order Rate %4]]-Table3[[#This Row],[Pre-Order Cancellations Mix %2]]-Table3[[#This Row],[Returns Rate %6]]<$AQ$1,$AQ$1,Table3[[#This Row],[Re-Order Rate %4]]-Table3[[#This Row],[Pre-Order Cancellations Mix %2]]-Table3[[#This Row],[Returns Rate %6]]) -> 0.68 | AR22: =Table3[[#This Row],[Pre-Orders Booked LYQ2 (shoes)]]*(1+Table3[[#This Row],[Re-Order Rate % FC]]+Table3[[#This Row],[Stock Clearance Rate %2]]+Table3[[#This Row],[Returns Rate %2]]-Table3[[#This Row],[FC Cancellation Mix %Shoes]]+Table3[[#This Row],[Exp Shoes PreOrder Growth Rate]]) -> 1003.2154 | AS22: =Table3[[#This Row],[Tommaso''s FC Q2 SS5 Net Sales FC Shoes]]/Table3[[#This Row],[Net Sales Invoiced Shoes]]-1 -> 1.5080386 | AT22: =Table3[[#This Row],[Pre-Orders Booked LYQ2 (apparel)]]*(1+Table3[[#This Row],[Re-Order Rate % FC]]+Table3[[#This Row],[Stock Clearance Rate %2]]+Table3[[#This Row],[Returns Rate %2]]-Table3[[#This Row],[FC Cancellation Mix %Shoes]]+Table3[[#This Row],[Exp Apparel PreOrder Growth Rate]]) -> 139.25822 | AU22: =Table3[[#This Row],[Tommaso''s FC Q2 SS5 Net Sales FC Apparel]]/Table3[[#This Row],[Net Sales Invoiced Apparel]]-1 -> 0.39258223 | AV22: 1900 | AW22: 75 | AX22: =Table3[[#This Row],[Actual Order Book Shoes ]]/Table3[[#This Row],[Tommaso''s FC Q2 SS5 Net Sales FC Shoes]]-1 -> 0.89391026 | AY22: =Table3[[#This Row],[Actual Order Book Apparel ]]/Table3[[#This Row],[Tommaso''s FC Q2 SS5 Net Sales FC Apparel]]-1 -> -0.46143216 | AZ22: =Table3[[#This Row],[Actual Order Book Shoes ]]/Table3[[#This Row],[Net Sales Invoiced Shoes]]-1 -> 3.75 | BA22: =IFERROR(Table3[[#This Row],[Actual Order Book Apparel ]]/Table3[[#This Row],[Net Sales Invoiced Apparel]]-1,"") -> -0.25
A23: North | B23: Nordics | C23: Nordic Nord | D23: Opportunity | E23: 900 | F23: 0.058 | G23: 1.219 | H23: 0 | I23: 0.003 | J23: 0 | K23: 0 | L23: 0.833 | M23: 0 | N23: 0 | P23: =IFERROR(E23/(1-F23+G23+H23-I23),0) -> 417.05283 | Q23: =IFERROR(J23/(1+L23+M23-N23-K23),0) -> 0 | R23: =E23+J23 -> 900 | S23: ='SS24 Q2 Data'!$P26+Q23 -> 4204.2042 | T23: =ROUND(P23*F23,0) -> 24 | U23: =ROUND(P23*G23,0) -> 508 | V23: =ROUND(P23*H23,0) -> 0 | W23: =ROUND(P23*I23,0) -> 1 | X23: =ROUND(Q23*K23,0) -> 0 | Y23: =ROUND(Q23*L23,0) -> 0 | Z23: =ROUND(Q23*M23,0) -> 0 | AA23: =ROUND(Q23*M23,0) -> 0 | AB23: =J23/E23 -> 0 | AD23: =Table3[[#This Row],[Pre-Order Cancellations Mix Shoes]]+Table3[[#This Row],[Pre-Order Cancellations Mix %Apparel]] -> 24 | AE23: =Table3[[#This Row],[Tot Cancellation]]/Table3[[#This Row],[Tot PreOrder Invoiced (units)]] -> 0.0057085714 | AF23: =Table3[[#This Row],[Re-Order Rate %7]]+Table3[[#This Row],[Re-Order Rate %11]] -> 508 | AG23: =Table3[[#This Row],[ToT Reorders]]/Table3[[#This Row],[Tot Net Sales Invoiced (units)]] -> 0.56444444 | AH23: =Table3[[#This Row],[Stock Clearance Rate %8]]+Table3[[#This Row],[Stock Clearance Rate %12]] -> 0 | AI23: =Table3[[#This Row],[ToT Stock Clearance]]/Table3[[#This Row],[Tot PreOrder Invoiced (units)]] -> 0 | AJ23: =Table3[[#This Row],[Returns Rate %13]]+Table3[[#This Row],[Returns Rate %9]] -> 1 | AK23: =Table3[[#This Row],[ToT Retruns]]/Table3[[#This Row],[Tot PreOrder Invoiced (units)]] -> 0.00023785714 | AL23: 0.03 | AM23: 0.3 | AN23: 0.01 | AO23: 0.03 | AP23: =$AQ$2 -> 0.25 | AQ23: NA | AR23: =Table3[[#This Row],[Pre-Orders Booked LYQ2 (shoes)]]*(1+Table3[[#This Row],[Re-Order Rate % FC]]+Table3[[#This Row],[Stock Clearance Rate %2]]+Table3[[#This Row],[Returns Rate %2]]-Table3[[#This Row],[FC Cancellation Mix %Shoes]]+Table3[[#This Row],[Exp Shoes PreOrder Growth Rate]]) -> 650.60241 | AS23: =Table3[[#This Row],[Tommaso''s FC Q2 SS5 Net Sales FC Shoes]]/Table3[[#This Row],[Net Sales Invoiced Shoes]]-1 -> -0.27710843 | AT23: 500 | AU23: NA | AV23: 3300 | AW23: 50 | AX23: =Table3[[#This Row],[Actual Order Book Shoes ]]/Table3[[#This Row],[Tommaso''s FC Q2 SS5 Net Sales FC Shoes]]-1 -> 4.0722222 | AY23: =Table3[[#This Row],[Actual Order Book Apparel ]]/Table3[[#This Row],[Tommaso''s FC Q2 SS5 Net Sales FC Apparel]]-1 -> -0.9 | AZ23: =Table3[[#This Row],[Actual Order Book Shoes ]]/Table3[[#This Row],[Net Sales Invoiced Shoes]]-1 -> 2.6666667 | BA23: =IFERROR(Table3[[#This Row],[Actual Order Book Apparel ]]/Table3[[#This Row],[Net Sales Invoiced Apparel]]-1,"")
A24: North | B24: United Kingdom | C24: Velvet & Vice | D24: Opportunity | E24: 1e-09 | F24: 0 | G24: 0 | H24: 0 | I24: 0 | J24: 0 | K24: 0 | L24: 0 | M24: 0 | N24: 0 | P24: =IFERROR(E24/(1-F24+G24+H24-I24),0) -> 1e-09 | Q24: =IFERROR(J24/(1+L24+M24-N24-K24),0) -> 0 | R24: =E24+J24 -> 1e-09 | S24: ='SS24 Q2 Data'!$P29+Q24 -> 19400 | T24: =ROUND(P24*F24,0) -> 0 | U24: =ROUND(P24*G24,0) -> 0 | V24: =ROUND(P24*H24,0) -> 0 | W24: =ROUND(P24*I24,0) -> 0 | X24: =ROUND(Q24*K24,0) -> 0 | Y24: =ROUND(Q24*L24,0) -> 0 | Z24: =ROUND(Q24*M24,0) -> 0 | AA24: =ROUND(Q24*M24,0) -> 0 | AB24: =J24/E24 -> 0 | AD24: =Table3[[#This Row],[Pre-Order Cancellations Mix Shoes]]+Table3[[#This Row],[Pre-Order Cancellations Mix %Apparel]] -> 0 | AE24: =Table3[[#This Row],[Tot Cancellation]]/Table3[[#This Row],[Tot PreOrder Invoiced (units)]] -> 0 | AF24: =Table3[[#This Row],[Re-Order Rate %7]]+Table3[[#This Row],[Re-Order Rate %11]] -> 0 | AG24: =Table3[[#This Row],[ToT Reorders]]/Table3[[#This Row],[Tot Net Sales Invoiced (units)]] -> 0 | AH24: =Table3[[#This Row],[Stock Clearance Rate %8]]+Table3[[#This Row],[Stock Clearance Rate %12]] -> 0 | AI24: =Table3[[#This Row],[ToT Stock Clearance]]/Table3[[#This Row],[Tot PreOrder Invoiced (units)]] -> 0 | AJ24: =Table3[[#This Row],[Returns Rate %13]]+Table3[[#This Row],[Returns Rate %9]] -> 0 | AK24: =Table3[[#This Row],[ToT Retruns]]/Table3[[#This Row],[Tot PreOrder Invoiced (units)]] -> 0 | AL24: 0.03 | AM24: 0.3 | AN24: 0.01 | AO24: 0.03 | AP24: =$AQ$2 -> 0.25 | AQ24: NA | AR24: 500 | AS24: NA | AT24: 500 | AU24: NA | AV24: 15100 | AW24: 345 | AX24: =Table3[[#This Row],[Actual Order Book Shoes ]]/Table3[[#This Row],[Tommaso''s FC Q2 SS5 Net Sales FC Shoes]]-1 -> 29.2 | AY24: =Table3[[#This Row],[Actual Order Book Apparel ]]/Table3[[#This Row],[Tommaso''s FC Q2 SS5 Net Sales FC Apparel]]-1 -> -0.31 | AZ24: =Table3[[#This Row],[Actual Order Book Shoes ]]/Table3[[#This Row],[Net Sales Invoiced Shoes]]-1 -> 15099999999999 | BA24: =IFERROR(Table3[[#This Row],[Actual Order Book Apparel ]]/Table3[[#This Row],[Net Sales Invoiced Apparel]]-1,"")
A25: South | B25: Spain | C25: Agora Athletics | D25: Opportunity | E25: 300 | F25: 0 | G25: 0.203 | H25: 0 | I25: 0.147 | J25: 0 | K25: 0 | L25: 0 | M25: 0 | N25: 0 | P25: =IFERROR(E25/(1-F25+G25+H25-I25),0) -> 284.09091 | Q25: =IFERROR(J25/(1+L25+M25-N25-K25),0) -> 0 | R25: =E25+J25 -> 300 | S25: ='SS24 Q2 Data'!$P28+Q25 -> 22086.957 | T25: =ROUND(P25*F25,0) -> 0 | U25: =ROUND(P25*G25,0) -> 58 | V25: =ROUND(P25*H25,0) -> 0 | W25: =ROUND(P25*I25,0) -> 42 | X25: =ROUND(Q25*K25,0) -> 0 | Y25: =ROUND(Q25*L25,0) -> 0 | Z25: =ROUND(Q25*M25,0) -> 0 | AA25: =ROUND(Q25*M25,0) -> 0 | AB25: =J25/E25 -> 0 | AD25: =Table3[[#This Row],[Pre-Order Cancellations Mix Shoes]]+Table3[[#This Row],[Pre-Order Cancellations Mix %Apparel]] -> 0 | AE25: =Table3[[#This Row],[Tot Cancellation]]/Table3[[#This Row],[Tot PreOrder Invoiced (units)]] -> 0 | AF25: =Table3[[#This Row],[Re-Order Rate %7]]+Table3[[#This Row],[Re-Order Rate %11]] -> 58 | AG25: =Table3[[#This Row],[ToT Reorders]]/Table3[[#This Row],[Tot Net Sales Invoiced (units)]] -> 0.19333333 | AH25: =Table3[[#This Row],[Stock Clearance Rate %8]]+Table3[[#This Row],[Stock Clearance Rate %12]] -> 0 | AI25: =Table3[[#This Row],[ToT Stock Clearance]]/Table3[[#This Row],[Tot PreOrder Invoiced (units)]] -> 0 | AJ25: =Table3[[#This Row],[Returns Rate %13]]+Table3[[#This Row],[Returns Rate %9]] -> 42 | AK25: =Table3[[#This Row],[ToT Retruns]]/Table3[[#This Row],[Tot PreOrder Invoiced (units)]] -> 0.0019015748 | AL25: 0.03 | AM25: 0.3 | AN25: 0.01 | AO25: 0.03 | AP25: =$AQ$2 -> 0.25 | AQ25: NA | AR25: =Table3[[#This Row],[Pre-Orders Booked LYQ2 (shoes)]]*(1+Table3[[#This Row],[Re-Order Rate % FC]]+Table3[[#This Row],[Stock Clearance Rate %2]]+Table3[[#This Row],[Returns Rate %2]]-Table3[[#This Row],[FC Cancellation Mix %Shoes]]+Table3[[#This Row],[Exp Shoes PreOrder Growth Rate]]) -> 443.18182 | AS25: =Table3[[#This Row],[Tommaso''s FC Q2 SS5 Net Sales FC Shoes]]/Table3[[#This Row],[Net Sales Invoiced Shoes]]-1 -> 0.47727273 | AT25: 500 | AU25: NA | AV25: 900 | AW25: 0 | AX25: =Table3[[#This Row],[Actual Order Book Shoes ]]/Table3[[#This Row],[Tommaso''s FC Q2 SS5 Net Sales FC Shoes]]-1 -> 1.0307692 | AY25: =Table3[[#This Row],[Actual Order Book Apparel ]]/Table3[[#This Row],[Tommaso''s FC Q2 SS5 Net Sales FC Apparel]]-1 -> -1 | AZ25: =Table3[[#This Row],[Actual Order Book Shoes ]]/Table3[[#This Row],[Net Sales Invoiced Shoes]]-1 -> 2 | BA25: =IFERROR(Table3[[#This Row],[Actual Order Book Apparel ]]/Table3[[#This Row],[Net Sales Invoiced Apparel]]-1,"")
A26: North | B26: France | C26: Velocity Labs | D26: Monitor | E26: 7000 | F26: 0.042 | G26: 0.003 | H26: 0.704 | I26: 0 | J26: 1300 | K26: 0.048 | L26: 0.007 | M26: 0 | N26: 0 | P26: =IFERROR(E26/(1-F26+G26+H26-I26),0) -> 4204.2042 | Q26: =IFERROR(J26/(1+L26+M26-N26-K26),0) -> 1355.5787 | R26: =E26+J26 -> 8300 | S26: ='SS24 Q2 Data'!$P20+Q26 -> 3355.5787 | T26: =ROUND(P26*F26,0) -> 177 | U26: =ROUND(P26*G26,0) -> 13 | V26: =ROUND(P26*H26,0) -> 2960 | W26: =ROUND(P26*I26,0) -> 0 | X26: =ROUND(Q26*K26,0) -> 65 | Y26: =ROUND(Q26*L26,0) -> 9 | Z26: =ROUND(Q26*M26,0) -> 0 | AA26: =ROUND(Q26*M26,0) -> 0 | AB26: =J26/E26 -> 0.18571429 | AD26: =Table3[[#This Row],[Pre-Order Cancellations Mix Shoes]]+Table3[[#This Row],[Pre-Order Cancellations Mix %Apparel]] -> 242 | AE26: =Table3[[#This Row],[Tot Cancellation]]/Table3[[#This Row],[Tot PreOrder Invoiced (units)]] -> 0.072118707 | AF26: =Table3[[#This Row],[Re-Order Rate %7]]+Table3[[#This Row],[Re-Order Rate %11]] -> 22 | AG26: =Table3[[#This Row],[ToT Reorders]]/Table3[[#This Row],[Tot Net Sales Invoiced (units)]] -> 0.0026506024 | AH26: =Table3[[#This Row],[Stock Clearance Rate %8]]+Table3[[#This Row],[Stock Clearance Rate %12]] -> 2960 | AI26: =Table3[[#This Row],[ToT Stock Clearance]]/Table3[[#This Row],[Tot PreOrder Invoiced (units)]] -> 0.88211311 | AJ26: =Table3[[#This Row],[Returns Rate %13]]+Table3[[#This Row],[Returns Rate %9]] -> 0 | AK26: =Table3[[#This Row],[ToT Retruns]]/Table3[[#This Row],[Tot PreOrder Invoiced (units)]] -> 0 | AL26: 0.03 | AM26: 0.15 | AN26: 0.01 | AO26: 0.03 | AP26: 0.1 | AQ26: =IF(Table3[[#This Row],[Re-Order Rate %4]]-Table3[[#This Row],[Pre-Order Cancellations Mix %2]]-Table3[[#This Row],[Returns Rate %6]]<$AQ$1,$AQ$1,Table3[[#This Row],[Re-Order Rate %4]]-Table3[[#This Row],[Pre-Order Cancellations Mix %2]]-Table3[[#This Row],[Returns Rate %6]]) -> 0.68 | AR26: =Table3[[#This Row],[Pre-Orders Booked LYQ2 (shoes)]]*(1+Table3[[#This Row],[Re-Order Rate % FC]]+Table3[[#This Row],[Stock Clearance Rate %2]]+Table3[[#This Row],[Returns Rate %2]]-Table3[[#This Row],[FC Cancellation Mix %Shoes]]+Table3[[#This Row],[Exp Shoes PreOrder Growth Rate]]) -> 5297.2973 | AS26: =Table3[[#This Row],[Tommaso''s FC Q2 SS5 Net Sales FC Shoes]]/Table3[[#This Row],[Net Sales Invoiced Shoes]]-1 -> -0.24324324 | AT26: =Table3[[#This Row],[Pre-Orders Booked LYQ2 (apparel)]]*(1+Table3[[#This Row],[Re-Order Rate % FC]]+Table3[[#This Row],[Stock Clearance Rate %2]]+Table3[[#This Row],[Returns Rate %2]]-Table3[[#This Row],[FC Cancellation Mix %Shoes]]+Table3[[#This Row],[Exp Apparel PreOrder Growth Rate]]) -> 2494.2649 | AU26: =Table3[[#This Row],[Tommaso''s FC Q2 SS5 Net Sales FC Apparel]]/Table3[[#This Row],[Net Sales Invoiced Apparel]]-1 -> 0.91866528 | AV26: 10400 | AW26: 213 | AX26: =Table3[[#This Row],[Actual Order Book Shoes ]]/Table3[[#This Row],[Tommaso''s FC Q2 SS5 Net Sales FC Shoes]]-1 -> 0.96326531 | AY26: =Table3[[#This Row],[Actual Order Book Apparel ]]/Table3[[#This Row],[Tommaso''s FC Q2 SS5 Net Sales FC Apparel]]-1 -> -0.9146041 | AZ26: =Table3[[#This Row],[Actual Order Book Shoes ]]/Table3[[#This Row],[Net Sales Invoiced Shoes]]-1 -> 0.48571429 | BA26: =IFERROR(Table3[[#This Row],[Actual Order Book Apparel ]]/Table3[[#This Row],[Net Sales Invoiced Apparel]]-1,"") -> -0.83615385
A27: Europe | B27: Europe | C27: Axiom Street | D27: Growth | E27: 9100 | F27: 0.042 | G27: 1.295 | H27: 0 | I27: 0 | J27: 1000 | K27: 0.196 | L27: 0.883 | M27: 0 | N27: 0 | P27: =IFERROR(E27/(1-F27+G27+H27-I27),0) -> 4039.059 | Q27: =IFERROR(J27/(1+L27+M27-N27-K27),0) -> 592.76823 | R27: =E27+J27 -> 10100 | S27: ='SS24 Q2 Data'!$P18+Q27 -> 109372.7 | T27: =ROUND(P27*F27,0) -> 170 | U27: =ROUND(P27*G27,0) -> 5231 | V27: =ROUND(P27*H27,0) -> 0 | W27: =ROUND(P27*I27,0) -> 0 | X27: =ROUND(Q27*K27,0) -> 116 | Y27: =ROUND(Q27*L27,0) -> 523 | Z27: =ROUND(Q27*M27,0) -> 0 | AA27: =ROUND(Q27*M27,0) -> 0 | AB27: =J27/E27 -> 0.10989011 | AD27: =Table3[[#This Row],[Pre-Order Cancellations Mix Shoes]]+Table3[[#This Row],[Pre-Order Cancellations Mix %Apparel]] -> 286 | AE27: =Table3[[#This Row],[Tot Cancellation]]/Table3[[#This Row],[Tot PreOrder Invoiced (units)]] -> 0.0026149121 | AF27: =Table3[[#This Row],[Re-Order Rate %7]]+Table3[[#This Row],[Re-Order Rate %11]] -> 5754 | AG27: =Table3[[#This Row],[ToT Reorders]]/Table3[[#This Row],[Tot Net Sales Invoiced (units)]] -> 0.56970297 | AH27: =Table3[[#This Row],[Stock Clearance Rate %8]]+Table3[[#This Row],[Stock Clearance Rate %12]] -> 0 | AI27: =Table3[[#This Row],[ToT Stock Clearance]]/Table3[[#This Row],[Tot PreOrder Invoiced (units)]] -> 0 | AJ27: =Table3[[#This Row],[Returns Rate %13]]+Table3[[#This Row],[Returns Rate %9]] -> 0 | AK27: =Table3[[#This Row],[ToT Retruns]]/Table3[[#This Row],[Tot PreOrder Invoiced (units)]] -> 0 | AL27: 0.03 | AM27: 0.15 | AN27: 0.01 | AO27: 0.03 | AP27: =100% -> 1 | AQ27: =IF(Table3[[#This Row],[Re-Order Rate %4]]-Table3[[#This Row],[Pre-Order Cancellations Mix %2]]-Table3[[#This Row],[Returns Rate %6]]<$AQ$1,$AQ$1,Table3[[#This Row],[Re-Order Rate %4]]-Table3[[#This Row],[Pre-Order Cancellations Mix %2]]-Table3[[#This Row],[Returns Rate %6]]) -> 0.687 | AR27: =Table3[[#This Row],[Pre-Orders Booked LYQ2 (shoes)]]*(1+Table3[[#This Row],[Re-Order Rate % FC]]+Table3[[#This Row],[Stock Clearance Rate %2]]+Table3[[#This Row],[Returns Rate %2]]-Table3[[#This Row],[FC Cancellation Mix %Shoes]]+Table3[[#This Row],[Exp Shoes PreOrder Growth Rate]]) -> 8724.3675 | AS27: =Table3[[#This Row],[Tommaso''s FC Q2 SS5 Net Sales FC Shoes]]/Table3[[#This Row],[Net Sales Invoiced Shoes]]-1 -> -0.041278296 | AT27: =Table3[[#This Row],[Pre-Orders Booked LYQ2 (apparel)]]*(1+Table3[[#This Row],[Re-Order Rate % FC]]+Table3[[#This Row],[Stock Clearance Rate %2]]+Table3[[#This Row],[Returns Rate %2]]-Table3[[#This Row],[FC Cancellation Mix %Shoes]]+Table3[[#This Row],[Exp Apparel PreOrder Growth Rate]]) -> 1094.8429 | AU27: =Table3[[#This Row],[Tommaso''s FC Q2 SS5 Net Sales FC Apparel]]/Table3[[#This Row],[Net Sales Invoiced Apparel]]-1 -> 0.094842916 | AV27: 21900 | AW27: 2345 | AX27: =Table3[[#This Row],[Actual Order Book Shoes ]]/Table3[[#This Row],[Tommaso''s FC Q2 SS5 Net Sales FC Shoes]]-1 -> 1.5102106 | AY27: =Table3[[#This Row],[Actual Order Book Apparel ]]/Table3[[#This Row],[Tommaso''s FC Q2 SS5 Net Sales FC Apparel]]-1 -> 1.1418598 | AZ27: =Table3[[#This Row],[Actual Order Book Shoes ]]/Table3[[#This Row],[Net Sales Invoiced Shoes]]-1 -> 1.4065934 | BA27: =IFERROR(Table3[[#This Row],[Actual Order Book Apparel ]]/Table3[[#This Row],[Net Sales Invoiced Apparel]]-1,"") -> 1.345
A28: South | B28: Spain | C28: Aurelian & Co. | E28: 25400 | F28: 0.011 | G28: 0.161 | H28: 0 | I28: 0 | J28: 5400 | K28: 0.064 | L28: 0 | M28: 0 | N28: 0 | P28: =IFERROR(E28/(1-F28+G28+H28-I28),0) -> 22086.957 | Q28: =IFERROR(J28/(1+L28+M28-N28-K28),0) -> 5769.2308 | R28: =E28+J28 -> 30800 | S28: ='SS24 Q2 Data'!$P15+Q28 -> 7464.146 | T28: =ROUND(P28*F28,0) -> 243 | U28: =ROUND(P28*G28,0) -> 3556 | V28: =ROUND(P28*H28,0) -> 0 | W28: =ROUND(P28*I28,0) -> 0 | X28: =ROUND(Q28*K28,0) -> 369 | Y28: =ROUND(Q28*L28,0) -> 0 | Z28: =ROUND(Q28*M28,0) -> 0 | AA28: =ROUND(Q28*M28,0) -> 0 | AB28: =J28/E28 -> 0.21259843 | AD28: =Table3[[#This Row],[Pre-Order Cancellations Mix Shoes]]+Table3[[#This Row],[Pre-Order Cancellations Mix %Apparel]] -> 612 | AE28: =Table3[[#This Row],[Tot Cancellation]]/Table3[[#This Row],[Tot PreOrder Invoiced (units)]] -> 0.081991965 | AF28: =Table3[[#This Row],[Re-Order Rate %7]]+Table3[[#This Row],[Re-Order Rate %11]] -> 3556 | AG28: =Table3[[#This Row],[ToT Reorders]]/Table3[[#This Row],[Tot Net Sales Invoiced (units)]] -> 0.11545455 | AH28: =Table3[[#This Row],[Stock Clearance Rate %8]]+Table3[[#This Row],[Stock Clearance Rate %12]] -> 0 | AI28: =Table3[[#This Row],[ToT Stock Clearance]]/Table3[[#This Row],[Tot PreOrder Invoiced (units)]] -> 0 | AJ28: =Table3[[#This Row],[Returns Rate %13]]+Table3[[#This Row],[Returns Rate %9]] -> 0 | AK28: =Table3[[#This Row],[ToT Retruns]]/Table3[[#This Row],[Tot PreOrder Invoiced (units)]] -> 0 | AL28: 0.03 | AM28: 0.15 | AN28: 0.01 | AO28: 0.03 | AP28: =$AQ$2 -> 0.25 | AQ28: =IF(Table3[[#This Row],[Re-Order Rate %4]]-Table3[[#This Row],[Pre-Order Cancellations Mix %2]]-Table3[[#This Row],[Returns Rate %6]]<$AQ$1,$AQ$1,Table3[[#This Row],[Re-Order Rate %4]]-Table3[[#This Row],[Pre-Order Cancellations Mix %2]]-Table3[[#This Row],[Returns Rate %6]]) -> 0.68 | AR28: =Table3[[#This Row],[Pre-Orders Booked LYQ2 (shoes)]]*(1+Table3[[#This Row],[Re-Order Rate % FC]]+Table3[[#This Row],[Stock Clearance Rate %2]]+Table3[[#This Row],[Returns Rate %2]]-Table3[[#This Row],[FC Cancellation Mix %Shoes]]+Table3[[#This Row],[Exp Shoes PreOrder Growth Rate]]) -> 31142.609 | AS28: =Table3[[#This Row],[Tommaso''s FC Q2 SS5 Net Sales FC Shoes]]/Table3[[#This Row],[Net Sales Invoiced Shoes]]-1 -> 0.22608696 | AT28: =Table3[[#This Row],[Pre-Orders Booked LYQ2 (apparel)]]*(1+Table3[[#This Row],[Re-Order Rate % FC]]+Table3[[#This Row],[Stock Clearance Rate %2]]+Table3[[#This Row],[Returns Rate %2]]-Table3[[#This Row],[FC Cancellation Mix %Shoes]]+Table3[[#This Row],[Exp Apparel PreOrder Growth Rate]]) -> 10615.385 | AU28: =Table3[[#This Row],[Tommaso''s FC Q2 SS5 Net Sales FC Apparel]]/Table3[[#This Row],[Net Sales Invoiced Apparel]]-1 -> 0.96581197 | AV28: 10700 | AW28: 1532 | AX28: =Table3[[#This Row],[Actual Order Book Shoes ]]/Table3[[#This Row],[Tommaso''s FC Q2 SS5 Net Sales FC Shoes]]-1 -> -0.65641928 | AY28: =Table3[[#This Row],[Actual Order Book Apparel ]]/Table3[[#This Row],[Tommaso''s FC Q2 SS5 Net Sales FC Apparel]]-1 -> -0.85568116 | AZ28: =Table3[[#This Row],[Actual Order Book Shoes ]]/Table3[[#This Row],[Net Sales Invoiced Shoes]]-1 -> -0.57874016 | BA28: =IFERROR(Table3[[#This Row],[Actual Order Book Apparel ]]/Table3[[#This Row],[Net Sales Invoiced Apparel]]-1,"") -> -0.7162963
A29: Central | B29: Germany | C29: Hanover & Hearth | E29: 19400 | F29: 0 | G29: 0 | H29: 0 | I29: 0 | J29: 1600 | K29: 0 | L29: 0 | M29: 0 | N29: 0 | P29: =IFERROR(E29/(1-F29+G29+H29-I29),0) -> 19400 | Q29: =IFERROR(J29/(1+L29+M29-N29-K29),0) -> 1600 | R29: =E29+J29 -> 21000 | S29: ='SS24 Q2 Data'!$P17+Q29 -> 231556.9 | T29: =ROUND(P29*F29,0) -> 0 | U29: =ROUND(P29*G29,0) -> 0 | V29: =ROUND(P29*H29,0) -> 0 | W29: =ROUND(P29*I29,0) -> 0 | X29: =ROUND(Q29*K29,0) -> 0 | Y29: =ROUND(Q29*L29,0) -> 0 | Z29: =ROUND(Q29*M29,0) -> 0 | AA29: =ROUND(Q29*M29,0) -> 0 | AB29: =J29/E29 -> 0.082474227 | AD29: =Table3[[#This Row],[Pre-Order Cancellations Mix Shoes]]+Table3[[#This Row],[Pre-Order Cancellations Mix %Apparel]] -> 0 | AE29: =Table3[[#This Row],[Tot Cancellation]]/Table3[[#This Row],[Tot PreOrder Invoiced (units)]] -> 0 | AF29: =Table3[[#This Row],[Re-Order Rate %7]]+Table3[[#This Row],[Re-Order Rate %11]] -> 0 | AG29: =Table3[[#This Row],[ToT Reorders]]/Table3[[#This Row],[Tot Net Sales Invoiced (units)]] -> 0 | AH29: =Table3[[#This Row],[Stock Clearance Rate %8]]+Table3[[#This Row],[Stock Clearance Rate %12]] -> 0 | AI29: =Table3[[#This Row],[ToT Stock Clearance]]/Table3[[#This Row],[Tot PreOrder Invoiced (units)]] -> 0 | AJ29: =Table3[[#This Row],[Returns Rate %13]]+Table3[[#This Row],[Returns Rate %9]] -> 0 | AK29: =Table3[[#This Row],[ToT Retruns]]/Table3[[#This Row],[Tot PreOrder Invoiced (units)]] -> 0 | AL29: 0.03 | AM29: 0.15 | AN29: 0.01 | AO29: 0.03 | AP29: =$AQ$2 -> 0.25 | AQ29: =IF(Table3[[#This Row],[Re-Order Rate %4]]-Table3[[#This Row],[Pre-Order Cancellations Mix %2]]-Table3[[#This Row],[Returns Rate %6]]<$AQ$1,$AQ$1,Table3[[#This Row],[Re-Order Rate %4]]-Table3[[#This Row],[Pre-Order Cancellations Mix %2]]-Table3[[#This Row],[Returns Rate %6]]) -> 0.68 | AR29: =Table3[[#This Row],[Pre-Orders Booked LYQ2 (shoes)]]*(1+Table3[[#This Row],[Re-Order Rate % FC]]+Table3[[#This Row],[Stock Clearance Rate %2]]+Table3[[#This Row],[Returns Rate %2]]-Table3[[#This Row],[FC Cancellation Mix %Shoes]]+Table3[[#This Row],[Exp Shoes PreOrder Growth Rate]]) -> 27354 | AS29: =Table3[[#This Row],[Tommaso''s FC Q2 SS5 Net Sales FC Shoes]]/Table3[[#This Row],[Net Sales Invoiced Shoes]]-1 -> 0.41 | AT29: =Table3[[#This Row],[Pre-Orders Booked LYQ2 (apparel)]]*(1+Table3[[#This Row],[Re-Order Rate % FC]]+Table3[[#This Row],[Stock Clearance Rate %2]]+Table3[[#This Row],[Returns Rate %2]]-Table3[[#This Row],[FC Cancellation Mix %Shoes]]+Table3[[#This Row],[Exp Apparel PreOrder Growth Rate]]) -> 2944 | AU29: =Table3[[#This Row],[Tommaso''s FC Q2 SS5 Net Sales FC Apparel]]/Table3[[#This Row],[Net Sales Invoiced Apparel]]-1 -> 0.84 | AV29: 14800 | AW29: 4095 | AX29: =Table3[[#This Row],[Actual Order Book Shoes ]]/Table3[[#This Row],[Tommaso''s FC Q2 SS5 Net Sales FC Shoes]]-1 -> -0.45894568 | AY29: =Table3[[#This Row],[Actual Order Book Apparel ]]/Table3[[#This Row],[Tommaso''s FC Q2 SS5 Net Sales FC Apparel]]-1 -> 0.39096467 | AZ29: =Table3[[#This Row],[Actual Order Book Shoes ]]/Table3[[#This Row],[Net Sales Invoiced Shoes]]-1 -> -0.2371134 | BA29: =IFERROR(Table3[[#This Row],[Actual Order Book Apparel ]]/Table3[[#This Row],[Net Sales Invoiced Apparel]]-1,"") -> 1.559375

Sheet Pivot SS24Q2 Summary
B3: Row Labels | C3: Sum of Tot Cancellation | D3: Sum of ToT Stock Clearance | E3: Sum of ToT Reorders | F3: Sum of ToT Retruns | G3: Sum of Net Sales Invoiced Shoes | H3: Sum of Net Sales Invoiced Apparel | I3: Sum of Tot Net Sales Invoiced (units) | J3: Average of Apparel vs Shoes Sell/Out
B4: Field Accounts | C4: 35804 | D4: 6189 | E4: 115231 | F4: 14559 | G4: 368300 | H4: 27900 | I4: 396200 | J4: 0.11267453 | M4: Weighted Averages
B5: Scale | C5: 15906 | D5: 0 | E5: 1004 | F5: 2530 | G5: 213400 | H5: 24300 | I5: 237700 | J5: 0.11387067 | M5: Shoes | N5: Apparel | O5: Total
B6: Vault | C6: 10117 | D6: 0 | E6: 1849 | F6: 5113 | G6: 95400 | H6: 0 | I6: 95400 | J6: 0 | L6: Net Sales Invoiced | M6: 785600 | N6: 64550 | O6: =SUM(M6:N6) -> 850150
B7: Titan Sport | C7: 56997 | D7: 0 | E7: 0 | F7: 4331 | G7: 36000 | H7: 2700 | I7: 38700 | J7: 0.075 | L7: Cancellations % | M7: 0.13712505 | N7: 0.17246251 | O7: =SUMPRODUCT(M7:N7,$M$6:$N$6)/$O$6 -> 0.13980815 | Q7: Investigate high Cancellation, specifically in Apparel Category
B8: Aurelian & Co. | C8: 612 | D8: 0 | E8: 3556 | F8: 0 | G8: 25400 | H8: 5400 | I8: 30800 | J8: 0.21259843 | L8: Re-Order Rate % | M8: 0.14914765 | N8: 0.14708894 | O8: =SUMPRODUCT(M8:N8,$M$6:$N$6)/$O$6 -> 0.14899134 | Q8: Push for lowering in season re-order to 10% to have a leaner warehouse
B9: Hanover & Hearth | C9: 0 | D9: 0 | E9: 0 | F9: 0 | G9: 19400 | H9: 1600 | I9: 21000 | J9: 0.082474227 | L9: Stock Clearance% | M9: 0.011346493 | N9: 0.0021136871 | O9: =SUMPRODUCT(M9:N9,$M$6:$N$6)/$O$6 -> 0.010645467 | Q9: Clearance in Apparel still low due being new products in the market, monitor
B10: Axiom Street | C10: 286 | D10: 0 | E10: 5754 | F10: 0 | G10: 9100 | H10: 1000 | I10: 10100 | J10: 0.10989011 | L10: Returns% | M10: 0.033306571 | N10: 0.042690528 | O10: =SUMPRODUCT(M10:N10,$M$6:$N$6)/$O$6 -> 0.034019074 | Q10: Return in Apparel Naturally Higher due to high SKUs, helthy below 6%
B11: Velocity Labs | C11: 242 | D11: 2960 | E11: 22 | F11: 0 | G11: 7000 | H11: 1300 | I11: 8300 | J11: 0.18571429
B12: Swift-Pulse | C12: 245 | D12: 0 | E12: 251 | F12: 0 | G12: 6800 | H12: 0 | I12: 6800 | J12: 0
B13: Vanguard Wilds | C13: 0 | D13: 0 | E13: 0 | F13: 0 | G13: 2000 | H13: 250 | I13: 2250 | J13: 0.125
B14: Strike-Point | C14: 0 | D14: 0 | E14: 0 | F14: 0 | G14: 1200 | H14: 0 | I14: 1200 | J14: 0
B15: Nordic Nord | C15: 24 | D15: 0 | E15: 508 | F15: 1 | G15: 900 | H15: 0 | I15: 900 | J15: 0
B16: Omni-Arena | C16: 492 | D16: 0 | E16: 279 | F16: 0 | G16: 400 | H16: 100 | I16: 500 | J16: 0.25
B17: Agora Athletics | C17: 0 | D17: 0 | E17: 58 | F17: 42 | G17: 300 | H17: 0 | I17: 300 | J17: 0
B18: Velvet & Vice | C18: 0 | D18: 0 | E18: 0 | F18: 0 | G18: 1e-09 | H18: 0 | I18: 1e-09 | J18: 0
B19: Grand Total | C19: 120725 | D19: 9149 | E19: 128512 | F19: 26576 | G19: 785600 | H19: 64550 | I19: 850150 | J19: 0.094287759

Sheet Actual vs Budget 
I1: Weighted ASP | AU1: =VLOOKUP('Hypotesis Panel'!$G$8,'Hypotesis Panel'!$C$15:$E$41,3,FALSE) -> 0.65 | BP1: Reasoning example: Proportion used below
B2: Total | F2: =SUM(F5:F27) -> 1.4742101e+08 | G2: =SUM(G5:G27) -> 2441900 | I2: =SUMPRODUCT(I5:I27,F5:F27)/SUM(F5:F27) -> 60.745906 | J2: =SUM(J5:J27) -> 2241257.6 | K2: =SUM(K5:K27) -> 200642.37 | L2: =SUM(L5:L27) -> 79543186 | M2: =SUM(M5:M27) -> 1155142 | N2: =SUM(N5:N27) -> 1141982 | O2: =SUMPRODUCT(Table1[Actual ASP Shoes per channel],Table1[Net Sales Units])/SUM(Table1[Net Sales Units]) -> 69.653625 | P2: =SUM(P5:P27) -> 111458 | Q2: =SUMPRODUCT(Table1[Can%],Table1[Pre-Orders Invoiced (units)])/SUM(Table1[Pre-Orders Invoiced (units)]) -> 0.09648857 | R2: =SUM(R5:R27) -> 97267 | T2: =SUM(T5:T27) -> 27786 | V2: =SUM(V5:V27) -> -26755 | X2: =SUM(X5:X27) -> 7396255.5 | Y2: =SUM(Y5:Y27) -> 166045.44 | Z2: =SUMPRODUCT(Z5:Z27,X5:X27)/SUM(X5:X27) -> 45.24228 | AA2: =SUM(AA5:AA27) -> 155592.14 | AB2: =SUM(AB5:AB27) -> 14817.2 | AD2: =SUM(AD5:AD27) -> 3277.5 | AF2: =SUM(AF5:AF27) -> 27786 | AH2: =SUM(AH5:AH27) -> -5793 | AL2: =SUM(Table1[Net Sales EUR)]) -> 86939441 | AM2: =SUM(AM5:AM27) -> 748800 | AN2: =SUM(AN5:AN27) -> 100381 | AO2: =SUM(AO5:AO27) -> 1141982 | AP2: =SUMPRODUCT(AP5:AP27,Table1[Actual Net Sales(units) Shoes])/SUM(Table1[Actual Net Sales(units) Shoes]) -> 69.653625 | AQ2: =SUM(AQ5:AQ27) -> 166045.44 | AR2: =SUMPRODUCT(AR5:AR27,Table1[Actual Net Sales(units) Shoes])/SUM(Table1[Actual Net Sales(units) Shoes]) -> 39.063173 | AT2: =SUM(AT5:AT27) -> 86939441 | AU2: =SUM(AU5:AU27) -> 95823657 | AV2: =(L2+X2)/AU2-1 -> -0.092714216 | AZ2: =SUM(AZ5:AZ27) -> 87950163 | BA2: =L2/AZ2-1 -> -0.095587959 | BB2: =AZ2/AT2 -> 1.0116256 | BC2: =BB2*BA2*10000 -> -966.99224 | BE2: =SUM(BE5:BE27) -> 7873494.2 | BF2: =X2/BE2-1 -> -0.060613326 | BG2: =BE2/AU2 -> 0.082166497 | BH2: =BG2*BF2*10000 -> -49.803847 | BN2: 0.57 | BP2: 14 weeks | BQ2: 1 | BR2: x
F3: SS25 Budget | L3: Q1 - Actuals - Shoes | X3: Q1 - Actuals - Apparel | AJ3: Q1 Actuals | AM3: Q2 Shoes | AN3: Q2 Apparel | AO3: GNT Q1 Actuals | AZ3: Actual vs Phased Splitted by Category | BP3: In which week we will finish stock at this rate? | CA3: =SUM(Table1[[Shoes Available Q2 Stock Current Season ]]) -> 973441 | CB3: =SUM(Table1[Shoes Available Q2 Stock Old Season]) -> 584065 | CC3: =SUM(Table1[Avg Apparel Q1 Weekly Sales2]) -> 11860.389 | CD3: =SUM(Table1[Apparel Q2 Available Stock Current Season 2]) -> 145551 | CE3: =SUM(Table1[Apparel Q2Available Stock Old Season3]) -> 40753
A4: Sub Region | B4: Market | C4: Account | D4: Concat Support | E4: Client Vertical | F4: Value (€) | G4: Units | H4: % Budget share | I4: Exp ASP | J4: Shoe Budget Units | K4: Apparel Budget Units | L4: Net Sales (€) | M4: Pre-Orders Invoiced (units) | N4: Net Sales Units | O4: Actual ASP Shoes per channel | P4: Cancellations (units) | Q4: Can% | R4: Re-Orders Invoiced (units) | S4: ReOrder % | T4: Stock Clearance Invoiced (units) | U4: Stock Clearance % | V4: Returns Processed (units) | W4: Retunrs % Units | X4: Net Sales (€)2 | Y4: Net Sales (Units0 | Z4: Actual ASP Apparel per channel | AA4: Pre-Orders Invoiced (units)3 | AB4: Cancellations (units)4 | AC4: Can%2 | AD4: Re-Orders Invoiced (units)5 | AE4: Re-Orders Invoiced (units)6 | AF4: Stock Clearance Invoiced (units)6 | AG4: Stock Clearance Invoiced (units)7 | AH4: Returns Processed (units)7 | AI4: Returns Processed (units)8 | AJ4: App/Shoes Split | AK4: Net Sales Units total | AL4: Net Sales EUR) | AM4: Orderbook (units) | AN4: Orderbook (units)8 | AO4: Actual Net Sales(units) Shoes | AP4: Actual ASP (shoes) | AQ4: Actual Net Sales(units)Apparel | AR4: Actual ASP (Apparel) | AS4: Column2 | AT4: STD Actuals SS25 | AU4: SS25 Phased Budget | AV4: vs Phased Plan | AW4: CtC | AX4: CTC (bps) | AY4: Column1 | AZ4: Exp Phased Q1 Shoes | BA4: vs Phased Plan15 | BB4: CtC16 | BC4: CtC (bps)17 | BD4: Column18 | BE4: Exp Phased Q1 Apparel | BF4: vs Phased Plan19 | BG4: CtC20 | BH4: CtC (bps)21 | BI4: CtC (bps)22 | BJ4: ST% Shoes | BK4: ST% Apparel | BL4: ST% ToTal | BM4: Avg Shoes Q1 Weekly Sales | BN4: Expected WoOS Shoes | BO4: Avg Apparel Q1 Weekly Sales | BP4: Expected WoOS Apparel | BQ4: Expected WoOS Total | BR4: WOCoverage Shoes | BS4: WOC Apparel | BT4: WOC Total | BU4: WOS at WK26 Shoes | BV4: Risk Shoes | BW4: Euro | BX4: WOS at WK26 Apparel | BY4: Risk Apparel | BZ4: Column3 | CA4: Shoes Available Q2 Stock Current Season | CB4: Shoes Available Q2 Stock Old Season | CC4: Avg Apparel Q1 Weekly Sales2 | CD4: Apparel Q2 Available Stock Current Season 2 | CE4: Apparel Q2Available Stock Old Season3 | CF4: Q2 Shoes New Stock WOC based on Q1 Sales Velocity | CG4: Q2 Shoes Old Stock WOC based on Q1 Sales Velocity | CH4: ToT Q2 WOC Shoes | CI4: Q2 Apparel New Stock WOC based on Q1 Sales Velocity | CJ4: Q2 Apparel Old Stock WOC based on Q1 Sales Velocity | CK4: Tot Q2 WoC Apparel
A5: Central | B5: Germany | C5: Field Accounts | D5: =_xlfn.CONCAT(Table1[[#This Row],[Sub Region]:[Account]]) -> CentralGermanyField Accounts | E5: =_xlfn.IFNA(VLOOKUP(Table1[[#This Row],[Account]],'Account Information'!$A$4:$B$18,2,FALSE),"") -> Field Accounts | F5: 36200171 | G5: 574000 | H5: =Table1[[#This Row],[Units]]/$G$2 -> 0.23506286 | I5: =F5/G5 -> 63.0665 | J5: =Table1[[#This Row],[Units]]*(1-'Hypotesis Panel'!$F$46) -> 526836.43 | K5: =Table1[[#This Row],[Units]]-Table1[[#This Row],[Shoe Budget Units]] -> 47163.569 | L5: 20914157 | M5: 279800 | N5: =Table1[[#This Row],[Pre-Orders Invoiced (units)]]-Table1[[#This Row],[Cancellations (units)]]+Table1[[#This Row],[Re-Orders Invoiced (units)]]+Table1[[#This Row],[Stock Clearance Invoiced (units)]]+Table1[[#This Row],[Returns Processed (units)]] -> 299000 | O5: =Table1[[#This Row],[Net Sales (€)]]/Table1[[#This Row],[Net Sales Units]] -> 69.947013 | P5: 13700 | Q5: =Table1[[#This Row],[Cancellations (units)]]/Table1[[#This Row],[Pre-Orders Invoiced (units)]] -> 0.048963545 | R5: 34200 | S5: =Table1[[#This Row],[Re-Orders Invoiced (units)]]/Table1[[#This Row],[Pre-Orders Invoiced (units)]] -> 0.12223016 | T5: 4300 | U5: =Table1[[#This Row],[Stock Clearance Invoiced (units)]]/Table1[[#This Row],[Pre-Orders Invoiced (units)]] -> 0.01536812 | V5: -5600 | W5: =Table1[[#This Row],[Returns Processed (units)]]/Table1[[#This Row],[Pre-Orders Invoiced (units)]] -> -0.020014296 | X5: 1932331.3 | Y5: =Table1[[#This Row],[Pre-Orders Invoiced (units)3]]-Table1[[#This Row],[Cancellations (units)4]]+Table1[[#This Row],[Re-Orders Invoiced (units)5]]+Table1[[#This Row],[Stock Clearance Invoiced (units)6]]+Table1[[#This Row],[Returns Processed (units)7]] -> 42160 | Z5: =Table1[[#This Row],[Net Sales (€)2]]/Table1[[#This Row],[Net Sales (Units0]] -> 45.833286 | AA5: 41970 | AB5: 3456 | AC5: =IFERROR(Table1[[#This Row],[Cancellations (units)4]]/Table1[[#This Row],[Pre-Orders Invoiced (units)3]],0) -> 0.082344532 | AD5: 546 | AE5: =IFERROR(Table1[[#This Row],[Re-Orders Invoiced (units)5]]/Table1[[#This Row],[Pre-Orders Invoiced (units)3]],0) -> 0.013009292 | AF5: 4300 | AG5: =IFERROR(Table1[[#This Row],[Stock Clearance Invoiced (units)6]]/Table1[[#This Row],[Pre-Orders Invoiced (units)3]],0) -> 0.10245413 | AH5: -1200 | AI5: =IFERROR(Table1[[#This Row],[Returns Processed (units)7]]/Table1[[#This Row],[Pre-Orders Invoiced (units)3]],0) -> -0.028591851 | AJ5: =Table1[[#This Row],[Net Sales (€)2]]/Table1[[#This Row],[Net Sales (€)]] -> 0.09239346 | AK5: =Table1[[#This Row],[Net Sales (Units0]]+Table1[[#This Row],[Net Sales Units]] -> 341160 | AL5: =Table1[[#This Row],[Net Sales (€)2]]+Table1[[#This Row],[Net Sales (€)]] -> 22846488 | AM5: 115000 | AN5: 20342 | AO5: =Table1[[#This Row],[Pre-Orders Invoiced (units)]]-Table1[[#This Row],[Cancellations (units)]]+Table1[[#This Row],[Re-Orders Invoiced (units)]]+Table1[[#This Row],[Stock Clearance Invoiced (units)]]+Table1[[#This Row],[Returns Processed (units)]] -> 299000 | AP5: =Table1[[#This Row],[Net Sales (€)]]/AO5 -> 69.947013 | AQ5: =AA5-+AB5+Table1[[#This Row],[Re-Orders Invoiced (units)5]]+AF5+AH5 -> 42160 | AR5: =IFERROR(Table1[[#This Row],[Net Sales (€)2]]/AQ5,"") -> 45.833286 | AT5: =L5+X5 -> 22846488 | AU5: =F5*$AU$1 -> 23530111 | AV5: =AT5/AU5-1 -> -0.029053111 | AW5: =AU5/$AU$2 -> 0.24555639 | AX5: =ROUND(AW5*AV5*10000,0) -> -71 | AZ5: =AU5*(1-'SS24 Q2 Data'!$AB$5) -> 21596724 | BA5: =L5/AZ5-1 -> -0.031605138 | BB5: =AZ5/$AZ$2 -> 0.24555639 | BC5: =BB5*BA5*10000 -> -77.608435 | BE5: =AU5*'SS24 Q2 Data'!$AB$5 -> 1933386.8 | BF5: =X5/BE5-1 -> -0.00054592383 | BG5: =BE5/$BE$2 -> 0.24555639 | BH5: =BG5*BF5*10000 -> -1.3405508 | BJ5: =Table1[[#This Row],[Net Sales Units]]/Table1[[#This Row],[Shoe Budget Units]] -> 0.56753858 | BK5: =Table1[[#This Row],[Net Sales (Units0]]/Table1[[#This Row],[Apparel Budget Units]] -> 0.89391029 | BL5: =Table1[[#This Row],[Net Sales Units total]]/Table1[[#This Row],[Units]] -> 0.5943554 | BM5: =ROUND(Table1[[#This Row],[Net Sales Units]]/'Hypotesis Panel'!$G$8,0) -> 21357 | BN5: =ROUND('Hypotesis Panel'!$G$8/Table1[[#This Row],[ST% Shoes]],0) -> 25 | BO5: =Table1[[#This Row],[Net Sales (Units0]]/'Hypotesis Panel'!$G$8 -> 3011.4286 | BP5: =IFERROR(ROUND('Hypotesis Panel'!$G$8/Table1[[#This Row],[ST% Apparel]],0),"NoStock") -> 16 | BQ5: =IFERROR(ROUND('Hypotesis Panel'!$G$8/Table1[[#This Row],[ST% ToTal]],0),"") -> 24 | BR5: =Table1[[#This Row],[Expected WoOS Shoes]]-'Hypotesis Panel'!$G$8 -> 11 | BS5: =IFERROR(Table1[[#This Row],[Expected WoOS Apparel]]-'Hypotesis Panel'!$G$8,"") -> 2 | BT5: =Table1[[#This Row],[Expected WoOS Total]]-'Hypotesis Panel'!$G$8 -> 10 | BU5: =Table1[[#This Row],[WOCoverage Shoes]]+'Hypotesis Panel'!$G$8-'Hypotesis Panel'!$F$3 -> -1 | BV5: =_xlfn.XLOOKUP(Table1[[#This Row],[WOS at WK26 Shoes]],Table2[Lower Bound],Table2[Action],,-1) -> Stock Out Risk | BW5: =IF(Table1[[#This Row],[WOS at WK26 Shoes]]*Table1[[#This Row],[Avg Shoes Q1 Weekly Sales]]*Table1[[#This Row],[Actual ASP Shoes per channel]]>0,0,Table1[[#This Row],[WOS at WK26 Shoes]]*Table1[[#This Row],[Avg Shoes Q1 Weekly Sales]]*Table1[[#This Row],[Actual ASP Shoes per channel]]) -> -1493858.4 | BX5: =Table1[[#This Row],[WOC Apparel]]+'Hypotesis Panel'!$G$8-'Hypotesis Panel'!$F$3 -> -10 | BY5: =_xlfn.XLOOKUP(Table1[[#This Row],[WOS at WK26 Apparel]],Table2[Lower Bound],Table2[Action],,-1) -> Stock Out Risk | CA5: =ROUND(Table1[[#This Row],[% Budget share]]*'Available Stock'!$H$6,0) -> 228820 | CB5: =ROUND(Table1[[#This Row],[% Budget share]]*'Available Stock'!$I$6,0) -> 137292 | CC5: =Table1[[#This Row],[Net Sales (Units0]]/'Hypotesis Panel'!$G$8 -> 3011.4286 | CD5: =ROUND(Table1[[#This Row],[% Budget share]]*'Available Stock'!$H$7,0) -> 34214 | CE5: =ROUND(Table1[[#This Row],[% Budget share]]*'Available Stock'!$I$7,0) -> 9580 | CF5: =Table1[[#This Row],[Shoes Available Q2 Stock Current Season ]]/#REF! -> #REF! | CG5: =Table1[[#This Row],[Shoes Available Q2 Stock Old Season]]/#REF! -> #REF! | CH5: =SUM(Table1[[#This Row],[Q2 Shoes New Stock WOC based on Q1 Sales Velocity]:[Q2 Shoes Old Stock WOC based on Q1 Sales Velocity]]) -> #REF! | CI5: =IFERROR(Table1[[#This Row],[Apparel Q2 Available Stock Current Season 2]]/Table1[[#This Row],[Avg Apparel Q1 Weekly Sales2]],"") -> 11.361385 | CJ5: =IFERROR(Table1[[#This Row],[Apparel Q2Available Stock Old Season3]]/Table1[[#This Row],[Avg Apparel Q1 Weekly Sales2]],"") -> 3.1812144 | CK5: =SUM(Table1[[#This Row],[Q2 Apparel New Stock WOC based on Q1 Sales Velocity]:[Q2 Apparel Old Stock WOC based on Q1 Sales Velocity]]) -> 14.5426
A6: Europe | B6: Europe | C6: Scale | D6: =_xlfn.CONCAT(Table1[[#This Row],[Sub Region]:[Account]]) -> EuropeEuropeScale | E6: =_xlfn.IFNA(VLOOKUP(Table1[[#This Row],[Account]],'Account Information'!$A$4:$B$18,2,FALSE),"") -> Lifestyle | F6: 25799200 | G6: 476000 | H6: =Table1[[#This Row],[Units]]/$G$2 -> 0.19493018 | I6: =F6/G6 -> 54.2 | J6: =Table1[[#This Row],[Units]]*(1-'Hypotesis Panel'!$F$46) -> 436888.75 | K6: =Table1[[#This Row],[Units]]-Table1[[#This Row],[Shoe Budget Units]] -> 39111.253 | L6: 12384334 | M6: 205000 | N6: =Table1[[#This Row],[Pre-Orders Invoiced (units)]]-Table1[[#This Row],[Cancellations (units)]]+Table1[[#This Row],[Re-Orders Invoiced (units)]]+Table1[[#This Row],[Stock Clearance Invoiced (units)]]+Table1[[#This Row],[Returns Processed (units)]] -> 184300 | O6: =Table1[[#This Row],[Net Sales (€)]]/Table1[[#This Row],[Net Sales Units]] -> 67.196604 | P6: 30000 | Q6: =Table1[[#This Row],[Cancellations (units)]]/Table1[[#This Row],[Pre-Orders Invoiced (units)]] -> 0.14634146 | R6: 9300 | S6: =Table1[[#This Row],[Re-Orders Invoiced (units)]]/Table1[[#This Row],[Pre-Orders Invoiced (units)]] -> 0.045365854 | T6: 0 | U6: =Table1[[#This Row],[Stock Clearance Invoiced (units)]]/Table1[[#This Row],[Pre-Orders Invoiced (units)]] -> 0 | V6: 0 | W6: =Table1[[#This Row],[Returns Processed (units)]]/Table1[[#This Row],[Pre-Orders Invoiced (units)]] -> 0 | X6: 1086705 | Y6: =Table1[[#This Row],[Pre-Orders Invoiced (units)3]]-Table1[[#This Row],[Cancellations (units)4]]+Table1[[#This Row],[Re-Orders Invoiced (units)5]]+Table1[[#This Row],[Stock Clearance Invoiced (units)6]]+Table1[[#This Row],[Returns Processed (units)7]] -> 27297 | Z6: =Table1[[#This Row],[Net Sales (€)2]]/Table1[[#This Row],[Net Sales (Units0]] -> 39.810419 | AA6: 30750 | AB6: 3453 | AC6: =IFERROR(Table1[[#This Row],[Cancellations (units)4]]/Table1[[#This Row],[Pre-Orders Invoiced (units)3]],0) -> 0.11229268 | AD6: 0 | AE6: =IFERROR(Table1[[#This Row],[Re-Orders Invoiced (units)5]]/Table1[[#This Row],[Pre-Orders Invoiced (units)3]],0) -> 0 | AF6: 0 | AG6: =IFERROR(Table1[[#This Row],[Stock Clearance Invoiced (units)6]]/Table1[[#This Row],[Pre-Orders Invoiced (units)3]],0) -> 0 | AH6: 0 | AI6: =IFERROR(Table1[[#This Row],[Returns Processed (units)7]]/Table1[[#This Row],[Pre-Orders Invoiced (units)3]],0) -> 0 | AJ6: =Table1[[#This Row],[Net Sales (€)2]]/Table1[[#This Row],[Net Sales (€)]] -> 0.087748359 | AK6: =Table1[[#This Row],[Net Sales (Units0]]+Table1[[#This Row],[Net Sales Units]] -> 211597 | AL6: =Table1[[#This Row],[Net Sales (€)2]]+Table1[[#This Row],[Net Sales (€)]] -> 13471039 | AM6: 256100 | AN6: 25435 | AO6: =Table1[[#This Row],[Pre-Orders Invoiced (units)]]-Table1[[#This Row],[Cancellations (units)]]+Table1[[#This Row],[Re-Orders Invoiced (units)]]+Table1[[#This Row],[Stock Clearance Invoiced (units)]]+Table1[[#This Row],[Returns Processed (units)]] -> 184300 | AP6: =Table1[[#This Row],[Net Sales (€)]]/AO6 -> 67.196604 | AQ6: =AA6-+AB6+Table1[[#This Row],[Re-Orders Invoiced (units)5]]+AF6+AH6 -> 27297 | AR6: =IFERROR(Table1[[#This Row],[Net Sales (€)2]]/AQ6,"") -> 39.810419 | AT6: =L6+X6 -> 13471039 | AU6: =F6*$AU$1 -> 16769480 | AV6: =AT6/AU6-1 -> -0.19669309 | AW6: =AU6/$AU$2 -> 0.17500355 | AX6: =ROUND(AW6*AV6*10000,0) -> -344 | AZ6: =AU6*(1-'SS24 Q2 Data'!$AB$5) -> 15391591 | BA6: =L6/AZ6-1 -> -0.19538308 | BB6: =AZ6/$AZ$2 -> 0.17500355 | BC6: =BB6*BA6*10000 -> -341.92732 | BE6: =AU6*'SS24 Q2 Data'!$AB$5 -> 1377889.4 | BF6: =X6/BE6-1 -> -0.21132641 | BG6: =BE6/$BE$2 -> 0.17500355 | BH6: =BG6*BF6*10000 -> -369.82872 | BJ6: =Table1[[#This Row],[Net Sales Units]]/Table1[[#This Row],[Shoe Budget Units]] -> 0.42184653 | BK6: =Table1[[#This Row],[Net Sales (Units0]]/Table1[[#This Row],[Apparel Budget Units]] -> 0.69793214 | BL6: =Table1[[#This Row],[Net Sales Units total]]/Table1[[#This Row],[Units]] -> 0.44453151 | BM6: =ROUND(Table1[[#This Row],[Net Sales Units]]/'Hypotesis Panel'!$G$8,0) -> 13164 | BN6: =ROUND('Hypotesis Panel'!$G$8/Table1[[#This Row],[ST% Shoes]],0) -> 33 | BO6: =Table1[[#This Row],[Net Sales (Units0]]/'Hypotesis Panel'!$G$8 -> 1949.7857 | BP6: =IFERROR(ROUND('Hypotesis Panel'!$G$8/Table1[[#This Row],[ST% Apparel]],0),"NoStock") -> 20 | BQ6: =IFERROR(ROUND('Hypotesis Panel'!$G$8/Table1[[#This Row],[ST% ToTal]],0),"") -> 31 | BR6: =Table1[[#This Row],[Expected WoOS Shoes]]-'Hypotesis Panel'!$G$8 -> 19 | BS6: =IFERROR(Table1[[#This Row],[Expected WoOS Apparel]]-'Hypotesis Panel'!$G$8,"") -> 6 | BT6: =Table1[[#This Row],[Expected WoOS Total]]-'Hypotesis Panel'!$G$8 -> 17 | BU6: =Table1[[#This Row],[WOCoverage Shoes]]+'Hypotesis Panel'!$G$8-'Hypotesis Panel'!$F$3 -> 7 | BV6: =_xlfn.XLOOKUP(Table1[[#This Row],[WOS at WK26 Shoes]],Table2[Lower Bound],Table2[Action],,-1) -> Overstock | BW6: =IF(Table1[[#This Row],[WOS at WK26 Shoes]]*Table1[[#This Row],[Avg Shoes Q1 Weekly Sales]]*Table1[[#This Row],[Actual ASP Shoes per channel]]>0,0,Table1[[#This Row],[WOS at WK26 Shoes]]*Table1[[#This Row],[Avg Shoes Q1 Weekly Sales]]*Table1[[#This Row],[Actual ASP Shoes per channel]]) -> 0 | BX6: =Table1[[#This Row],[WOC Apparel]]+'Hypotesis Panel'!$G$8-'Hypotesis Panel'!$F$3 -> -6 | BY6: =_xlfn.XLOOKUP(Table1[[#This Row],[WOS at WK26 Apparel]],Table2[Lower Bound],Table2[Action],,-1) -> Stock Out Risk | CA6: =ROUND(Table1[[#This Row],[% Budget share]]*'Available Stock'!$H$6,0) -> 189753 | CB6: =ROUND(Table1[[#This Row],[% Budget share]]*'Available Stock'!$I$6,0) -> 113852 | CC6: =Table1[[#This Row],[Net Sales (Units0]]/'Hypotesis Panel'!$G$8 -> 1949.7857 | CD6: =ROUND(Table1[[#This Row],[% Budget share]]*'Available Stock'!$H$7,0) -> 28372 | CE6: =ROUND(Table1[[#This Row],[% Budget share]]*'Available Stock'!$I$7,0) -> 7944 | CF6: =Table1[[#This Row],[Shoes Available Q2 Stock Current Season ]]/#REF! -> #REF! | CG6: =Table1[[#This Row],[Shoes Available Q2 Stock Old Season]]/#REF! -> #REF! | CH6: =SUM(Table1[[#This Row],[Q2 Shoes New Stock WOC based on Q1 Sales Velocity]:[Q2 Shoes Old Stock WOC based on Q1 Sales Velocity]]) -> #REF! | CI6: =IFERROR(Table1[[#This Row],[Apparel Q2 Available Stock Current Season 2]]/Table1[[#This Row],[Avg Apparel Q1 Weekly Sales2]],"") -> 14.551343 | CJ6: =IFERROR(Table1[[#This Row],[Apparel Q2Available Stock Old Season3]]/Table1[[#This Row],[Avg Apparel Q1 Weekly Sales2]],"") -> 4.0742939 | CK6: =SUM(Table1[[#This Row],[Q2 Apparel New Stock WOC based on Q1 Sales Velocity]:[Q2 Apparel Old Stock WOC based on Q1 Sales Velocity]]) -> 18.625637
A7: Europe | B7: Europe | C7: Vault | D7: =_xlfn.CONCAT(Table1[[#This Row],[Sub Region]:[Account]]) -> EuropeEuropeVault | E7: =_xlfn.IFNA(VLOOKUP(Table1[[#This Row],[Account]],'Account Information'!$A$4:$B$18,2,FALSE),"") -> Lifestyle | F7: 16282750 | G7: 275000 | H7: =Table1[[#This Row],[Units]]/$G$2 -> 0.11261722 | I7: =F7/G7 -> 59.21 | J7: =Table1[[#This Row],[Units]]*(1-'Hypotesis Panel'!$F$46) -> 252404.21 | K7: =Table1[[#This Row],[Units]]-Table1[[#This Row],[Shoe Budget Units]] -> 22595.787 | L7: 9595260 | M7: 156500 | N7: =Table1[[#This Row],[Pre-Orders Invoiced (units)]]-Table1[[#This Row],[Cancellations (units)]]+Table1[[#This Row],[Re-Orders Invoiced (units)]]+Table1[[#This Row],[Stock Clearance Invoiced (units)]]+Table1[[#This Row],[Returns Processed (units)]] -> 151500 | O7: =Table1[[#This Row],[Net Sales (€)]]/Table1[[#This Row],[Net Sales Units]] -> 63.33505 | P7: 10000 | Q7: =Table1[[#This Row],[Cancellations (units)]]/Table1[[#This Row],[Pre-Orders Invoiced (units)]] -> 0.063897764 | R7: 5000 | S7: =Table1[[#This Row],[Re-Orders Invoiced (units)]]/Table1[[#This Row],[Pre-Orders Invoiced (units)]] -> 0.031948882 | T7: 0 | U7: =Table1[[#This Row],[Stock Clearance Invoiced (units)]]/Table1[[#This Row],[Pre-Orders Invoiced (units)]] -> 0 | V7: 0 | W7: =Table1[[#This Row],[Returns Processed (units)]]/Table1[[#This Row],[Pre-Orders Invoiced (units)]] -> 0 | X7: 0 | Y7: =Table1[[#This Row],[Pre-Orders Invoiced (units)3]]-Table1[[#This Row],[Cancellations (units)4]]+Table1[[#This Row],[Re-Orders Invoiced (units)5]]+Table1[[#This Row],[Stock Clearance Invoiced (units)6]]+Table1[[#This Row],[Returns Processed (units)7]] -> 0 | AA7: 0 | AB7: 0 | AC7: =IFERROR(Table1[[#This Row],[Cancellations (units)4]]/Table1[[#This Row],[Pre-Orders Invoiced (units)3]],0) -> 0 | AD7: 0 | AE7: =IFERROR(Table1[[#This Row],[Re-Orders Invoiced (units)5]]/Table1[[#This Row],[Pre-Orders Invoiced (units)3]],0) -> 0 | AF7: 0 | AG7: =IFERROR(Table1[[#This Row],[Stock Clearance Invoiced (units)6]]/Table1[[#This Row],[Pre-Orders Invoiced (units)3]],0) -> 0 | AH7: 0 | AI7: =IFERROR(Table1[[#This Row],[Returns Processed (units)7]]/Table1[[#This Row],[Pre-Orders Invoiced (units)3]],0) -> 0 | AJ7: =Table1[[#This Row],[Net Sales (€)2]]/Table1[[#This Row],[Net Sales (€)]] -> 0 | AK7: =Table1[[#This Row],[Net Sales (Units0]]+Table1[[#This Row],[Net Sales Units]] -> 151500 | AL7: =Table1[[#This Row],[Net Sales (€)2]]+Table1[[#This Row],[Net Sales (€)]] -> 9595260 | AM7: 124000 | AN7: 0 | AO7: =Table1[[#This Row],[Pre-Orders Invoiced (units)]]-Table1[[#This Row],[Cancellations (units)]]+Table1[[#This Row],[Re-Orders Invoiced (units)]]+Table1[[#This Row],[Stock Clearance Invoiced (units)]]+Table1[[#This Row],[Returns Processed (units)]] -> 151500 | AP7: =Table1[[#This Row],[Net Sales (€)]]/AO7 -> 63.33505 | AQ7: =AA7-+AB7+Table1[[#This Row],[Re-Orders Invoiced (units)5]]+AF7+AH7 -> 0 | AR7: =IFERROR(Table1[[#This Row],[Net Sales (€)2]]/AQ7,"") | AT7: =L7+X7 -> 9595260 | AU7: =F7*$AU$1 -> 10583788 | AV7: =AT7/AU7-1 -> -0.093400165 | AW7: =AU7/$AU$2 -> 0.11045067 | AX7: =ROUND(AW7*AV7*10000,0) -> -103 | AZ7: =AU7*(1-'SS24 Q2 Data'!$AB$5) -> 9714154.8 | BA7: =L7/AZ7-1 -> -0.012239331 | BB7: =AZ7/$AZ$2 -> 0.11045067 | BC7: =BB7*BA7*10000 -> -13.518424 | BE7: =AU7*'SS24 Q2 Data'!$AB$5 -> 869632.74 | BF7: =X7/BE7-1 -> -1 | BG7: =BE7/$BE$2 -> 0.11045067 | BH7: =BG7*BF7*10000 -> -1104.5067 | BJ7: =Table1[[#This Row],[Net Sales Units]]/Table1[[#This Row],[Shoe Budget Units]] -> 0.6002277 | BK7: =Table1[[#This Row],[Net Sales (Units0]]/Table1[[#This Row],[Apparel Budget Units]] -> 0 | BL7: =Table1[[#This Row],[Net Sales Units total]]/Table1[[#This Row],[Units]] -> 0.55090909 | BM7: =ROUND(Table1[[#This Row],[Net Sales Units]]/'Hypotesis Panel'!$G$8,0) -> 10821 | BN7: =ROUND('Hypotesis Panel'!$G$8/Table1[[#This Row],[ST% Shoes]],0) -> 23 | BO7: =Table1[[#This Row],[Net Sales (Units0]]/'Hypotesis Panel'!$G$8 -> 0 | BP7: =IFERROR(ROUND('Hypotesis Panel'!$G$8/Table1[[#This Row],[ST% Apparel]],0),"NoStock") -> NoStock | BQ7: =IFERROR(ROUND('Hypotesis Panel'!$G$8/Table1[[#This Row],[ST% ToTal]],0),"") -> 25 | BR7: =Table1[[#This Row],[Expected WoOS Shoes]]-'Hypotesis Panel'!$G$8 -> 9 | BS7: 0 | BT7: =Table1[[#This Row],[Expected WoOS Total]]-'Hypotesis Panel'!$G$8 -> 11 | BU7: =Table1[[#This Row],[WOCoverage Shoes]]+'Hypotesis Panel'!$G$8-'Hypotesis Panel'!$F$3 -> -3 | BV7: =_xlfn.XLOOKUP(Table1[[#This Row],[WOS at WK26 Shoes]],Table2[Lower Bound],Table2[Action],,-1) -> Stock Out Risk | BW7: =IF(Table1[[#This Row],[WOS at WK26 Shoes]]*Table1[[#This Row],[Avg Shoes Q1 Weekly Sales]]*Table1[[#This Row],[Actual ASP Shoes per channel]]>0,0,Table1[[#This Row],[WOS at WK26 Shoes]]*Table1[[#This Row],[Avg Shoes Q1 Weekly Sales]]*Table1[[#This Row],[Actual ASP Shoes per channel]]) -> -2056045.7 | BX7: =Table1[[#This Row],[WOC Apparel]]+'Hypotesis Panel'!$G$8-'Hypotesis Panel'!$F$3 -> -12 | BY7: =_xlfn.XLOOKUP(Table1[[#This Row],[WOS at WK26 Apparel]],Table2[Lower Bound],Table2[Action],,-1) -> Stock Out Risk | CA7: =ROUND(Table1[[#This Row],[% Budget share]]*'Available Stock'!$H$6,0) -> 109626 | CB7: =ROUND(Table1[[#This Row],[% Budget share]]*'Available Stock'!$I$6,0) -> 65776 | CC7: =Table1[[#This Row],[Net Sales (Units0]]/'Hypotesis Panel'!$G$8 -> 0 | CD7: =ROUND(Table1[[#This Row],[% Budget share]]*'Available Stock'!$H$7,0) -> 16392 | CE7: =ROUND(Table1[[#This Row],[% Budget share]]*'Available Stock'!$I$7,0) -> 4590 | CF7: =Table1[[#This Row],[Shoes Available Q2 Stock Current Season ]]/#REF! -> #REF! | CG7: =Table1[[#This Row],[Shoes Available Q2 Stock Old Season]]/#REF! -> #REF! | CH7: =SUM(Table1[[#This Row],[Q2 Shoes New Stock WOC based on Q1 Sales Velocity]:[Q2 Shoes Old Stock WOC based on Q1 Sales Velocity]]) -> #REF! | CI7: =IFERROR(Table1[[#This Row],[Apparel Q2 Available Stock Current Season 2]]/Table1[[#This Row],[Avg Apparel Q1 Weekly Sales2]],"") | CJ7: =IFERROR(Table1[[#This Row],[Apparel Q2Available Stock Old Season3]]/Table1[[#This Row],[Avg Apparel Q1 Weekly Sales2]],"") | CK7: =SUM(Table1[[#This Row],[Q2 Apparel New Stock WOC based on Q1 Sales Velocity]:[Q2 Apparel Old Stock WOC based on Q1 Sales Velocity]]) -> 0
A8: Central | B8: Austria | C8: Field Accounts | D8: =_xlfn.CONCAT(Table1[[#This Row],[Sub Region]:[Account]]) -> CentralAustriaField Accounts | E8: =_xlfn.IFNA(VLOOKUP(Table1[[#This Row],[Account]],'Account Information'!$A$4:$B$18,2,FALSE),"") -> Field Accounts | F8: 8700222.6 | G8: 142200 | H8: =Table1[[#This Row],[Units]]/$G$2 -> 0.058233343 | I8: =F8/G8 -> 61.183 | J8: =Table1[[#This Row],[Units]]*(1-'Hypotesis Panel'!$F$46) -> 130515.92 | K8: =Table1[[#This Row],[Units]]-Table1[[#This Row],[Shoe Budget Units]] -> 11684.076 | L8: 5702536 | M8: 82100 | N8: =Table1[[#This Row],[Pre-Orders Invoiced (units)]]-Table1[[#This Row],[Cancellations (units)]]+Table1[[#This Row],[Re-Orders Invoiced (units)]]+Table1[[#This Row],[Stock Clearance Invoiced (units)]]+Table1[[#This Row],[Returns Processed (units)]] -> 85500 | O8: =Table1[[#This Row],[Net Sales (€)]]/Table1[[#This Row],[Net Sales Units]] -> 66.696327 | P8: 2500 | Q8: =Table1[[#This Row],[Cancellations (units)]]/Table1[[#This Row],[Pre-Orders Invoiced (units)]] -> 0.03045067 | R8: 6600 | S8: =Table1[[#This Row],[Re-Orders Invoiced (units)]]/Table1[[#This Row],[Pre-Orders Invoiced (units)]] -> 0.080389769 | T8: 600 | U8: =Table1[[#This Row],[Stock Clearance Invoiced (units)]]/Table1[[#This Row],[Pre-Orders Invoiced (units)]] -> 0.0073081608 | V8: -1300 | W8: =Table1[[#This Row],[Returns Processed (units)]]/Table1[[#This Row],[Pre-Orders Invoiced (units)]] -> -0.015834348 | X8: 563848.71 | Y8: =Table1[[#This Row],[Pre-Orders Invoiced (units)3]]-Table1[[#This Row],[Cancellations (units)4]]+Table1[[#This Row],[Re-Orders Invoiced (units)5]]+Table1[[#This Row],[Stock Clearance Invoiced (units)6]]+Table1[[#This Row],[Returns Processed (units)7]] -> 13014 | Z8: =Table1[[#This Row],[Net Sales (€)2]]/Table1[[#This Row],[Net Sales (Units0]] -> 43.326318 | AA8: 12315 | AB8: 375 | AC8: =IFERROR(Table1[[#This Row],[Cancellations (units)4]]/Table1[[#This Row],[Pre-Orders Invoiced (units)3]],0) -> 0.03045067 | AD8: 674 | AE8: =IFERROR(Table1[[#This Row],[Re-Orders Invoiced (units)5]]/Table1[[#This Row],[Pre-Orders Invoiced (units)3]],0) -> 0.054730004 | AF8: 600 | AG8: =IFERROR(Table1[[#This Row],[Stock Clearance Invoiced (units)6]]/Table1[[#This Row],[Pre-Orders Invoiced (units)3]],0) -> 0.048721072 | AH8: -200 | AI8: =IFERROR(Table1[[#This Row],[Returns Processed (units)7]]/Table1[[#This Row],[Pre-Orders Invoiced (units)3]],0) -> -0.016240357 | AJ8: =Table1[[#This Row],[Net Sales (€)2]]/Table1[[#This Row],[Net Sales (€)]] -> 0.098876834 | AK8: =Table1[[#This Row],[Net Sales (Units0]]+Table1[[#This Row],[Net Sales Units]] -> 98514 | AL8: =Table1[[#This Row],[Net Sales (€)2]]+Table1[[#This Row],[Net Sales (€)]] -> 6266384.7 | AM8: 24900 | AN8: 2435 | AO8: =Table1[[#This Row],[Pre-Orders Invoiced (units)]]-Table1[[#This Row],[Cancellations (units)]]+Table1[[#This Row],[Re-Orders Invoiced (units)]]+Table1[[#This Row],[Stock Clearance Invoiced (units)]]+Table1[[#This Row],[Returns Processed (units)]] -> 85500 | AP8: =Table1[[#This Row],[Net Sales (€)]]/AO8 -> 66.696327 | AQ8: =AA8-+AB8+Table1[[#This Row],[Re-Orders Invoiced (units)5]]+AF8+AH8 -> 13014 | AR8: =IFERROR(Table1[[#This Row],[Net Sales (€)2]]/AQ8,"") -> 43.326318 | AT8: =L8+X8 -> 6266384.7 | AU8: =F8*$AU$1 -> 5655144.7 | AV8: =AT8/AU8-1 -> 0.10808566 | AW8: =AU8/$AU$2 -> 0.059016165 | AX8: =ROUND(AW8*AV8*10000,0) -> 64 | AZ8: =AU8*(1-'SS24 Q2 Data'!$AB$5) -> 5190481.3 | BA8: =L8/AZ8-1 -> 0.098652651 | BB8: =AZ8/$AZ$2 -> 0.059016165 | BC8: =BB8*BA8*10000 -> 58.221011 | BE8: =AU8*'SS24 Q2 Data'!$AB$5 -> 464663.43 | BF8: =X8/BE8-1 -> 0.21345618 | BG8: =BE8/$BE$2 -> 0.059016165 | BH8: =BG8*BF8*10000 -> 125.97365 | BJ8: =Table1[[#This Row],[Net Sales Units]]/Table1[[#This Row],[Shoe Budget Units]] -> 0.65509248 | BK8: =Table1[[#This Row],[Net Sales (Units0]]/Table1[[#This Row],[Apparel Budget Units]] -> 1.1138236 | BL8: =Table1[[#This Row],[Net Sales Units total]]/Table1[[#This Row],[Units]] -> 0.69278481 | BM8: =ROUND(Table1[[#This Row],[Net Sales Units]]/'Hypotesis Panel'!$G$8,0) -> 6107 | BN8: =ROUND('Hypotesis Panel'!$G$8/Table1[[#This Row],[ST% Shoes]],0) -> 21 | BO8: =Table1[[#This Row],[Net Sales (Units0]]/'Hypotesis Panel'!$G$8 -> 929.57143 | BP8: =IFERROR(ROUND('Hypotesis Panel'!$G$8/Table1[[#This Row],[ST% Apparel]],0),"NoStock") -> 13 | BQ8: =IFERROR(ROUND('Hypotesis Panel'!$G$8/Table1[[#This Row],[ST% ToTal]],0),"") -> 20 | BR8: =Table1[[#This Row],[Expected WoOS Shoes]]-'Hypotesis Panel'!$G$8 -> 7 | BS8: =IFERROR(Table1[[#This Row],[Expected WoOS Apparel]]-'Hypotesis Panel'!$G$8,"") -> -1 | BT8: =Table1[[#This Row],[Expected WoOS Total]]-'Hypotesis Panel'!$G$8 -> 6 | BU8: =Table1[[#This Row],[WOCoverage Shoes]]+'Hypotesis Panel'!$G$8-'Hypotesis Panel'!$F$3 -> -5 | BV8: =_xlfn.XLOOKUP(Table1[[#This Row],[WOS at WK26 Shoes]],Table2[Lower Bound],Table2[Action],,-1) -> Stock Out Risk | BW8: =IF(Table1[[#This Row],[WOS at WK26 Shoes]]*Table1[[#This Row],[Avg Shoes Q1 Weekly Sales]]*Table1[[#This Row],[Actual ASP Shoes per channel]]>0,0,Table1[[#This Row],[WOS at WK26 Shoes]]*Table1[[#This Row],[Avg Shoes Q1 Weekly Sales]]*Table1[[#This Row],[Actual ASP Shoes per channel]]) -> -2036572.4 | BX8: =Table1[[#This Row],[WOC Apparel]]+'Hypotesis Panel'!$G$8-'Hypotesis Panel'!$F$3 -> -13 | BY8: =_xlfn.XLOOKUP(Table1[[#This Row],[WOS at WK26 Apparel]],Table2[Lower Bound],Table2[Action],,-1) -> Stock Out Risk | CA8: =ROUND(Table1[[#This Row],[% Budget share]]*'Available Stock'!$H$6,0) -> 56687 | CB8: =ROUND(Table1[[#This Row],[% Budget share]]*'Available Stock'!$I$6,0) -> 34012 | CC8: =Table1[[#This Row],[Net Sales (Units0]]/'Hypotesis Panel'!$G$8 -> 929.57143 | CD8: =ROUND(Table1[[#This Row],[% Budget share]]*'Available Stock'!$H$7,0) -> 8476 | CE8: =ROUND(Table1[[#This Row],[% Budget share]]*'Available Stock'!$I$7,0) -> 2373 | CF8: =Table1[[#This Row],[Shoes Available Q2 Stock Current Season ]]/#REF! -> #REF! | CG8: =Table1[[#This Row],[Shoes Available Q2 Stock Old Season]]/#REF! -> #REF! | CH8: =SUM(Table1[[#This Row],[Q2 Shoes New Stock WOC based on Q1 Sales Velocity]:[Q2 Shoes Old Stock WOC based on Q1 Sales Velocity]]) -> #REF! | CI8: =IFERROR(Table1[[#This Row],[Apparel Q2 Available Stock Current Season 2]]/Table1[[#This Row],[Avg Apparel Q1 Weekly Sales2]],"") -> 9.1181804 | CJ8: =IFERROR(Table1[[#This Row],[Apparel Q2Available Stock Old Season3]]/Table1[[#This Row],[Avg Apparel Q1 Weekly Sales2]],"") -> 2.5527893 | CK8: =SUM(Table1[[#This Row],[Q2 Apparel New Stock WOC based on Q1 Sales Velocity]:[Q2 Apparel Old Stock WOC based on Q1 Sales Velocity]]) -> 11.67097
A9: North | B9: United Kingdom | C9: Field Accounts | D9: =_xlfn.CONCAT(Table1[[#This Row],[Sub Region]:[Account]]) -> NorthUnited KingdomField Accounts | E9: =_xlfn.IFNA(VLOOKUP(Table1[[#This Row],[Account]],'Account Information'!$A$4:$B$18,2,FALSE),"") -> Field Accounts | F9: 10404450 | G9: 157500 | H9: =Table1[[#This Row],[Units]]/$G$2 -> 0.064498956 | I9: =F9/G9 -> 66.06 | J9: =Table1[[#This Row],[Units]]*(1-'Hypotesis Panel'!$F$46) -> 144558.78 | K9: =Table1[[#This Row],[Units]]-Table1[[#This Row],[Shoe Budget Units]] -> 12941.223 | L9: 5451235.8 | M9: 72200 | N9: =Table1[[#This Row],[Pre-Orders Invoiced (units)]]-Table1[[#This Row],[Cancellations (units)]]+Table1[[#This Row],[Re-Orders Invoiced (units)]]+Table1[[#This Row],[Stock Clearance Invoiced (units)]]+Table1[[#This Row],[Returns Processed (units)]] -> 62552 | O9: =Table1[[#This Row],[Net Sales (€)]]/Table1[[#This Row],[Net Sales Units]] -> 87.147266 | P9: 17700 | Q9: =Table1[[#This Row],[Cancellations (units)]]/Table1[[#This Row],[Pre-Orders Invoiced (units)]] -> 0.24515235 | R9: 8500 | S9: =Table1[[#This Row],[Re-Orders Invoiced (units)]]/Table1[[#This Row],[Pre-Orders Invoiced (units)]] -> 0.11772853 | T9: 4452 | U9: =Table1[[#This Row],[Stock Clearance Invoiced (units)]]/Table1[[#This Row],[Pre-Orders Invoiced (units)]] -> 0.06166205 | V9: -4900 | W9: =Table1[[#This Row],[Returns Processed (units)]]/Table1[[#This Row],[Pre-Orders Invoiced (units)]] -> -0.067867036 | X9: 467854.39 | Y9: =Table1[[#This Row],[Pre-Orders Invoiced (units)3]]-Table1[[#This Row],[Cancellations (units)4]]+Table1[[#This Row],[Re-Orders Invoiced (units)5]]+Table1[[#This Row],[Stock Clearance Invoiced (units)6]]+Table1[[#This Row],[Returns Processed (units)7]] -> 10395 | Z9: =Table1[[#This Row],[Net Sales (€)2]]/Table1[[#This Row],[Net Sales (Units0]] -> 45.007638 | AA9: 7220 | AB9: 1236 | AC9: =IFERROR(Table1[[#This Row],[Cancellations (units)4]]/Table1[[#This Row],[Pre-Orders Invoiced (units)3]],0) -> 0.17119114 | AD9: 234 | AE9: =IFERROR(Table1[[#This Row],[Re-Orders Invoiced (units)5]]/Table1[[#This Row],[Pre-Orders Invoiced (units)3]],0) -> 0.032409972 | AF9: 4452 | AG9: =IFERROR(Table1[[#This Row],[Stock Clearance Invoiced (units)6]]/Table1[[#This Row],[Pre-Orders Invoiced (units)3]],0) -> 0.6166205 | AH9: -275 | AI9: =IFERROR(Table1[[#This Row],[Returns Processed (units)7]]/Table1[[#This Row],[Pre-Orders Invoiced (units)3]],0) -> -0.038088643 | AJ9: =Table1[[#This Row],[Net Sales (€)2]]/Table1[[#This Row],[Net Sales (€)]] -> 0.085825382 | AK9: =Table1[[#This Row],[Net Sales (Units0]]+Table1[[#This Row],[Net Sales Units]] -> 72947 | AL9: =Table1[[#This Row],[Net Sales (€)2]]+Table1[[#This Row],[Net Sales (€)]] -> 5919090.2 | AM9: 30700 | AN9: 1231 | AO9: =Table1[[#This Row],[Pre-Orders Invoiced (units)]]-Table1[[#This Row],[Cancellations (units)]]+Table1[[#This Row],[Re-Orders Invoiced (units)]]+Table1[[#This Row],[Stock Clearance Invoiced (units)]]+Table1[[#This Row],[Returns Processed (units)]] -> 62552 | AP9: =Table1[[#This Row],[Net Sales (€)]]/AO9 -> 87.147266 | AQ9: =AA9-+AB9+Table1[[#This Row],[Re-Orders Invoiced (units)5]]+AF9+AH9 -> 10395 | AR9: =IFERROR(Table1[[#This Row],[Net Sales (€)2]]/AQ9,"") -> 45.007638 | AT9: =L9+X9 -> 5919090.2 | AU9: =F9*$AU$1 -> 6762892.5 | AV9: =AT9/AU9-1 -> -0.12476944 | AW9: =AU9/$AU$2 -> 0.070576439 | AX9: =ROUND(AW9*AV9*10000,0) -> -88 | AZ9: =AU9*(1-'SS24 Q2 Data'!$AB$5) -> 6207209.3 | BA9: =L9/AZ9-1 -> -0.1217896 | BB9: =AZ9/$AZ$2 -> 0.070576439 | BC9: =BB9*BA9*10000 -> -85.954763 | BE9: =AU9*'SS24 Q2 Data'!$AB$5 -> 555683.19 | BF9: =X9/BE9-1 -> -0.15805552 | BG9: =BE9/$BE$2 -> 0.070576439 | BH9: =BG9*BF9*10000 -> -111.54996 | BJ9: =Table1[[#This Row],[Net Sales Units]]/Table1[[#This Row],[Shoe Budget Units]] -> 0.4327098 | BK9: =Table1[[#This Row],[Net Sales (Units0]]/Table1[[#This Row],[Apparel Budget Units]] -> 0.8032471 | BL9: =Table1[[#This Row],[Net Sales Units total]]/Table1[[#This Row],[Units]] -> 0.46315556 | BM9: =ROUND(Table1[[#This Row],[Net Sales Units]]/'Hypotesis Panel'!$G$8,0) -> 4468 | BN9: =ROUND('Hypotesis Panel'!$G$8/Table1[[#This Row],[ST% Shoes]],0) -> 32 | BO9: =Table1[[#This Row],[Net Sales (Units0]]/'Hypotesis Panel'!$G$8 -> 742.5 | BP9: =IFERROR(ROUND('Hypotesis Panel'!$G$8/Table1[[#This Row],[ST% Apparel]],0),"NoStock") -> 17 | BQ9: =IFERROR(ROUND('Hypotesis Panel'!$G$8/Table1[[#This Row],[ST% ToTal]],0),"") -> 30 | BR9: =Table1[[#This Row],[Expected WoOS Shoes]]-'Hypotesis Panel'!$G$8 -> 18 | BS9: =IFERROR(Table1[[#This Row],[Expected WoOS Apparel]]-'Hypotesis Panel'!$G$8,"") -> 3 | BT9: =Table1[[#This Row],[Expected WoOS Total]]-'Hypotesis Panel'!$G$8 -> 16 | BU9: =Table1[[#This Row],[WOCoverage Shoes]]+'Hypotesis Panel'!$G$8-'Hypotesis Panel'!$F$3 -> 6 | BV9: =_xlfn.XLOOKUP(Table1[[#This Row],[WOS at WK26 Shoes]],Table2[Lower Bound],Table2[Action],,-1) -> Overstock | BW9: =IF(Table1[[#This Row],[WOS at WK26 Shoes]]*Table1[[#This Row],[Avg Shoes Q1 Weekly Sales]]*Table1[[#This Row],[Actual ASP Shoes per channel]]>0,0,Table1[[#This Row],[WOS at WK26 Shoes]]*Table1[[#This Row],[Avg Shoes Q1 Weekly Sales]]*Table1[[#This Row],[Actual ASP Shoes per channel]]) -> 0 | BX9: =Table1[[#This Row],[WOC Apparel]]+'Hypotesis Panel'!$G$8-'Hypotesis Panel'!$F$3 -> -9 | BY9: =_xlfn.XLOOKUP(Table1[[#This Row],[WOS at WK26 Apparel]],Table2[Lower Bound],Table2[Action],,-1) -> Stock Out Risk | CA9: =ROUND(Table1[[#This Row],[% Budget share]]*'Available Stock'!$H$6,0) -> 62786 | CB9: =ROUND(Table1[[#This Row],[% Budget share]]*'Available Stock'!$I$6,0) -> 37672 | CC9: =Table1[[#This Row],[Net Sales (Units0]]/'Hypotesis Panel'!$G$8 -> 742.5 | CD9: =ROUND(Table1[[#This Row],[% Budget share]]*'Available Stock'!$H$7,0) -> 9388 | CE9: =ROUND(Table1[[#This Row],[% Budget share]]*'Available Stock'!$I$7,0) -> 2629 | CF9: =Table1[[#This Row],[Shoes Available Q2 Stock Current Season ]]/#REF! -> #REF! | CG9: =Table1[[#This Row],[Shoes Available Q2 Stock Old Season]]/#REF! -> #REF! | CH9: =SUM(Table1[[#This Row],[Q2 Shoes New Stock WOC based on Q1 Sales Velocity]:[Q2 Shoes Old Stock WOC based on Q1 Sales Velocity]]) -> #REF! | CI9: =IFERROR(Table1[[#This Row],[Apparel Q2 Available Stock Current Season 2]]/Table1[[#This Row],[Avg Apparel Q1 Weekly Sales2]],"") -> 12.643771 | CJ9: =IFERROR(Table1[[#This Row],[Apparel Q2Available Stock Old Season3]]/Table1[[#This Row],[Avg Apparel Q1 Weekly Sales2]],"") -> 3.5407407 | CK9: =SUM(Table1[[#This Row],[Q2 Apparel New Stock WOC based on Q1 Sales Velocity]:[Q2 Apparel Old Stock WOC based on Q1 Sales Velocity]]) -> 16.184512
A10: North | B10: BeNeLux | C10: Field Accounts | D10: =_xlfn.CONCAT(Table1[[#This Row],[Sub Region]:[Account]]) -> NorthBeNeLuxField Accounts | E10: =_xlfn.IFNA(VLOOKUP(Table1[[#This Row],[Account]],'Account Information'!$A$4:$B$18,2,FALSE),"") -> Field Accounts | F10: 6317520 | G10: 105600 | H10: =Table1[[#This Row],[Units]]/$G$2 -> 0.043245014 | I10: =F10/G10 -> 59.825 | J10: =Table1[[#This Row],[Units]]*(1-'Hypotesis Panel'!$F$46) -> 96923.218 | K10: =Table1[[#This Row],[Units]]-Table1[[#This Row],[Shoe Budget Units]] -> 8676.7821 | L10: 3873149 | M10: 48600 | N10: =Table1[[#This Row],[Pre-Orders Invoiced (units)]]-Table1[[#This Row],[Cancellations (units)]]+Table1[[#This Row],[Re-Orders Invoiced (units)]]+Table1[[#This Row],[Stock Clearance Invoiced (units)]]+Table1[[#This Row],[Returns Processed (units)]] -> 60000 | O10: =Table1[[#This Row],[Net Sales (€)]]/Table1[[#This Row],[Net Sales Units]] -> 64.552483 | P10: 6100 | Q10: =Table1[[#This Row],[Cancellations (units)]]/Table1[[#This Row],[Pre-Orders Invoiced (units)]] -> 0.1255144 | R10: 4200 | S10: =Table1[[#This Row],[Re-Orders Invoiced (units)]]/Table1[[#This Row],[Pre-Orders Invoiced (units)]] -> 0.086419753 | T10: 15000 | U10: =Table1[[#This Row],[Stock Clearance Invoiced (units)]]/Table1[[#This Row],[Pre-Orders Invoiced (units)]] -> 0.30864198 | V10: -1700 | W10: =Table1[[#This Row],[Returns Processed (units)]]/Table1[[#This Row],[Pre-Orders Invoiced (units)]] -> -0.034979424 | X10: 748052.58 | Y10: =Table1[[#This Row],[Pre-Orders Invoiced (units)3]]-Table1[[#This Row],[Cancellations (units)4]]+Table1[[#This Row],[Re-Orders Invoiced (units)5]]+Table1[[#This Row],[Stock Clearance Invoiced (units)6]]+Table1[[#This Row],[Returns Processed (units)7]] -> 20839 | Z10: =Table1[[#This Row],[Net Sales (€)2]]/Table1[[#This Row],[Net Sales (Units0]] -> 35.89676 | AA10: 6804 | AB10: 854 | AC10: =IFERROR(Table1[[#This Row],[Cancellations (units)4]]/Table1[[#This Row],[Pre-Orders Invoiced (units)3]],0) -> 0.1255144 | AD10: 234 | AE10: =IFERROR(Table1[[#This Row],[Re-Orders Invoiced (units)5]]/Table1[[#This Row],[Pre-Orders Invoiced (units)3]],0) -> 0.034391534 | AF10: 15000 | AG10: =IFERROR(Table1[[#This Row],[Stock Clearance Invoiced (units)6]]/Table1[[#This Row],[Pre-Orders Invoiced (units)3]],0) -> 2.2045855 | AH10: -345 | AI10: =IFERROR(Table1[[#This Row],[Returns Processed (units)7]]/Table1[[#This Row],[Pre-Orders Invoiced (units)3]],0) -> -0.050705467 | AJ10: =Table1[[#This Row],[Net Sales (€)2]]/Table1[[#This Row],[Net Sales (€)]] -> 0.19313808 | AK10: =Table1[[#This Row],[Net Sales (Units0]]+Table1[[#This Row],[Net Sales Units]] -> 80839 | AL10: =Table1[[#This Row],[Net Sales (€)2]]+Table1[[#This Row],[Net Sales (€)]] -> 4621201.6 | AM10: 33600 | AN10: 3564 | AO10: =Table1[[#This Row],[Pre-Orders Invoiced (units)]]-Table1[[#This Row],[Cancellations (units)]]+Table1[[#This Row],[Re-Orders Invoiced (units)]]+Table1[[#This Row],[Stock Clearance Invoiced (units)]]+Table1[[#This Row],[Returns Processed (units)]] -> 60000 | AP10: =Table1[[#This Row],[Net Sales (€)]]/AO10 -> 64.552483 | AQ10: =AA10-+AB10+Table1[[#This Row],[Re-Orders Invoiced (units)5]]+AF10+AH10 -> 20839 | AR10: =IFERROR(Table1[[#This Row],[Net Sales (€)2]]/AQ10,"") -> 35.89676 | AT10: =L10+X10 -> 4621201.6 | AU10: =F10*$AU$1 -> 4106388 | AV10: =AT10/AU10-1 -> 0.12536896 | AW10: =AU10/$AU$2 -> 0.042853593 | AX10: =ROUND(AW10*AV10*10000,0) -> 54 | AZ10: =AU10*(1-'SS24 Q2 Data'!$AB$5) -> 3768980.5 | BA10: =L10/AZ10-1 -> 0.027638381 | BB10: =AZ10/$AZ$2 -> 0.042853593 | BC10: =BB10*BA10*10000 -> 11.844039 | BE10: =AU10*'SS24 Q2 Data'!$AB$5 -> 337407.52 | BF10: =X10/BE10-1 -> 1.2170596 | BG10: =BE10/$BE$2 -> 0.042853593 | BH10: =BG10*BF10*10000 -> 521.55378 | BJ10: =Table1[[#This Row],[Net Sales Units]]/Table1[[#This Row],[Shoe Budget Units]] -> 0.61904672 | BK10: =Table1[[#This Row],[Net Sales (Units0]]/Table1[[#This Row],[Apparel Budget Units]] -> 2.4016968 | BL10: =Table1[[#This Row],[Net Sales Units total]]/Table1[[#This Row],[Units]] -> 0.76552083 | BM10: =ROUND(Table1[[#This Row],[Net Sales Units]]/'Hypotesis Panel'!$G$8,0) -> 4286 | BN10: =ROUND('Hypotesis Panel'!$G$8/Table1[[#This Row],[ST% Shoes]],0) -> 23 | BO10: =Table1[[#This Row],[Net Sales (Units0]]/'Hypotesis Panel'!$G$8 -> 1488.5 | BP10: =IFERROR(ROUND('Hypotesis Panel'!$G$8/Table1[[#This Row],[ST% Apparel]],0),"NoStock") -> 6 | BQ10: =IFERROR(ROUND('Hypotesis Panel'!$G$8/Table1[[#This Row],[ST% ToTal]],0),"") -> 18 | BR10: =Table1[[#This Row],[Expected WoOS Shoes]]-'Hypotesis Panel'!$G$8 -> 9 | BS10: =IFERROR(Table1[[#This Row],[Expected WoOS Apparel]]-'Hypotesis Panel'!$G$8,"") -> -8 | BT10: =Table1[[#This Row],[Expected WoOS Total]]-'Hypotesis Panel'!$G$8 -> 4 | BU10: =Table1[[#This Row],[WOCoverage Shoes]]+'Hypotesis Panel'!$G$8-'Hypotesis Panel'!$F$3 -> -3 | BV10: =_xlfn.XLOOKUP(Table1[[#This Row],[WOS at WK26 Shoes]],Table2[Lower Bound],Table2[Action],,-1) -> Stock Out Risk | BW10: =IF(Table1[[#This Row],[WOS at WK26 Shoes]]*Table1[[#This Row],[Avg Shoes Q1 Weekly Sales]]*Table1[[#This Row],[Actual ASP Shoes per channel]]>0,0,Table1[[#This Row],[WOS at WK26 Shoes]]*Table1[[#This Row],[Avg Shoes Q1 Weekly Sales]]*Table1[[#This Row],[Actual ASP Shoes per channel]]) -> -830015.83 | BX10: =Table1[[#This Row],[WOC Apparel]]+'Hypotesis Panel'!$G$8-'Hypotesis Panel'!$F$3 -> -20 | BY10: =_xlfn.XLOOKUP(Table1[[#This Row],[WOS at WK26 Apparel]],Table2[Lower Bound],Table2[Action],,-1) -> Stock Out Risk | CA10: =ROUND(Table1[[#This Row],[% Budget share]]*'Available Stock'!$H$6,0) -> 42096 | CB10: =ROUND(Table1[[#This Row],[% Budget share]]*'Available Stock'!$I$6,0) -> 25258 | CC10: =Table1[[#This Row],[Net Sales (Units0]]/'Hypotesis Panel'!$G$8 -> 1488.5 | CD10: =ROUND(Table1[[#This Row],[% Budget share]]*'Available Stock'!$H$7,0) -> 6294 | CE10: =ROUND(Table1[[#This Row],[% Budget share]]*'Available Stock'!$I$7,0) -> 1762 | CF10: =Table1[[#This Row],[Shoes Available Q2 Stock Current Season ]]/#REF! -> #REF! | CG10: =Table1[[#This Row],[Shoes Available Q2 Stock Old Season]]/#REF! -> #REF! | CH10: =SUM(Table1[[#This Row],[Q2 Shoes New Stock WOC based on Q1 Sales Velocity]:[Q2 Shoes Old Stock WOC based on Q1 Sales Velocity]]) -> #REF! | CI10: =IFERROR(Table1[[#This Row],[Apparel Q2 Available Stock Current Season 2]]/Table1[[#This Row],[Avg Apparel Q1 Weekly Sales2]],"") -> 4.2284179 | CJ10: =IFERROR(Table1[[#This Row],[Apparel Q2Available Stock Old Season3]]/Table1[[#This Row],[Avg Apparel Q1 Weekly Sales2]],"") -> 1.183742 | CK10: =SUM(Table1[[#This Row],[Q2 Apparel New Stock WOC based on Q1 Sales Velocity]:[Q2 Apparel Old Stock WOC based on Q1 Sales Velocity]]) -> 5.4121599
A11: Central | B11: Germany | C11: Hanover & Hearth | D11: =_xlfn.CONCAT(Table1[[#This Row],[Sub Region]:[Account]]) -> CentralGermanyHanover & Hearth | E11: =_xlfn.IFNA(VLOOKUP(Table1[[#This Row],[Account]],'Account Information'!$A$4:$B$18,2,FALSE),"") -> Lifestyle / Sport | F11: 5464828.2 | G11: 103300 | H11: =Table1[[#This Row],[Units]]/$G$2 -> 0.042303125 | I11: =F11/G11 -> 52.9025 | J11: =Table1[[#This Row],[Units]]*(1-'Hypotesis Panel'!$F$46) -> 94812.201 | K11: =Table1[[#This Row],[Units]]-Table1[[#This Row],[Shoe Budget Units]] -> 8487.7991 | L11: 3075537.1 | M11: 54600 | N11: =Table1[[#This Row],[Pre-Orders Invoiced (units)]]-Table1[[#This Row],[Cancellations (units)]]+Table1[[#This Row],[Re-Orders Invoiced (units)]]+Table1[[#This Row],[Stock Clearance Invoiced (units)]]+Table1[[#This Row],[Returns Processed (units)]] -> 50323 | O11: =Table1[[#This Row],[Net Sales (€)]]/Table1[[#This Row],[Net Sales Units]] -> 61.115934 | P11: 4123 | Q11: =Table1[[#This Row],[Cancellations (units)]]/Table1[[#This Row],[Pre-Orders Invoiced (units)]] -> 0.075512821 | R11: 2567 | S11: =Table1[[#This Row],[Re-Orders Invoiced (units)]]/Table1[[#This Row],[Pre-Orders Invoiced (units)]] -> 0.047014652 | T11: 734 | U11: =Table1[[#This Row],[Stock Clearance Invoiced (units)]]/Table1[[#This Row],[Pre-Orders Invoiced (units)]] -> 0.013443223 | V11: -3455 | W11: =Table1[[#This Row],[Returns Processed (units)]]/Table1[[#This Row],[Pre-Orders Invoiced (units)]] -> -0.063278388 | X11: 566532.49 | Y11: =Table1[[#This Row],[Pre-Orders Invoiced (units)3]]-Table1[[#This Row],[Cancellations (units)4]]+Table1[[#This Row],[Re-Orders Invoiced (units)5]]+Table1[[#This Row],[Stock Clearance Invoiced (units)6]]+Table1[[#This Row],[Returns Processed (units)7]] -> 11187.5 | Z11: =Table1[[#This Row],[Net Sales (€)2]]/Table1[[#This Row],[Net Sales (Units0]] -> 50.639775 | AA11: 13650 | AB11: 2345 | AC11: =IFERROR(Table1[[#This Row],[Cancellations (units)4]]/Table1[[#This Row],[Pre-Orders Invoiced (units)3]],0) -> 0.17179487 | AD11: 682.5 | AE11: =IFERROR(Table1[[#This Row],[Re-Orders Invoiced (units)5]]/Table1[[#This Row],[Pre-Orders Invoiced (units)3]],0) -> 0.05 | AF11: 734 | AG11: =IFERROR(Table1[[#This Row],[Stock Clearance Invoiced (units)6]]/Table1[[#This Row],[Pre-Orders Invoiced (units)3]],0) -> 0.053772894 | AH11: -1534 | AI11: =IFERROR(Table1[[#This Row],[Returns Processed (units)7]]/Table1[[#This Row],[Pre-Orders Invoiced (units)3]],0) -> -0.11238095 | AJ11: =Table1[[#This Row],[Net Sales (€)2]]/Table1[[#This Row],[Net Sales (€)]] -> 0.18420603 | AK11: =Table1[[#This Row],[Net Sales (Units0]]+Table1[[#This Row],[Net Sales Units]] -> 61510.5 | AL11: =Table1[[#This Row],[Net Sales (€)2]]+Table1[[#This Row],[Net Sales (€)]] -> 3642069.6 | AM11: 14800 | AN11: 4095 | AO11: =Table1[[#This Row],[Pre-Orders Invoiced (units)]]-Table1[[#This Row],[Cancellations (units)]]+Table1[[#This Row],[Re-Orders Invoiced (units)]]+Table1[[#This Row],[Stock Clearance Invoiced (units)]]+Table1[[#This Row],[Returns Processed (units)]] -> 50323 | AP11: =Table1[[#This Row],[Net Sales (€)]]/AO11 -> 61.115934 | AQ11: =AA11-+AB11+Table1[[#This Row],[Re-Orders Invoiced (units)5]]+AF11+AH11 -> 11187.5 | AR11: =IFERROR(Table1[[#This Row],[Net Sales (€)2]]/AQ11,"") -> 50.639775 | AT11: =L11+X11 -> 3642069.6 | AU11: =F11*$AU$1 -> 3552138.4 | AV11: =AT11/AU11-1 -> 0.025317496 | AW11: =AU11/$AU$2 -> 0.037069535 | AX11: =ROUND(AW11*AV11*10000,0) -> 9 | AZ11: =AU11*(1-'SS24 Q2 Data'!$AB$5) -> 3260271.6 | BA11: =L11/AZ11-1 -> -0.056662295 | BB11: =AZ11/$AZ$2 -> 0.037069535 | BC11: =BB11*BA11*10000 -> -21.004449 | BE11: =AU11*'SS24 Q2 Data'!$AB$5 -> 291866.77 | BF11: =X11/BE11-1 -> 0.94106542 | BG11: =BE11/$BE$2 -> 0.037069535 | BH11: =BG11*BF11*10000 -> 348.84857 | BJ11: =Table1[[#This Row],[Net Sales Units]]/Table1[[#This Row],[Shoe Budget Units]] -> 0.53076502 | BK11: =Table1[[#This Row],[Net Sales (Units0]]/Table1[[#This Row],[Apparel Budget Units]] -> 1.3180684 | BL11: =Table1[[#This Row],[Net Sales Units total]]/Table1[[#This Row],[Units]] -> 0.59545499 | BM11: =ROUND(Table1[[#This Row],[Net Sales Units]]/'Hypotesis Panel'!$G$8,0) -> 3595 | BN11: =ROUND('Hypotesis Panel'!$G$8/Table1[[#This Row],[ST% Shoes]],0) -> 26 | BO11: =Table1[[#This Row],[Net Sales (Units0]]/'Hypotesis Panel'!$G$8 -> 799.10714 | BP11: =IFERROR(ROUND('Hypotesis Panel'!$G$8/Table1[[#This Row],[ST% Apparel]],0),"NoStock") -> 11 | BQ11: =IFERROR(ROUND('Hypotesis Panel'!$G$8/Table1[[#This Row],[ST% ToTal]],0),"") -> 24 | BR11: =Table1[[#This Row],[Expected WoOS Shoes]]-'Hypotesis Panel'!$G$8 -> 12 | BS11: =IFERROR(Table1[[#This Row],[Expected WoOS Apparel]]-'Hypotesis Panel'!$G$8,"") -> -3 | BT11: =Table1[[#This Row],[Expected WoOS Total]]-'Hypotesis Panel'!$G$8 -> 10 | BU11: =Table1[[#This Row],[WOCoverage Shoes]]+'Hypotesis Panel'!$G$8-'Hypotesis Panel'!$F$3 -> 0 | BV11: =_xlfn.XLOOKUP(Table1[[#This Row],[WOS at WK26 Shoes]],Table2[Lower Bound],Table2[Action],,-1) -> Monitor | BW11: =IF(Table1[[#This Row],[WOS at WK26 Shoes]]*Table1[[#This Row],[Avg Shoes Q1 Weekly Sales]]*Table1[[#This Row],[Actual ASP Shoes per channel]]>0,0,Table1[[#This Row],[WOS at WK26 Shoes]]*Table1[[#This Row],[Avg Shoes Q1 Weekly Sales]]*Table1[[#This Row],[Actual ASP Shoes per channel]]) -> 0 | BX11: =Table1[[#This Row],[WOC Apparel]]+'Hypotesis Panel'!$G$8-'Hypotesis Panel'!$F$3 -> -15 | BY11: =_xlfn.XLOOKUP(Table1[[#This Row],[WOS at WK26 Apparel]],Table2[Lower Bound],Table2[Action],,-1) -> Stock Out Risk | CA11: =ROUND(Table1[[#This Row],[% Budget share]]*'Available Stock'!$H$6,0) -> 41180 | CB11: =ROUND(Table1[[#This Row],[% Budget share]]*'Available Stock'!$I$6,0) -> 24708 | CC11: =Table1[[#This Row],[Net Sales (Units0]]/'Hypotesis Panel'!$G$8 -> 799.10714 | CD11: =ROUND(Table1[[#This Row],[% Budget share]]*'Available Stock'!$H$7,0) -> 6157 | CE11: =ROUND(Table1[[#This Row],[% Budget share]]*'Available Stock'!$I$7,0) -> 1724 | CF11: =Table1[[#This Row],[Shoes Available Q2 Stock Current Season ]]/#REF! -> #REF! | CG11: =Table1[[#This Row],[Shoes Available Q2 Stock Old Season]]/#REF! -> #REF! | CH11: =SUM(Table1[[#This Row],[Q2 Shoes New Stock WOC based on Q1 Sales Velocity]:[Q2 Shoes Old Stock WOC based on Q1 Sales Velocity]]) -> #REF! | CI11: =IFERROR(Table1[[#This Row],[Apparel Q2 Available Stock Current Season 2]]/Table1[[#This Row],[Avg Apparel Q1 Weekly Sales2]],"") -> 7.7048492 | CJ11: =IFERROR(Table1[[#This Row],[Apparel Q2Available Stock Old Season3]]/Table1[[#This Row],[Avg Apparel Q1 Weekly Sales2]],"") -> 2.1574078 | CK11: =SUM(Table1[[#This Row],[Q2 Apparel New Stock WOC based on Q1 Sales Velocity]:[Q2 Apparel Old Stock WOC based on Q1 Sales Velocity]]) -> 9.862257
A12: South | B12: Spain | C12: Field Accounts | D12: =_xlfn.CONCAT(Table1[[#This Row],[Sub Region]:[Account]]) -> SouthSpainField Accounts | E12: =_xlfn.IFNA(VLOOKUP(Table1[[#This Row],[Account]],'Account Information'!$A$4:$B$18,2,FALSE),"") -> Field Accounts | F12: 6067988.4 | G12: 102700 | H12: =Table1[[#This Row],[Units]]/$G$2 -> 0.042057414 | I12: =F12/G12 -> 59.0846 | J12: =Table1[[#This Row],[Units]]*(1-'Hypotesis Panel'!$F$46) -> 94261.501 | K12: =Table1[[#This Row],[Units]]-Table1[[#This Row],[Shoe Budget Units]] -> 8438.4992 | L12: 3055283.4 | M12: 39300 | N12: =Table1[[#This Row],[Pre-Orders Invoiced (units)]]-Table1[[#This Row],[Cancellations (units)]]+Table1[[#This Row],[Re-Orders Invoiced (units)]]+Table1[[#This Row],[Stock Clearance Invoiced (units)]]+Table1[[#This Row],[Returns Processed (units)]] -> 45000 | O12: =Table1[[#This Row],[Net Sales (€)]]/Table1[[#This Row],[Net Sales Units]] -> 67.895187 | P12: 3100 | Q12: =Table1[[#This Row],[Cancellations (units)]]/Table1[[#This Row],[Pre-Orders Invoiced (units)]] -> 0.078880407 | R12: 9400 | S12: =Table1[[#This Row],[Re-Orders Invoiced (units)]]/Table1[[#This Row],[Pre-Orders Invoiced (units)]] -> 0.23918575 | T12: 100 | U12: =Table1[[#This Row],[Stock Clearance Invoiced (units)]]/Table1[[#This Row],[Pre-Orders Invoiced (units)]] -> 0.0025445293 | V12: -700 | W12: =Table1[[#This Row],[Returns Processed (units)]]/Table1[[#This Row],[Pre-Orders Invoiced (units)]] -> -0.017811705 | X12: 219582.08 | Y12: =Table1[[#This Row],[Pre-Orders Invoiced (units)3]]-Table1[[#This Row],[Cancellations (units)4]]+Table1[[#This Row],[Re-Orders Invoiced (units)5]]+Table1[[#This Row],[Stock Clearance Invoiced (units)6]]+Table1[[#This Row],[Returns Processed (units)7]] -> 4971 | Z12: =Table1[[#This Row],[Net Sales (€)2]]/Table1[[#This Row],[Net Sales (Units0]] -> 44.172617 | AA12: 5502 | AB12: 654 | AC12: =IFERROR(Table1[[#This Row],[Cancellations (units)4]]/Table1[[#This Row],[Pre-Orders Invoiced (units)3]],0) -> 0.11886587 | AD12: 23 | AE12: =IFERROR(Table1[[#This Row],[Re-Orders Invoiced (units)5]]/Table1[[#This Row],[Pre-Orders Invoiced (units)3]],0) -> 0.0041802981 | AF12: 100 | AG12: =IFERROR(Table1[[#This Row],[Stock Clearance Invoiced (units)6]]/Table1[[#This Row],[Pre-Orders Invoiced (units)3]],0) -> 0.018175209 | AH12: 0 | AI12: =IFERROR(Table1[[#This Row],[Returns Processed (units)7]]/Table1[[#This Row],[Pre-Orders Invoiced (units)3]],0) -> 0 | AJ12: =Table1[[#This Row],[Net Sales (€)2]]/Table1[[#This Row],[Net Sales (€)]] -> 0.071869627 | AK12: =Table1[[#This Row],[Net Sales (Units0]]+Table1[[#This Row],[Net Sales Units]] -> 49971 | AL12: =Table1[[#This Row],[Net Sales (€)2]]+Table1[[#This Row],[Net Sales (€)]] -> 3274865.5 | AM12: 20200 | AN12: 1675 | AO12: =Table1[[#This Row],[Pre-Orders Invoiced (units)]]-Table1[[#This Row],[Cancellations (units)]]+Table1[[#This Row],[Re-Orders Invoiced (units)]]+Table1[[#This Row],[Stock Clearance Invoiced (units)]]+Table1[[#This Row],[Returns Processed (units)]] -> 45000 | AP12: =Table1[[#This Row],[Net Sales (€)]]/AO12 -> 67.895187 | AQ12: =AA12-+AB12+Table1[[#This Row],[Re-Orders Invoiced (units)5]]+AF12+AH12 -> 4971 | AR12: =IFERROR(Table1[[#This Row],[Net Sales (€)2]]/AQ12,"") -> 44.172617 | AT12: =L12+X12 -> 3274865.5 | AU12: =F12*$AU$1 -> 3944192.5 | AV12: =AT12/AU12-1 -> -0.16969937 | AW12: =AU12/$AU$2 -> 0.041160947 | AX12: =ROUND(AW12*AV12*10000,0) -> -70 | AZ12: =AU12*(1-'SS24 Q2 Data'!$AB$5) -> 3620112 | BA12: =L12/AZ12-1 -> -0.15602517 | BB12: =AZ12/$AZ$2 -> 0.041160947 | BC12: =BB12*BA12*10000 -> -64.221438 | BE12: =AU12*'SS24 Q2 Data'!$AB$5 -> 324080.48 | BF12: =X12/BE12-1 -> -0.32244583 | BG12: =BE12/$BE$2 -> 0.041160947 | BH12: =BG12*BF12*10000 -> -132.72176 | BJ12: =Table1[[#This Row],[Net Sales Units]]/Table1[[#This Row],[Shoe Budget Units]] -> 0.47739533 | BK12: =Table1[[#This Row],[Net Sales (Units0]]/Table1[[#This Row],[Apparel Budget Units]] -> 0.58908579 | BL12: =Table1[[#This Row],[Net Sales Units total]]/Table1[[#This Row],[Units]] -> 0.48657254 | BM12: =ROUND(Table1[[#This Row],[Net Sales Units]]/'Hypotesis Panel'!$G$8,0) -> 3214 | BN12: =ROUND('Hypotesis Panel'!$G$8/Table1[[#This Row],[ST% Shoes]],0) -> 29 | BO12: =Table1[[#This Row],[Net Sales (Units0]]/'Hypotesis Panel'!$G$8 -> 355.07143 | BP12: =IFERROR(ROUND('Hypotesis Panel'!$G$8/Table1[[#This Row],[ST% Apparel]],0),"NoStock") -> 24 | BQ12: =IFERROR(ROUND('Hypotesis Panel'!$G$8/Table1[[#This Row],[ST% ToTal]],0),"") -> 29 | BR12: =Table1[[#This Row],[Expected WoOS Shoes]]-'Hypotesis Panel'!$G$8 -> 15 | BS12: =IFERROR(Table1[[#This Row],[Expected WoOS Apparel]]-'Hypotesis Panel'!$G$8,"") -> 10 | BT12: =Table1[[#This Row],[Expected WoOS Total]]-'Hypotesis Panel'!$G$8 -> 15 | BU12: =Table1[[#This Row],[WOCoverage Shoes]]+'Hypotesis Panel'!$G$8-'Hypotesis Panel'!$F$3 -> 3 | BV12: =_xlfn.XLOOKUP(Table1[[#This Row],[WOS at WK26 Shoes]],Table2[Lower Bound],Table2[Action],,-1) -> Monitor | BW12: =IF(Table1[[#This Row],[WOS at WK26 Shoes]]*Table1[[#This Row],[Avg Shoes Q1 Weekly Sales]]*Table1[[#This Row],[Actual ASP Shoes per channel]]>0,0,Table1[[#This Row],[WOS at WK26 Shoes]]*Table1[[#This Row],[Avg Shoes Q1 Weekly Sales]]*Table1[[#This Row],[Actual ASP Shoes per channel]]) -> 0 | BX12: =Table1[[#This Row],[WOC Apparel]]+'Hypotesis Panel'!$G$8-'Hypotesis Panel'!$F$3 -> -2 | BY12: =_xlfn.XLOOKUP(Table1[[#This Row],[WOS at WK26 Apparel]],Table2[Lower Bound],Table2[Action],,-1) -> Stock Out Risk | CA12: =ROUND(Table1[[#This Row],[% Budget share]]*'Available Stock'!$H$6,0) -> 40940 | CB12: =ROUND(Table1[[#This Row],[% Budget share]]*'Available Stock'!$I$6,0) -> 24564 | CC12: =Table1[[#This Row],[Net Sales (Units0]]/'Hypotesis Panel'!$G$8 -> 355.07143 | CD12: =ROUND(Table1[[#This Row],[% Budget share]]*'Available Stock'!$H$7,0) -> 6122 | CE12: =ROUND(Table1[[#This Row],[% Budget share]]*'Available Stock'!$I$7,0) -> 1714 | CF12: =Table1[[#This Row],[Shoes Available Q2 Stock Current Season ]]/#REF! -> #REF! | CG12: =Table1[[#This Row],[Shoes Available Q2 Stock Old Season]]/#REF! -> #REF! | CH12: =SUM(Table1[[#This Row],[Q2 Shoes New Stock WOC based on Q1 Sales Velocity]:[Q2 Shoes Old Stock WOC based on Q1 Sales Velocity]]) -> #REF! | CI12: =IFERROR(Table1[[#This Row],[Apparel Q2 Available Stock Current Season 2]]/Table1[[#This Row],[Avg Apparel Q1 Weekly Sales2]],"") -> 17.241601 | CJ12: =IFERROR(Table1[[#This Row],[Apparel Q2Available Stock Old Season3]]/Table1[[#This Row],[Avg Apparel Q1 Weekly Sales2]],"") -> 4.8271977 | CK12: =SUM(Table1[[#This Row],[Q2 Apparel New Stock WOC based on Q1 Sales Velocity]:[Q2 Apparel Old Stock WOC based on Q1 Sales Velocity]]) -> 22.068799
A13: North | B13: France | C13: Field Accounts | D13: =_xlfn.CONCAT(Table1[[#This Row],[Sub Region]:[Account]]) -> NorthFranceField Accounts | E13: =_xlfn.IFNA(VLOOKUP(Table1[[#This Row],[Account]],'Account Information'!$A$4:$B$18,2,FALSE),"") -> Field Accounts | F13: 7911060 | G13: 118500 | H13: =Table1[[#This Row],[Units]]/$G$2 -> 0.048527786 | I13: =F13/G13 -> 66.76 | J13: =Table1[[#This Row],[Units]]*(1-'Hypotesis Panel'!$F$46) -> 108763.27 | K13: =Table1[[#This Row],[Units]]-Table1[[#This Row],[Shoe Budget Units]] -> 9736.7299 | L13: 3287347.2 | M13: 39300 | N13: =Table1[[#This Row],[Pre-Orders Invoiced (units)]]-Table1[[#This Row],[Cancellations (units)]]+Table1[[#This Row],[Re-Orders Invoiced (units)]]+Table1[[#This Row],[Stock Clearance Invoiced (units)]]+Table1[[#This Row],[Returns Processed (units)]] -> 40000 | O13: =Table1[[#This Row],[Net Sales (€)]]/Table1[[#This Row],[Net Sales Units]] -> 82.18368 | P13: 6300 | Q13: =Table1[[#This Row],[Cancellations (units)]]/Table1[[#This Row],[Pre-Orders Invoiced (units)]] -> 0.16030534 | R13: 5600 | S13: =Table1[[#This Row],[Re-Orders Invoiced (units)]]/Table1[[#This Row],[Pre-Orders Invoiced (units)]] -> 0.14249364 | T13: 2600 | U13: =Table1[[#This Row],[Stock Clearance Invoiced (units)]]/Table1[[#This Row],[Pre-Orders Invoiced (units)]] -> 0.066157761 | V13: -1200 | W13: =Table1[[#This Row],[Returns Processed (units)]]/Table1[[#This Row],[Pre-Orders Invoiced (units)]] -> -0.030534351 | X13: 468849.66 | Y13: =Table1[[#This Row],[Pre-Orders Invoiced (units)3]]-Table1[[#This Row],[Cancellations (units)4]]+Table1[[#This Row],[Re-Orders Invoiced (units)5]]+Table1[[#This Row],[Stock Clearance Invoiced (units)6]]+Table1[[#This Row],[Returns Processed (units)7]] -> 10111 | Z13: =Table1[[#This Row],[Net Sales (€)2]]/Table1[[#This Row],[Net Sales (Units0]] -> 46.370256 | AA13: 7860 | AB13: 345 | AC13: =IFERROR(Table1[[#This Row],[Cancellations (units)4]]/Table1[[#This Row],[Pre-Orders Invoiced (units)3]],0) -> 0.04389313 | AD13: 230 | AE13: =IFERROR(Table1[[#This Row],[Re-Orders Invoiced (units)5]]/Table1[[#This Row],[Pre-Orders Invoiced (units)3]],0) -> 0.029262087 | AF13: 2600 | AG13: =IFERROR(Table1[[#This Row],[Stock Clearance Invoiced (units)6]]/Table1[[#This Row],[Pre-Orders Invoiced (units)3]],0) -> 0.3307888 | AH13: -234 | AI13: =IFERROR(Table1[[#This Row],[Returns Processed (units)7]]/Table1[[#This Row],[Pre-Orders Invoiced (units)3]],0) -> -0.029770992 | AJ13: =Table1[[#This Row],[Net Sales (€)2]]/Table1[[#This Row],[Net Sales (€)]] -> 0.1426225 | AK13: =Table1[[#This Row],[Net Sales (Units0]]+Table1[[#This Row],[Net Sales Units]] -> 50111 | AL13: =Table1[[#This Row],[Net Sales (€)2]]+Table1[[#This Row],[Net Sales (€)]] -> 3756196.9 | AM13: 21000 | AN13: 1238 | AO13: =Table1[[#This Row],[Pre-Orders Invoiced (units)]]-Table1[[#This Row],[Cancellations (units)]]+Table1[[#This Row],[Re-Orders Invoiced (units)]]+Table1[[#This Row],[Stock Clearance Invoiced (units)]]+Table1[[#This Row],[Returns Processed (units)]] -> 40000 | AP13: =Table1[[#This Row],[Net Sales (€)]]/AO13 -> 82.18368 | AQ13: =AA13-+AB13+Table1[[#This Row],[Re-Orders Invoiced (units)5]]+AF13+AH13 -> 10111 | AR13: =IFERROR(Table1[[#This Row],[Net Sales (€)2]]/AQ13,"") -> 46.370256 | AT13: =L13+X13 -> 3756196.9 | AU13: =F13*$AU$1 -> 5142189 | AV13: =AT13/AU13-1 -> -0.26953349 | AW13: =AU13/$AU$2 -> 0.053663043 | AX13: =ROUND(AW13*AV13*10000,0) -> -145 | AZ13: =AU13*(1-'SS24 Q2 Data'!$AB$5) -> 4719673.3 | BA13: =L13/AZ13-1 -> -0.30347993 | BB13: =AZ13/$AZ$2 -> 0.053663043 | BC13: =BB13*BA13*10000 -> -162.85657 | BE13: =AU13*'SS24 Q2 Data'!$AB$5 -> 422515.66 | BF13: =X13/BE13-1 -> 0.10966222 | BG13: =BE13/$BE$2 -> 0.053663043 | BH13: =BG13*BF13*10000 -> 58.848082 | BJ13: =Table1[[#This Row],[Net Sales Units]]/Table1[[#This Row],[Shoe Budget Units]] -> 0.36777122 | BK13: =Table1[[#This Row],[Net Sales (Units0]]/Table1[[#This Row],[Apparel Budget Units]] -> 1.038439 | BL13: =Table1[[#This Row],[Net Sales Units total]]/Table1[[#This Row],[Units]] -> 0.42287764 | BM13: =ROUND(Table1[[#This Row],[Net Sales Units]]/'Hypotesis Panel'!$G$8,0) -> 2857 | BN13: =ROUND('Hypotesis Panel'!$G$8/Table1[[#This Row],[ST% Shoes]],0) -> 38 | BO13: =Table1[[#This Row],[Net Sales (Units0]]/'Hypotesis Panel'!$G$8 -> 722.21429 | BP13: =IFERROR(ROUND('Hypotesis Panel'!$G$8/Table1[[#This Row],[ST% Apparel]],0),"NoStock") -> 13 | BQ13: =IFERROR(ROUND('Hypotesis Panel'!$G$8/Table1[[#This Row],[ST% ToTal]],0),"") -> 33 | BR13: =Table1[[#This Row],[Expected WoOS Shoes]]-'Hypotesis Panel'!$G$8 -> 24 | BS13: =IFERROR(Table1[[#This Row],[Expected WoOS Apparel]]-'Hypotesis Panel'!$G$8,"") -> -1 | BT13: =Table1[[#This Row],[Expected WoOS Total]]-'Hypotesis Panel'!$G$8 -> 19 | BU13: =Table1[[#This Row],[WOCoverage Shoes]]+'Hypotesis Panel'!$G$8-'Hypotesis Panel'!$F$3 -> 12 | BV13: =_xlfn.XLOOKUP(Table1[[#This Row],[WOS at WK26 Shoes]],Table2[Lower Bound],Table2[Action],,-1) -> Overstock | BW13: =IF(Table1[[#This Row],[WOS at WK26 Shoes]]*Table1[[#This Row],[Avg Shoes Q1 Weekly Sales]]*Table1[[#This Row],[Actual ASP Shoes per channel]]>0,0,Table1[[#This Row],[WOS at WK26 Shoes]]*Table1[[#This Row],[Avg Shoes Q1 Weekly Sales]]*Table1[[#This Row],[Actual ASP Shoes per channel]]) -> 0 | BX13: =Table1[[#This Row],[WOC Apparel]]+'Hypotesis Panel'!$G$8-'Hypotesis Panel'!$F$3 -> -13 | BY13: =_xlfn.XLOOKUP(Table1[[#This Row],[WOS at WK26 Apparel]],Table2[Lower Bound],Table2[Action],,-1) -> Stock Out Risk | CA13: =ROUND(Table1[[#This Row],[% Budget share]]*'Available Stock'!$H$6,0) -> 47239 | CB13: =ROUND(Table1[[#This Row],[% Budget share]]*'Available Stock'!$I$6,0) -> 28343 | CC13: =Table1[[#This Row],[Net Sales (Units0]]/'Hypotesis Panel'!$G$8 -> 722.21429 | CD13: =ROUND(Table1[[#This Row],[% Budget share]]*'Available Stock'!$H$7,0) -> 7063 | CE13: =ROUND(Table1[[#This Row],[% Budget share]]*'Available Stock'!$I$7,0) -> 1978 | CF13: =Table1[[#This Row],[Shoes Available Q2 Stock Current Season ]]/#REF! -> #REF! | CG13: =Table1[[#This Row],[Shoes Available Q2 Stock Old Season]]/#REF! -> #REF! | CH13: =SUM(Table1[[#This Row],[Q2 Shoes New Stock WOC based on Q1 Sales Velocity]:[Q2 Shoes Old Stock WOC based on Q1 Sales Velocity]]) -> #REF! | CI13: =IFERROR(Table1[[#This Row],[Apparel Q2 Available Stock Current Season 2]]/Table1[[#This Row],[Avg Apparel Q1 Weekly Sales2]],"") -> 9.7796459 | CJ13: =IFERROR(Table1[[#This Row],[Apparel Q2Available Stock Old Season3]]/Table1[[#This Row],[Avg Apparel Q1 Weekly Sales2]],"") -> 2.7387993 | CK13: =SUM(Table1[[#This Row],[Q2 Apparel New Stock WOC based on Q1 Sales Velocity]:[Q2 Apparel Old Stock WOC based on Q1 Sales Velocity]]) -> 12.518445
A14: Central | B14: Switzerland | C14: Field Accounts | D14: =_xlfn.CONCAT(Table1[[#This Row],[Sub Region]:[Account]]) -> CentralSwitzerlandField Accounts | E14: =_xlfn.IFNA(VLOOKUP(Table1[[#This Row],[Account]],'Account Information'!$A$4:$B$18,2,FALSE),"") -> Field Accounts | F14: 4711869.6 | G14: 63600 | H14: =Table1[[#This Row],[Units]]/$G$2 -> 0.026045293 | I14: =F14/G14 -> 74.086 | J14: =Table1[[#This Row],[Units]]*(1-'Hypotesis Panel'!$F$46) -> 58374.211 | K14: =Table1[[#This Row],[Units]]-Table1[[#This Row],[Shoe Budget Units]] -> 5225.7892 | L14: 3328956 | M14: 42400 | N14: =Table1[[#This Row],[Pre-Orders Invoiced (units)]]-Table1[[#This Row],[Cancellations (units)]]+Table1[[#This Row],[Re-Orders Invoiced (units)]]+Table1[[#This Row],[Stock Clearance Invoiced (units)]]+Table1[[#This Row],[Returns Processed (units)]] -> 39200 | O14: =Table1[[#This Row],[Net Sales (€)]]/Table1[[#This Row],[Net Sales Units]] -> 84.922347 | P14: 1900 | Q14: =Table1[[#This Row],[Cancellations (units)]]/Table1[[#This Row],[Pre-Orders Invoiced (units)]] -> 0.044811321 | R14: 4600 | S14: =Table1[[#This Row],[Re-Orders Invoiced (units)]]/Table1[[#This Row],[Pre-Orders Invoiced (units)]] -> 0.10849057 | T14: 0 | U14: =Table1[[#This Row],[Stock Clearance Invoiced (units)]]/Table1[[#This Row],[Pre-Orders Invoiced (units)]] -> 0 | V14: -5900 | W14: =Table1[[#This Row],[Returns Processed (units)]]/Table1[[#This Row],[Pre-Orders Invoiced (units)]] -> -0.13915094 | X14: 338168.45 | Y14: =Table1[[#This Row],[Pre-Orders Invoiced (units)3]]-Table1[[#This Row],[Cancellations (units)4]]+Table1[[#This Row],[Re-Orders Invoiced (units)5]]+Table1[[#This Row],[Stock Clearance Invoiced (units)6]]+Table1[[#This Row],[Returns Processed (units)7]] -> 6277 | Z14: =Table1[[#This Row],[Net Sales (€)2]]/Table1[[#This Row],[Net Sales (Units0]] -> 53.874216 | AA14: 8480 | AB14: 432 | AC14: =IFERROR(Table1[[#This Row],[Cancellations (units)4]]/Table1[[#This Row],[Pre-Orders Invoiced (units)3]],0) -> 0.050943396 | AD14: 234 | AE14: =IFERROR(Table1[[#This Row],[Re-Orders Invoiced (units)5]]/Table1[[#This Row],[Pre-Orders Invoiced (units)3]],0) -> 0.02759434 | AF14: 0 | AG14: =IFERROR(Table1[[#This Row],[Stock Clearance Invoiced (units)6]]/Table1[[#This Row],[Pre-Orders Invoiced (units)3]],0) -> 0 | AH14: -2005 | AI14: =IFERROR(Table1[[#This Row],[Returns Processed (units)7]]/Table1[[#This Row],[Pre-Orders Invoiced (units)3]],0) -> -0.23643868 | AJ14: =Table1[[#This Row],[Net Sales (€)2]]/Table1[[#This Row],[Net Sales (€)]] -> 0.10158394 | AK14: =Table1[[#This Row],[Net Sales (Units0]]+Table1[[#This Row],[Net Sales Units]] -> 45477 | AL14: =Table1[[#This Row],[Net Sales (€)2]]+Table1[[#This Row],[Net Sales (€)]] -> 3667124.5 | AM14: 8700 | AN14: 30324 | AO14: =Table1[[#This Row],[Pre-Orders Invoiced (units)]]-Table1[[#This Row],[Cancellations (units)]]+Table1[[#This Row],[Re-Orders Invoiced (units)]]+Table1[[#This Row],[Stock Clearance Invoiced (units)]]+Table1[[#This Row],[Returns Processed (units)]] -> 39200 | AP14: =Table1[[#This Row],[Net Sales (€)]]/AO14 -> 84.922347 | AQ14: =AA14-+AB14+Table1[[#This Row],[Re-Orders Invoiced (units)5]]+AF14+AH14 -> 6277 | AR14: =IFERROR(Table1[[#This Row],[Net Sales (€)2]]/AQ14,"") -> 53.874216 | AT14: =L14+X14 -> 3667124.5 | AU14: =F14*$AU$1 -> 3062715.2 | AV14: =AT14/AU14-1 -> 0.19734424 | AW14: =AU14/$AU$2 -> 0.031961995 | AX14: =ROUND(AW14*AV14*10000,0) -> 63 | AZ14: =AU14*(1-'SS24 Q2 Data'!$AB$5) -> 2811062.7 | BA14: =L14/AZ14-1 -> 0.18423401 | BB14: =AZ14/$AZ$2 -> 0.031961995 | BC14: =BB14*BA14*10000 -> 58.884865 | BE14: =AU14*'SS24 Q2 Data'!$AB$5 -> 251652.58 | BF14: =X14/BE14-1 -> 0.34379091 | BG14: =BE14/$BE$2 -> 0.031961995 | BH14: =BG14*BF14*10000 -> 109.88243 | BJ14: =Table1[[#This Row],[Net Sales Units]]/Table1[[#This Row],[Shoe Budget Units]] -> 0.67152942 | BK14: =Table1[[#This Row],[Net Sales (Units0]]/Table1[[#This Row],[Apparel Budget Units]] -> 1.2011583 | BL14: =Table1[[#This Row],[Net Sales Units total]]/Table1[[#This Row],[Units]] -> 0.71504717 | BM14: =ROUND(Table1[[#This Row],[Net Sales Units]]/'Hypotesis Panel'!$G$8,0) -> 2800 | BN14: =ROUND('Hypotesis Panel'!$G$8/Table1[[#This Row],[ST% Shoes]],0) -> 21 | BO14: =Table1[[#This Row],[Net Sales (Units0]]/'Hypotesis Panel'!$G$8 -> 448.35714 | BP14: =IFERROR(ROUND('Hypotesis Panel'!$G$8/Table1[[#This Row],[ST% Apparel]],0),"NoStock") -> 12 | BQ14: =IFERROR(ROUND('Hypotesis Panel'!$G$8/Table1[[#This Row],[ST% ToTal]],0),"") -> 20 | BR14: =Table1[[#This Row],[Expected WoOS Shoes]]-'Hypotesis Panel'!$G$8 -> 7 | BS14: =IFERROR(Table1[[#This Row],[Expected WoOS Apparel]]-'Hypotesis Panel'!$G$8,"") -> -2 | BT14: =Table1[[#This Row],[Expected WoOS Total]]-'Hypotesis Panel'!$G$8 -> 6 | BU14: =Table1[[#This Row],[WOCoverage Shoes]]+'Hypotesis Panel'!$G$8-'Hypotesis Panel'!$F$3 -> -5 | BV14: =_xlfn.XLOOKUP(Table1[[#This Row],[WOS at WK26 Shoes]],Table2[Lower Bound],Table2[Action],,-1) -> Stock Out Risk | BW14: =IF(Table1[[#This Row],[WOS at WK26 Shoes]]*Table1[[#This Row],[Avg Shoes Q1 Weekly Sales]]*Table1[[#This Row],[Actual ASP Shoes per channel]]>0,0,Table1[[#This Row],[WOS at WK26 Shoes]]*Table1[[#This Row],[Avg Shoes Q1 Weekly Sales]]*Table1[[#This Row],[Actual ASP Shoes per channel]]) -> -1188912.9 | BX14: =Table1[[#This Row],[WOC Apparel]]+'Hypotesis Panel'!$G$8-'Hypotesis Panel'!$F$3 -> -14 | BY14: =_xlfn.XLOOKUP(Table1[[#This Row],[WOS at WK26 Apparel]],Table2[Lower Bound],Table2[Action],,-1) -> Stock Out Risk | CA14: =ROUND(Table1[[#This Row],[% Budget share]]*'Available Stock'!$H$6,0) -> 25354 | CB14: =ROUND(Table1[[#This Row],[% Budget share]]*'Available Stock'!$I$6,0) -> 15212 | CC14: =Table1[[#This Row],[Net Sales (Units0]]/'Hypotesis Panel'!$G$8 -> 448.35714 | CD14: =ROUND(Table1[[#This Row],[% Budget share]]*'Available Stock'!$H$7,0) -> 3791 | CE14: =ROUND(Table1[[#This Row],[% Budget share]]*'Available Stock'!$I$7,0) -> 1061 | CF14: =Table1[[#This Row],[Shoes Available Q2 Stock Current Season ]]/#REF! -> #REF! | CG14: =Table1[[#This Row],[Shoes Available Q2 Stock Old Season]]/#REF! -> #REF! | CH14: =SUM(Table1[[#This Row],[Q2 Shoes New Stock WOC based on Q1 Sales Velocity]:[Q2 Shoes Old Stock WOC based on Q1 Sales Velocity]]) -> #REF! | CI14: =IFERROR(Table1[[#This Row],[Apparel Q2 Available Stock Current Season 2]]/Table1[[#This Row],[Avg Apparel Q1 Weekly Sales2]],"") -> 8.455313 | CJ14: =IFERROR(Table1[[#This Row],[Apparel Q2Available Stock Old Season3]]/Table1[[#This Row],[Avg Apparel Q1 Weekly Sales2]],"") -> 2.3664171 | CK14: =SUM(Table1[[#This Row],[Q2 Apparel New Stock WOC based on Q1 Sales Velocity]:[Q2 Apparel Old Stock WOC based on Q1 Sales Velocity]]) -> 10.82173
A15: South | B15: Spain | C15: Aurelian & Co. | D15: =_xlfn.CONCAT(Table1[[#This Row],[Sub Region]:[Account]]) -> SouthSpainAurelian & Co. | E15: =_xlfn.IFNA(VLOOKUP(Table1[[#This Row],[Account]],'Account Information'!$A$4:$B$18,2,FALSE),"") -> Lifestyle / Sport | F15: 4762982.7 | G15: 78300 | H15: =Table1[[#This Row],[Units]]/$G$2 -> 0.032065195 | I15: =F15/G15 -> 60.82992 | J15: =Table1[[#This Row],[Units]]*(1-'Hypotesis Panel'!$F$46) -> 71866.363 | K15: =Table1[[#This Row],[Units]]-Table1[[#This Row],[Shoe Budget Units]] -> 6433.6367 | L15: 2102250.3 | M15: 28400 | N15: =Table1[[#This Row],[Pre-Orders Invoiced (units)]]-Table1[[#This Row],[Cancellations (units)]]+Table1[[#This Row],[Re-Orders Invoiced (units)]]+Table1[[#This Row],[Stock Clearance Invoiced (units)]]+Table1[[#This Row],[Returns Processed (units)]] -> 31900 | O15: =Table1[[#This Row],[Net Sales (€)]]/Table1[[#This Row],[Net Sales Units]] -> 65.901263 | P15: 400 | Q15: =Table1[[#This Row],[Cancellations (units)]]/Table1[[#This Row],[Pre-Orders Invoiced (units)]] -> 0.014084507 | R15: 4000 | S15: =Table1[[#This Row],[Re-Orders Invoiced (units)]]/Table1[[#This Row],[Pre-Orders Invoiced (units)]] -> 0.14084507 | T15: 0 | U15: =Table1[[#This Row],[Stock Clearance Invoiced (units)]]/Table1[[#This Row],[Pre-Orders Invoiced (units)]] -> 0 | V15: -100 | W15: =Table1[[#This Row],[Returns Processed (units)]]/Table1[[#This Row],[Pre-Orders Invoiced (units)]] -> -0.0035211268 | X15: 323066.32 | Y15: =Table1[[#This Row],[Pre-Orders Invoiced (units)3]]-Table1[[#This Row],[Cancellations (units)4]]+Table1[[#This Row],[Re-Orders Invoiced (units)5]]+Table1[[#This Row],[Stock Clearance Invoiced (units)6]]+Table1[[#This Row],[Returns Processed (units)7]] -> 6498 | Z15: =Table1[[#This Row],[Net Sales (€)2]]/Table1[[#This Row],[Net Sales (Units0]] -> 49.717809 | AA15: 6532 | AB15: 54 | AC15: =IFERROR(Table1[[#This Row],[Cancellations (units)4]]/Table1[[#This Row],[Pre-Orders Invoiced (units)3]],0) -> 0.0082669933 | AD15: 20 | AE15: =IFERROR(Table1[[#This Row],[Re-Orders Invoiced (units)5]]/Table1[[#This Row],[Pre-Orders Invoiced (units)3]],0) -> 0.0030618494 | AF15: 0 | AG15: =IFERROR(Table1[[#This Row],[Stock Clearance Invoiced (units)6]]/Table1[[#This Row],[Pre-Orders Invoiced (units)3]],0) -> 0 | AH15: 0 | AI15: =IFERROR(Table1[[#This Row],[Returns Processed (units)7]]/Table1[[#This Row],[Pre-Orders Invoiced (units)3]],0) -> 0 | AJ15: =Table1[[#This Row],[Net Sales (€)2]]/Table1[[#This Row],[Net Sales (€)]] -> 0.15367643 | AK15: =Table1[[#This Row],[Net Sales (Units0]]+Table1[[#This Row],[Net Sales Units]] -> 38398 | AL15: =Table1[[#This Row],[Net Sales (€)2]]+Table1[[#This Row],[Net Sales (€)]] -> 2425316.6 | AM15: 10700 | AN15: 1532 | AO15: =Table1[[#This Row],[Pre-Orders Invoiced (units)]]-Table1[[#This Row],[Cancellations (units)]]+Table1[[#This Row],[Re-Orders Invoiced (units)]]+Table1[[#This Row],[Stock Clearance Invoiced (units)]]+Table1[[#This Row],[Returns Processed (units)]] -> 31900 | AP15: =Table1[[#This Row],[Net Sales (€)]]/AO15 -> 65.901263 | AQ15: =AA15-+AB15+Table1[[#This Row],[Re-Orders Invoiced (units)5]]+AF15+AH15 -> 6498 | AR15: =IFERROR(Table1[[#This Row],[Net Sales (€)2]]/AQ15,"") -> 49.717809 | AT15: =L15+X15 -> 2425316.6 | AU15: =F15*$AU$1 -> 3095938.8 | AV15: =AT15/AU15-1 -> -0.21661351 | AW15: =AU15/$AU$2 -> 0.03230871 | AX15: =ROUND(AW15*AV15*10000,0) -> -70 | AZ15: =AU15*(1-'SS24 Q2 Data'!$AB$5) -> 2841556.3 | BA15: =L15/AZ15-1 -> -0.26017645 | BB15: =AZ15/$AZ$2 -> 0.03230871 | BC15: =BB15*BA15*10000 -> -84.059655 | BE15: =AU15*'SS24 Q2 Data'!$AB$5 -> 254382.44 | BF15: =X15/BE15-1 -> 0.27000243 | BG15: =BE15/$BE$2 -> 0.03230871 | BH15: =BG15*BF15*10000 -> 87.234303 | BJ15: =Table1[[#This Row],[Net Sales Units]]/Table1[[#This Row],[Shoe Budget Units]] -> 0.44387942 | BK15: =Table1[[#This Row],[Net Sales (Units0]]/Table1[[#This Row],[Apparel Budget Units]] -> 1.0100042 | BL15: =Table1[[#This Row],[Net Sales Units total]]/Table1[[#This Row],[Units]] -> 0.49039591 | BM15: =ROUND(Table1[[#This Row],[Net Sales Units]]/'Hypotesis Panel'!$G$8,0) -> 2279 | BN15: =ROUND('Hypotesis Panel'!$G$8/Table1[[#This Row],[ST% Shoes]],0) -> 32 | BO15: =Table1[[#This Row],[Net Sales (Units0]]/'Hypotesis Panel'!$G$8 -> 464.14286 | BP15: =IFERROR(ROUND('Hypotesis Panel'!$G$8/Table1[[#This Row],[ST% Apparel]],0),"NoStock") -> 14 | BQ15: =IFERROR(ROUND('Hypotesis Panel'!$G$8/Table1[[#This Row],[ST% ToTal]],0),"") -> 29 | BR15: =Table1[[#This Row],[Expected WoOS Shoes]]-'Hypotesis Panel'!$G$8 -> 18 | BS15: =IFERROR(Table1[[#This Row],[Expected WoOS Apparel]]-'Hypotesis Panel'!$G$8,"") -> 0 | BT15: =Table1[[#This Row],[Expected WoOS Total]]-'Hypotesis Panel'!$G$8 -> 15 | BU15: =Table1[[#This Row],[WOCoverage Shoes]]+'Hypotesis Panel'!$G$8-'Hypotesis Panel'!$F$3 -> 6 | BV15: =_xlfn.XLOOKUP(Table1[[#This Row],[WOS at WK26 Shoes]],Table2[Lower Bound],Table2[Action],,-1) -> Overstock | BW15: =IF(Table1[[#This Row],[WOS at WK26 Shoes]]*Table1[[#This Row],[Avg Shoes Q1 Weekly Sales]]*Table1[[#This Row],[Actual ASP Shoes per channel]]>0,0,Table1[[#This Row],[WOS at WK26 Shoes]]*Table1[[#This Row],[Avg Shoes Q1 Weekly Sales]]*Table1[[#This Row],[Actual ASP Shoes per channel]]) -> 0 | BX15: =Table1[[#This Row],[WOC Apparel]]+'Hypotesis Panel'!$G$8-'Hypotesis Panel'!$F$3 -> -12 | BY15: =_xlfn.XLOOKUP(Table1[[#This Row],[WOS at WK26 Apparel]],Table2[Lower Bound],Table2[Action],,-1) -> Stock Out Risk | CA15: =ROUND(Table1[[#This Row],[% Budget share]]*'Available Stock'!$H$6,0) -> 31214 | CB15: =ROUND(Table1[[#This Row],[% Budget share]]*'Available Stock'!$I$6,0) -> 18728 | CC15: =Table1[[#This Row],[Net Sales (Units0]]/'Hypotesis Panel'!$G$8 -> 464.14286 | CD15: =ROUND(Table1[[#This Row],[% Budget share]]*'Available Stock'!$H$7,0) -> 4667 | CE15: =ROUND(Table1[[#This Row],[% Budget share]]*'Available Stock'!$I$7,0) -> 1307 | CF15: =Table1[[#This Row],[Shoes Available Q2 Stock Current Season ]]/#REF! -> #REF! | CG15: =Table1[[#This Row],[Shoes Available Q2 Stock Old Season]]/#REF! -> #REF! | CH15: =SUM(Table1[[#This Row],[Q2 Shoes New Stock WOC based on Q1 Sales Velocity]:[Q2 Shoes Old Stock WOC based on Q1 Sales Velocity]]) -> #REF! | CI15: =IFERROR(Table1[[#This Row],[Apparel Q2 Available Stock Current Season 2]]/Table1[[#This Row],[Avg Apparel Q1 Weekly Sales2]],"") -> 10.055094 | CJ15: =IFERROR(Table1[[#This Row],[Apparel Q2Available Stock Old Season3]]/Table1[[#This Row],[Avg Apparel Q1 Weekly Sales2]],"") -> 2.8159434 | CK15: =SUM(Table1[[#This Row],[Q2 Apparel New Stock WOC based on Q1 Sales Velocity]:[Q2 Apparel Old Stock WOC based on Q1 Sales Velocity]]) -> 12.871037
A16: Europe | B16: Europe | C16: Axiom Street | D16: =_xlfn.CONCAT(Table1[[#This Row],[Sub Region]:[Account]]) -> EuropeEuropeAxiom Street | E16: =_xlfn.IFNA(VLOOKUP(Table1[[#This Row],[Account]],'Account Information'!$A$4:$B$18,2,FALSE),"") -> Lifestyle / Sport | F16: 2424493.2 | G16: 42500 | H16: =Table1[[#This Row],[Units]]/$G$2 -> 0.01740448 | I16: =F16/G16 -> 57.0469 | J16: =Table1[[#This Row],[Units]]*(1-'Hypotesis Panel'!$F$46) -> 39007.924 | K16: =Table1[[#This Row],[Units]]-Table1[[#This Row],[Shoe Budget Units]] -> 3492.0761 | L16: 1805037 | M16: 29200 | N16: =Table1[[#This Row],[Pre-Orders Invoiced (units)]]-Table1[[#This Row],[Cancellations (units)]]+Table1[[#This Row],[Re-Orders Invoiced (units)]]+Table1[[#This Row],[Stock Clearance Invoiced (units)]]+Table1[[#This Row],[Returns Processed (units)]] -> 26900 | O16: =Table1[[#This Row],[Net Sales (€)]]/Table1[[#This Row],[Net Sales Units]] -> 67.101747 | P16: 2900 | Q16: =Table1[[#This Row],[Cancellations (units)]]/Table1[[#This Row],[Pre-Orders Invoiced (units)]] -> 0.099315068 | R16: 600 | S16: =Table1[[#This Row],[Re-Orders Invoiced (units)]]/Table1[[#This Row],[Pre-Orders Invoiced (units)]] -> 0.020547945 | T16: 0 | U16: =Table1[[#This Row],[Stock Clearance Invoiced (units)]]/Table1[[#This Row],[Pre-Orders Invoiced (units)]] -> 0 | V16: 0 | W16: =Table1[[#This Row],[Returns Processed (units)]]/Table1[[#This Row],[Pre-Orders Invoiced (units)]] -> 0 | X16: 286846.99 | Y16: =Table1[[#This Row],[Pre-Orders Invoiced (units)3]]-Table1[[#This Row],[Cancellations (units)4]]+Table1[[#This Row],[Re-Orders Invoiced (units)5]]+Table1[[#This Row],[Stock Clearance Invoiced (units)6]]+Table1[[#This Row],[Returns Processed (units)7]] -> 5815.6 | Z16: =Table1[[#This Row],[Net Sales (€)2]]/Table1[[#This Row],[Net Sales (Units0]] -> 49.323714 | AA16: 6132 | AB16: 623 | AC16: =IFERROR(Table1[[#This Row],[Cancellations (units)4]]/Table1[[#This Row],[Pre-Orders Invoiced (units)3]],0) -> 0.10159817 | AD16: 306.6 | AE16: =IFERROR(Table1[[#This Row],[Re-Orders Invoiced (units)5]]/Table1[[#This Row],[Pre-Orders Invoiced (units)3]],0) -> 0.05 | AF16: 0 | AG16: =IFERROR(Table1[[#This Row],[Stock Clearance Invoiced (units)6]]/Table1[[#This Row],[Pre-Orders Invoiced (units)3]],0) -> 0 | AH16: 0 | AI16: =IFERROR(Table1[[#This Row],[Returns Processed (units)7]]/Table1[[#This Row],[Pre-Orders Invoiced (units)3]],0) -> 0 | AJ16: =Table1[[#This Row],[Net Sales (€)2]]/Table1[[#This Row],[Net Sales (€)]] -> 0.15891474 | AK16: =Table1[[#This Row],[Net Sales (Units0]]+Table1[[#This Row],[Net Sales Units]] -> 32715.6 | AL16: =Table1[[#This Row],[Net Sales (€)2]]+Table1[[#This Row],[Net Sales (€)]] -> 2091884 | AM16: 21900 | AN16: 2345 | AO16: =Table1[[#This Row],[Pre-Orders Invoiced (units)]]-Table1[[#This Row],[Cancellations (units)]]+Table1[[#This Row],[Re-Orders Invoiced (units)]]+Table1[[#This Row],[Stock Clearance Invoiced (units)]]+Table1[[#This Row],[Returns Processed (units)]] -> 26900 | AP16: =Table1[[#This Row],[Net Sales (€)]]/AO16 -> 67.101747 | AQ16: =AA16-+AB16+Table1[[#This Row],[Re-Orders Invoiced (units)5]]+AF16+AH16 -> 5815.6 | AR16: =IFERROR(Table1[[#This Row],[Net Sales (€)2]]/AQ16,"") -> 49.323714 | AT16: =L16+X16 -> 2091884 | AU16: =F16*$AU$1 -> 1575920.6 | AV16: =AT16/AU16-1 -> 0.32740442 | AW16: =AU16/$AU$2 -> 0.01644605 | AX16: =ROUND(AW16*AV16*10000,0) -> 54 | AZ16: =AU16*(1-'SS24 Q2 Data'!$AB$5) -> 1446432.7 | BA16: =L16/AZ16-1 -> 0.24792322 | BB16: =AZ16/$AZ$2 -> 0.01644605 | BC16: =BB16*BA16*10000 -> 40.773576 | BE16: =AU16*'SS24 Q2 Data'!$AB$5 -> 129487.88 | BF16: =X16/BE16-1 -> 1.2152421 | BG16: =BE16/$BE$2 -> 0.01644605 | BH16: =BG16*BF16*10000 -> 199.85931 | BJ16: =Table1[[#This Row],[Net Sales Units]]/Table1[[#This Row],[Shoe Budget Units]] -> 0.68960348 | BK16: =Table1[[#This Row],[Net Sales (Units0]]/Table1[[#This Row],[Apparel Budget Units]] -> 1.6653703 | BL16: =Table1[[#This Row],[Net Sales Units total]]/Table1[[#This Row],[Units]] -> 0.76977882 | BM16: =ROUND(Table1[[#This Row],[Net Sales Units]]/'Hypotesis Panel'!$G$8,0) -> 1921 | BN16: =ROUND('Hypotesis Panel'!$G$8/Table1[[#This Row],[ST% Shoes]],0) -> 20 | BO16: =Table1[[#This Row],[Net Sales (Units0]]/'Hypotesis Panel'!$G$8 -> 415.4 | BP16: =IFERROR(ROUND('Hypotesis Panel'!$G$8/Table1[[#This Row],[ST% Apparel]],0),"NoStock") -> 8 | BQ16: =IFERROR(ROUND('Hypotesis Panel'!$G$8/Table1[[#This Row],[ST% ToTal]],0),"") -> 18 | BR16: =Table1[[#This Row],[Expected WoOS Shoes]]-'Hypotesis Panel'!$G$8 -> 6 | BS16: =IFERROR(Table1[[#This Row],[Expected WoOS Apparel]]-'Hypotesis Panel'!$G$8,"") -> -6 | BT16: =Table1[[#This Row],[Expected WoOS Total]]-'Hypotesis Panel'!$G$8 -> 4 | BU16: =Table1[[#This Row],[WOCoverage Shoes]]+'Hypotesis Panel'!$G$8-'Hypotesis Panel'!$F$3 -> -6 | BV16: =_xlfn.XLOOKUP(Table1[[#This Row],[WOS at WK26 Shoes]],Table2[Lower Bound],Table2[Action],,-1) -> Stock Out Risk | BW16: =IF(Table1[[#This Row],[WOS at WK26 Shoes]]*Table1[[#This Row],[Avg Shoes Q1 Weekly Sales]]*Table1[[#This Row],[Actual ASP Shoes per channel]]>0,0,Table1[[#This Row],[WOS at WK26 Shoes]]*Table1[[#This Row],[Avg Shoes Q1 Weekly Sales]]*Table1[[#This Row],[Actual ASP Shoes per channel]]) -> -773414.74 | BX16: =Table1[[#This Row],[WOC Apparel]]+'Hypotesis Panel'!$G$8-'Hypotesis Panel'!$F$3 -> -18 | BY16: =_xlfn.XLOOKUP(Table1[[#This Row],[WOS at WK26 Apparel]],Table2[Lower Bound],Table2[Action],,-1) -> Stock Out Risk | CA16: =ROUND(Table1[[#This Row],[% Budget share]]*'Available Stock'!$H$6,0) -> 16942 | CB16: =ROUND(Table1[[#This Row],[% Budget share]]*'Available Stock'!$I$6,0) -> 10165 | CC16: =Table1[[#This Row],[Net Sales (Units0]]/'Hypotesis Panel'!$G$8 -> 415.4 | CD16: =ROUND(Table1[[#This Row],[% Budget share]]*'Available Stock'!$H$7,0) -> 2533 | CE16: =ROUND(Table1[[#This Row],[% Budget share]]*'Available Stock'!$I$7,0) -> 709 | CF16: =Table1[[#This Row],[Shoes Available Q2 Stock Current Season ]]/#REF! -> #REF! | CG16: =Table1[[#This Row],[Shoes Available Q2 Stock Old Season]]/#REF! -> #REF! | CH16: =SUM(Table1[[#This Row],[Q2 Shoes New Stock WOC based on Q1 Sales Velocity]:[Q2 Shoes Old Stock WOC based on Q1 Sales Velocity]]) -> #REF! | CI16: =IFERROR(Table1[[#This Row],[Apparel Q2 Available Stock Current Season 2]]/Table1[[#This Row],[Avg Apparel Q1 Weekly Sales2]],"") -> 6.0977371 | CJ16: =IFERROR(Table1[[#This Row],[Apparel Q2Available Stock Old Season3]]/Table1[[#This Row],[Avg Apparel Q1 Weekly Sales2]],"") -> 1.7067886 | CK16: =SUM(Table1[[#This Row],[Q2 Apparel New Stock WOC based on Q1 Sales Velocity]:[Q2 Apparel Old Stock WOC based on Q1 Sales Velocity]]) -> 7.8045258
A17: South | B17: Italy | C17: Field Accounts | D17: =_xlfn.CONCAT(Table1[[#This Row],[Sub Region]:[Account]]) -> SouthItalyField Accounts | E17: =_xlfn.IFNA(VLOOKUP(Table1[[#This Row],[Account]],'Account Information'!$A$4:$B$18,2,FALSE),"") -> Field Accounts | F17: 1304135 | G17: 20800 | H17: =Table1[[#This Row],[Units]]/$G$2 -> 0.0085179573 | I17: =F17/G17 -> 62.6988 | J17: =Table1[[#This Row],[Units]]*(1-'Hypotesis Panel'!$F$46) -> 19090.937 | K17: =Table1[[#This Row],[Units]]-Table1[[#This Row],[Shoe Budget Units]] -> 1709.0631 | L17: 871807 | M17: 13000 | N17: =Table1[[#This Row],[Pre-Orders Invoiced (units)]]-Table1[[#This Row],[Cancellations (units)]]+Table1[[#This Row],[Re-Orders Invoiced (units)]]+Table1[[#This Row],[Stock Clearance Invoiced (units)]]+Table1[[#This Row],[Returns Processed (units)]] -> 13400 | O17: =Table1[[#This Row],[Net Sales (€)]]/Table1[[#This Row],[Net Sales Units]] -> 65.060224 | P17: 100 | Q17: =Table1[[#This Row],[Cancellations (units)]]/Table1[[#This Row],[Pre-Orders Invoiced (units)]] -> 0.0076923077 | R17: 500 | S17: =Table1[[#This Row],[Re-Orders Invoiced (units)]]/Table1[[#This Row],[Pre-Orders Invoiced (units)]] -> 0.038461538 | T17: 0 | U17: =Table1[[#This Row],[Stock Clearance Invoiced (units)]]/Table1[[#This Row],[Pre-Orders Invoiced (units)]] -> 0 | V17: 0 | W17: =Table1[[#This Row],[Returns Processed (units)]]/Table1[[#This Row],[Pre-Orders Invoiced (units)]] -> 0 | X17: 45207.118 | Y17: =Table1[[#This Row],[Pre-Orders Invoiced (units)3]]-Table1[[#This Row],[Cancellations (units)4]]+Table1[[#This Row],[Re-Orders Invoiced (units)5]]+Table1[[#This Row],[Stock Clearance Invoiced (units)6]]+Table1[[#This Row],[Returns Processed (units)7]] -> 1032.4 | Z17: =Table1[[#This Row],[Net Sales (€)2]]/Table1[[#This Row],[Net Sales (Units0]] -> 43.788375 | AA17: 1040 | AB17: 8 | AC17: =IFERROR(Table1[[#This Row],[Cancellations (units)4]]/Table1[[#This Row],[Pre-Orders Invoiced (units)3]],0) -> 0.0076923077 | AD17: 0.4 | AE17: =IFERROR(Table1[[#This Row],[Re-Orders Invoiced (units)5]]/Table1[[#This Row],[Pre-Orders Invoiced (units)3]],0) -> 0.00038461538 | AF17: 0 | AG17: =IFERROR(Table1[[#This Row],[Stock Clearance Invoiced (units)6]]/Table1[[#This Row],[Pre-Orders Invoiced (units)3]],0) -> 0 | AH17: 0 | AI17: =IFERROR(Table1[[#This Row],[Returns Processed (units)7]]/Table1[[#This Row],[Pre-Orders Invoiced (units)3]],0) -> 0 | AJ17: =Table1[[#This Row],[Net Sales (€)2]]/Table1[[#This Row],[Net Sales (€)]] -> 0.051854502 | AK17: =Table1[[#This Row],[Net Sales (Units0]]+Table1[[#This Row],[Net Sales Units]] -> 14432.4 | AL17: =Table1[[#This Row],[Net Sales (€)2]]+Table1[[#This Row],[Net Sales (€)]] -> 917014.12 | AM17: 3300 | AN17: 345 | AO17: =Table1[[#This Row],[Pre-Orders Invoiced (units)]]-Table1[[#This Row],[Cancellations (units)]]+Table1[[#This Row],[Re-Orders Invoiced (units)]]+Table1[[#This Row],[Stock Clearance Invoiced (units)]]+Table1[[#This Row],[Returns Processed (units)]] -> 13400 | AP17: =Table1[[#This Row],[Net Sales (€)]]/AO17 -> 65.060224 | AQ17: =AA17-+AB17+Table1[[#This Row],[Re-Orders Invoiced (units)5]]+AF17+AH17 -> 1032.4 | AR17: =IFERROR(Table1[[#This Row],[Net Sales (€)2]]/AQ17,"") -> 43.788375 | AT17: =L17+X17 -> 917014.12 | AU17: =F17*$AU$1 -> 847687.78 | AV17: =AT17/AU17-1 -> 0.081782873 | AW17: =AU17/$AU$2 -> 0.0088463309 | AX17: =ROUND(AW17*AV17*10000,0) -> 7 | AZ17: =AU17*(1-'SS24 Q2 Data'!$AB$5) -> 778036.24 | BA17: =L17/AZ17-1 -> 0.12052235 | BB17: =AZ17/$AZ$2 -> 0.0088463309 | BC17: =BB17*BA17*10000 -> 10.661806 | BE17: =AU17*'SS24 Q2 Data'!$AB$5 -> 69651.535 | BF17: =X17/BE17-1 -> -0.35095303 | BG17: =BE17/$BE$2 -> 0.0088463309 | BH17: =BG17*BF17*10000 -> -31.046466 | BJ17: =Table1[[#This Row],[Net Sales Units]]/Table1[[#This Row],[Shoe Budget Units]] -> 0.70190374 | BK17: =Table1[[#This Row],[Net Sales (Units0]]/Table1[[#This Row],[Apparel Budget Units]] -> 0.60407365 | BL17: =Table1[[#This Row],[Net Sales Units total]]/Table1[[#This Row],[Units]] -> 0.69386538 | BM17: =ROUND(Table1[[#This Row],[Net Sales Units]]/'Hypotesis Panel'!$G$8,0) -> 957 | BN17: =ROUND('Hypotesis Panel'!$G$8/Table1[[#This Row],[ST% Shoes]],0) -> 20 | BO17: =Table1[[#This Row],[Net Sales (Units0]]/'Hypotesis Panel'!$G$8 -> 73.742857 | BP17: =IFERROR(ROUND('Hypotesis Panel'!$G$8/Table1[[#This Row],[ST% Apparel]],0),"NoStock") -> 23 | BQ17: =IFERROR(ROUND('Hypotesis Panel'!$G$8/Table1[[#This Row],[ST% ToTal]],0),"") -> 20 | BR17: =Table1[[#This Row],[Expected WoOS Shoes]]-'Hypotesis Panel'!$G$8 -> 6 | BS17: =IFERROR(Table1[[#This Row],[Expected WoOS Apparel]]-'Hypotesis Panel'!$G$8,"") -> 9 | BT17: =Table1[[#This Row],[Expected WoOS Total]]-'Hypotesis Panel'!$G$8 -> 6 | BU17: =Table1[[#This Row],[WOCoverage Shoes]]+'Hypotesis Panel'!$G$8-'Hypotesis Panel'!$F$3 -> -6 | BV17: =_xlfn.XLOOKUP(Table1[[#This Row],[WOS at WK26 Shoes]],Table2[Lower Bound],Table2[Action],,-1) -> Stock Out Risk | BW17: =IF(Table1[[#This Row],[WOS at WK26 Shoes]]*Table1[[#This Row],[Avg Shoes Q1 Weekly Sales]]*Table1[[#This Row],[Actual ASP Shoes per channel]]>0,0,Table1[[#This Row],[WOS at WK26 Shoes]]*Table1[[#This Row],[Avg Shoes Q1 Weekly Sales]]*Table1[[#This Row],[Actual ASP Shoes per channel]]) -> -373575.81 | BX17: =Table1[[#This Row],[WOC Apparel]]+'Hypotesis Panel'!$G$8-'Hypotesis Panel'!$F$3 -> -3 | BY17: =_xlfn.XLOOKUP(Table1[[#This Row],[WOS at WK26 Apparel]],Table2[Lower Bound],Table2[Action],,-1) -> Stock Out Risk | CA17: =ROUND(Table1[[#This Row],[% Budget share]]*'Available Stock'!$H$6,0) -> 8292 | CB17: =ROUND(Table1[[#This Row],[% Budget share]]*'Available Stock'!$I$6,0) -> 4975 | CC17: =Table1[[#This Row],[Net Sales (Units0]]/'Hypotesis Panel'!$G$8 -> 73.742857 | CD17: =ROUND(Table1[[#This Row],[% Budget share]]*'Available Stock'!$H$7,0) -> 1240 | CE17: =ROUND(Table1[[#This Row],[% Budget share]]*'Available Stock'!$I$7,0) -> 347 | CF17: =Table1[[#This Row],[Shoes Available Q2 Stock Current Season ]]/#REF! -> #REF! | CG17: =Table1[[#This Row],[Shoes Available Q2 Stock Old Season]]/#REF! -> #REF! | CH17: =SUM(Table1[[#This Row],[Q2 Shoes New Stock WOC based on Q1 Sales Velocity]:[Q2 Shoes Old Stock WOC based on Q1 Sales Velocity]]) -> #REF! | CI17: =IFERROR(Table1[[#This Row],[Apparel Q2 Available Stock Current Season 2]]/Table1[[#This Row],[Avg Apparel Q1 Weekly Sales2]],"") -> 16.815188 | CJ17: =IFERROR(Table1[[#This Row],[Apparel Q2Available Stock Old Season3]]/Table1[[#This Row],[Avg Apparel Q1 Weekly Sales2]],"") -> 4.7055405 | CK17: =SUM(Table1[[#This Row],[Q2 Apparel New Stock WOC based on Q1 Sales Velocity]:[Q2 Apparel Old Stock WOC based on Q1 Sales Velocity]]) -> 21.520728
A18: North | B18: France | C18: Velocity Labs | D18: =_xlfn.CONCAT(Table1[[#This Row],[Sub Region]:[Account]]) -> NorthFranceVelocity Labs | E18: =_xlfn.IFNA(VLOOKUP(Table1[[#This Row],[Account]],'Account Information'!$A$4:$B$18,2,FALSE),"") -> Sport | F18: 1809249 | G18: 29900 | H18: =Table1[[#This Row],[Units]]/$G$2 -> 0.012244564 | I18: =F18/G18 -> 60.51 | J18: =Table1[[#This Row],[Units]]*(1-'Hypotesis Panel'!$F$46) -> 27443.222 | K18: =Table1[[#This Row],[Units]]-Table1[[#This Row],[Shoe Budget Units]] -> 2456.7783 | L18: 786870 | M18: 12600 | N18: =Table1[[#This Row],[Pre-Orders Invoiced (units)]]-Table1[[#This Row],[Cancellations (units)]]+Table1[[#This Row],[Re-Orders Invoiced (units)]]+Table1[[#This Row],[Stock Clearance Invoiced (units)]]+Table1[[#This Row],[Returns Processed (units)]] -> 12100 | O18: =Table1[[#This Row],[Net Sales (€)]]/Table1[[#This Row],[Net Sales Units]] -> 65.030579 | P18: 500 | Q18: =Table1[[#This Row],[Cancellations (units)]]/Table1[[#This Row],[Pre-Orders Invoiced (units)]] -> 0.03968254 | R18: 0 | S18: =Table1[[#This Row],[Re-Orders Invoiced (units)]]/Table1[[#This Row],[Pre-Orders Invoiced (units)]] -> 0 | T18: 0 | U18: =Table1[[#This Row],[Stock Clearance Invoiced (units)]]/Table1[[#This Row],[Pre-Orders Invoiced (units)]] -> 0 | V18: 0 | W18: =Table1[[#This Row],[Returns Processed (units)]]/Table1[[#This Row],[Pre-Orders Invoiced (units)]] -> 0 | X18: 55320.54 | Y18: =Table1[[#This Row],[Pre-Orders Invoiced (units)3]]-Table1[[#This Row],[Cancellations (units)4]]+Table1[[#This Row],[Re-Orders Invoiced (units)5]]+Table1[[#This Row],[Stock Clearance Invoiced (units)6]]+Table1[[#This Row],[Returns Processed (units)7]] -> 1222 | Z18: =Table1[[#This Row],[Net Sales (€)2]]/Table1[[#This Row],[Net Sales (Units0]] -> 45.270491 | AA18: 1260 | AB18: 50 | AC18: =IFERROR(Table1[[#This Row],[Cancellations (units)4]]/Table1[[#This Row],[Pre-Orders Invoiced (units)3]],0) -> 0.03968254 | AD18: 12 | AE18: =IFERROR(Table1[[#This Row],[Re-Orders Invoiced (units)5]]/Table1[[#This Row],[Pre-Orders Invoiced (units)3]],0) -> 0.0095238095 | AF18: 0 | AG18: =IFERROR(Table1[[#This Row],[Stock Clearance Invoiced (units)6]]/Table1[[#This Row],[Pre-Orders Invoiced (units)3]],0) -> 0 | AH18: 0 | AI18: =IFERROR(Table1[[#This Row],[Returns Processed (units)7]]/Table1[[#This Row],[Pre-Orders Invoiced (units)3]],0) -> 0 | AJ18: =Table1[[#This Row],[Net Sales (€)2]]/Table1[[#This Row],[Net Sales (€)]] -> 0.070304548 | AK18: =Table1[[#This Row],[Net Sales (Units0]]+Table1[[#This Row],[Net Sales Units]] -> 13322 | AL18: =Table1[[#This Row],[Net Sales (€)2]]+Table1[[#This Row],[Net Sales (€)]] -> 842190.54 | AM18: 10400 | AN18: 213 | AO18: =Table1[[#This Row],[Pre-Orders Invoiced (units)]]-Table1[[#This Row],[Cancellations (units)]]+Table1[[#This Row],[Re-Orders Invoiced (units)]]+Table1[[#This Row],[Stock Clearance Invoiced (units)]]+Table1[[#This Row],[Returns Processed (units)]] -> 12100 | AP18: =Table1[[#This Row],[Net Sales (€)]]/AO18 -> 65.030579 | AQ18: =AA18-+AB18+Table1[[#This Row],[Re-Orders Invoiced (units)5]]+AF18+AH18 -> 1222 | AR18: =IFERROR(Table1[[#This Row],[Net Sales (€)2]]/AQ18,"") -> 45.270491 | AT18: =L18+X18 -> 842190.54 | AU18: =F18*$AU$1 -> 1176011.9 | AV18: =AT18/AU18-1 -> -0.2838588 | AW18: =AU18/$AU$2 -> 0.012272667 | AX18: =ROUND(AW18*AV18*10000,0) -> -35 | AZ18: =AU18*(1-'SS24 Q2 Data'!$AB$5) -> 1079383.1 | BA18: =L18/AZ18-1 -> -0.27100024 | BB18: =AZ18/$AZ$2 -> 0.012272667 | BC18: =BB18*BA18*10000 -> -33.258958 | BE18: =AU18*'SS24 Q2 Data'!$AB$5 -> 96628.774 | BF18: =X18/BE18-1 -> -0.42749413 | BG18: =BE18/$BE$2 -> 0.012272667 | BH18: =BG18*BF18*10000 -> -52.464932 | BJ18: =Table1[[#This Row],[Net Sales Units]]/Table1[[#This Row],[Shoe Budget Units]] -> 0.44091033 | BK18: =Table1[[#This Row],[Net Sales (Units0]]/Table1[[#This Row],[Apparel Budget Units]] -> 0.49739939 | BL18: =Table1[[#This Row],[Net Sales Units total]]/Table1[[#This Row],[Units]] -> 0.44555184 | BM18: =ROUND(Table1[[#This Row],[Net Sales Units]]/'Hypotesis Panel'!$G$8,0) -> 864 | BN18: =ROUND('Hypotesis Panel'!$G$8/Table1[[#This Row],[ST% Shoes]],0) -> 32 | BO18: =Table1[[#This Row],[Net Sales (Units0]]/'Hypotesis Panel'!$G$8 -> 87.285714 | BP18: =IFERROR(ROUND('Hypotesis Panel'!$G$8/Table1[[#This Row],[ST% Apparel]],0),"NoStock") -> 28 | BQ18: =IFERROR(ROUND('Hypotesis Panel'!$G$8/Table1[[#This Row],[ST% ToTal]],0),"") -> 31 | BR18: =Table1[[#This Row],[Expected WoOS Shoes]]-'Hypotesis Panel'!$G$8 -> 18 | BS18: =IFERROR(Table1[[#This Row],[Expected WoOS Apparel]]-'Hypotesis Panel'!$G$8,"") -> 14 | BT18: =Table1[[#This Row],[Expected WoOS Total]]-'Hypotesis Panel'!$G$8 -> 17 | BU18: =Table1[[#This Row],[WOCoverage Shoes]]+'Hypotesis Panel'!$G$8-'Hypotesis Panel'!$F$3 -> 6 | BV18: =_xlfn.XLOOKUP(Table1[[#This Row],[WOS at WK26 Shoes]],Table2[Lower Bound],Table2[Action],,-1) -> Overstock | BW18: =IF(Table1[[#This Row],[WOS at WK26 Shoes]]*Table1[[#This Row],[Avg Shoes Q1 Weekly Sales]]*Table1[[#This Row],[Actual ASP Shoes per channel]]>0,0,Table1[[#This Row],[WOS at WK26 Shoes]]*Table1[[#This Row],[Avg Shoes Q1 Weekly Sales]]*Table1[[#This Row],[Actual ASP Shoes per channel]]) -> 0 | BX18: =Table1[[#This Row],[WOC Apparel]]+'Hypotesis Panel'!$G$8-'Hypotesis Panel'!$F$3 -> 2 | BY18: =_xlfn.XLOOKUP(Table1[[#This Row],[WOS at WK26 Apparel]],Table2[Lower Bound],Table2[Action],,-1) -> Monitor | CA18: =ROUND(Table1[[#This Row],[% Budget share]]*'Available Stock'!$H$6,0) -> 11919 | CB18: =ROUND(Table1[[#This Row],[% Budget share]]*'Available Stock'!$I$6,0) -> 7152 | CC18: =Table1[[#This Row],[Net Sales (Units0]]/'Hypotesis Panel'!$G$8 -> 87.285714 | CD18: =ROUND(Table1[[#This Row],[% Budget share]]*'Available Stock'!$H$7,0) -> 1782 | CE18: =ROUND(Table1[[#This Row],[% Budget share]]*'Available Stock'!$I$7,0) -> 499 | CF18: =Table1[[#This Row],[Shoes Available Q2 Stock Current Season ]]/#REF! -> #REF! | CG18: =Table1[[#This Row],[Shoes Available Q2 Stock Old Season]]/#REF! -> #REF! | CH18: =SUM(Table1[[#This Row],[Q2 Shoes New Stock WOC based on Q1 Sales Velocity]:[Q2 Shoes Old Stock WOC based on Q1 Sales Velocity]]) -> #REF! | CI18: =IFERROR(Table1[[#This Row],[Apparel Q2 Available Stock Current Season 2]]/Table1[[#This Row],[Avg Apparel Q1 Weekly Sales2]],"") -> 20.415712 | CJ18: =IFERROR(Table1[[#This Row],[Apparel Q2Available Stock Old Season3]]/Table1[[#This Row],[Avg Apparel Q1 Weekly Sales2]],"") -> 5.7168576 | CK18: =SUM(Table1[[#This Row],[Q2 Apparel New Stock WOC based on Q1 Sales Velocity]:[Q2 Apparel Old Stock WOC based on Q1 Sales Velocity]]) -> 26.13257
A19: North | B19: United Kingdom | C19: Titan Sport | D19: =_xlfn.CONCAT(Table1[[#This Row],[Sub Region]:[Account]]) -> NorthUnited KingdomTitan Sport | E19: =_xlfn.IFNA(VLOOKUP(Table1[[#This Row],[Account]],'Account Information'!$A$4:$B$18,2,FALSE),"") -> Sport | F19: 2912567.1 | G19: 45300 | H19: =Table1[[#This Row],[Units]]/$G$2 -> 0.018551128 | I19: =F19/G19 -> 64.29508 | J19: =Table1[[#This Row],[Units]]*(1-'Hypotesis Panel'!$F$46) -> 41577.858 | K19: =Table1[[#This Row],[Units]]-Table1[[#This Row],[Shoe Budget Units]] -> 3722.1423 | L19: 903579.24 | M19: 15200 | N19: =Table1[[#This Row],[Pre-Orders Invoiced (units)]]-Table1[[#This Row],[Cancellations (units)]]+Table1[[#This Row],[Re-Orders Invoiced (units)]]+Table1[[#This Row],[Stock Clearance Invoiced (units)]]+Table1[[#This Row],[Returns Processed (units)]] -> 11240 | O19: =Table1[[#This Row],[Net Sales (€)]]/Table1[[#This Row],[Net Sales Units]] -> 80.389612 | P19: 2560 | Q19: =Table1[[#This Row],[Cancellations (units)]]/Table1[[#This Row],[Pre-Orders Invoiced (units)]] -> 0.16842105 | R19: 200 | S19: =Table1[[#This Row],[Re-Orders Invoiced (units)]]/Table1[[#This Row],[Pre-Orders Invoiced (units)]] -> 0.013157895 | T19: 0 | U19: =Table1[[#This Row],[Stock Clearance Invoiced (units)]]/Table1[[#This Row],[Pre-Orders Invoiced (units)]] -> 0 | V19: -1600 | W19: =Table1[[#This Row],[Returns Processed (units)]]/Table1[[#This Row],[Pre-Orders Invoiced (units)]] -> -0.10526316 | X19: 55539.196 | Y19: =Table1[[#This Row],[Pre-Orders Invoiced (units)3]]-Table1[[#This Row],[Cancellations (units)4]]+Table1[[#This Row],[Re-Orders Invoiced (units)5]]+Table1[[#This Row],[Stock Clearance Invoiced (units)6]]+Table1[[#This Row],[Returns Processed (units)7]] -> 918.8 | Z19: =Table1[[#This Row],[Net Sales (€)2]]/Table1[[#This Row],[Net Sales (Units0]] -> 60.447536 | AA19: 1064 | AB19: 179.2 | AC19: =IFERROR(Table1[[#This Row],[Cancellations (units)4]]/Table1[[#This Row],[Pre-Orders Invoiced (units)3]],0) -> 0.16842105 | AD19: 34 | AE19: =IFERROR(Table1[[#This Row],[Re-Orders Invoiced (units)5]]/Table1[[#This Row],[Pre-Orders Invoiced (units)3]],0) -> 0.031954887 | AF19: 0 | AG19: =IFERROR(Table1[[#This Row],[Stock Clearance Invoiced (units)6]]/Table1[[#This Row],[Pre-Orders Invoiced (units)3]],0) -> 0 | AH19: 0 | AI19: =IFERROR(Table1[[#This Row],[Returns Processed (units)7]]/Table1[[#This Row],[Pre-Orders Invoiced (units)3]],0) -> 0 | AJ19: =Table1[[#This Row],[Net Sales (€)2]]/Table1[[#This Row],[Net Sales (€)]] -> 0.061465773 | AK19: =Table1[[#This Row],[Net Sales (Units0]]+Table1[[#This Row],[Net Sales Units]] -> 12158.8 | AL19: =Table1[[#This Row],[Net Sales (€)2]]+Table1[[#This Row],[Net Sales (€)]] -> 959118.44 | AM19: 24800 | AN19: 2345 | AO19: =Table1[[#This Row],[Pre-Orders Invoiced (units)]]-Table1[[#This Row],[Cancellations (units)]]+Table1[[#This Row],[Re-Orders Invoiced (units)]]+Table1[[#This Row],[Stock Clearance Invoiced (units)]]+Table1[[#This Row],[Returns Processed (units)]] -> 11240 | AP19: =Table1[[#This Row],[Net Sales (€)]]/AO19 -> 80.389612 | AQ19: =AA19-+AB19+Table1[[#This Row],[Re-Orders Invoiced (units)5]]+AF19+AH19 -> 918.8 | AR19: =IFERROR(Table1[[#This Row],[Net Sales (€)2]]/AQ19,"") -> 60.447536 | AT19: =L19+X19 -> 959118.44 | AU19: =F19*$AU$1 -> 1893168.6 | AV19: =AT19/AU19-1 -> -0.49337929 | AW19: =AU19/$AU$2 -> 0.019756798 | AX19: =ROUND(AW19*AV19*10000,0) -> -97 | AZ19: =AU19*(1-'SS24 Q2 Data'!$AB$5) -> 1737613.6 | BA19: =L19/AZ19-1 -> -0.47998839 | BB19: =AZ19/$AZ$2 -> 0.019756798 | BC19: =BB19*BA19*10000 -> -94.830337 | BE19: =AU19*'SS24 Q2 Data'!$AB$5 -> 155555.03 | BF19: =X19/BE19-1 -> -0.64296111 | BG19: =BE19/$BE$2 -> 0.019756798 | BH19: =BG19*BF19*10000 -> -127.02853 | BJ19: =Table1[[#This Row],[Net Sales Units]]/Table1[[#This Row],[Shoe Budget Units]] -> 0.2703362 | BK19: =Table1[[#This Row],[Net Sales (Units0]]/Table1[[#This Row],[Apparel Budget Units]] -> 0.24684709 | BL19: =Table1[[#This Row],[Net Sales Units total]]/Table1[[#This Row],[Units]] -> 0.26840618 | BM19: =ROUND(Table1[[#This Row],[Net Sales Units]]/'Hypotesis Panel'!$G$8,0) -> 803 | BN19: =ROUND('Hypotesis Panel'!$G$8/Table1[[#This Row],[ST% Shoes]],0) -> 52 | BO19: =Table1[[#This Row],[Net Sales (Units0]]/'Hypotesis Panel'!$G$8 -> 65.628571 | BP19: =IFERROR(ROUND('Hypotesis Panel'!$G$8/Table1[[#This Row],[ST% Apparel]],0),"NoStock") -> 57 | BQ19: =IFERROR(ROUND('Hypotesis Panel'!$G$8/Table1[[#This Row],[ST% ToTal]],0),"") -> 52 | BR19: =Table1[[#This Row],[Expected WoOS Shoes]]-'Hypotesis Panel'!$G$8 -> 38 | BS19: =IFERROR(Table1[[#This Row],[Expected WoOS Apparel]]-'Hypotesis Panel'!$G$8,"") -> 43 | BT19: =Table1[[#This Row],[Expected WoOS Total]]-'Hypotesis Panel'!$G$8 -> 38 | BU19: =Table1[[#This Row],[WOCoverage Shoes]]+'Hypotesis Panel'!$G$8-'Hypotesis Panel'!$F$3 -> 26 | BV19: =_xlfn.XLOOKUP(Table1[[#This Row],[WOS at WK26 Shoes]],Table2[Lower Bound],Table2[Action],,-1) -> Overstock | BW19: =IF(Table1[[#This Row],[WOS at WK26 Shoes]]*Table1[[#This Row],[Avg Shoes Q1 Weekly Sales]]*Table1[[#This Row],[Actual ASP Shoes per channel]]>0,0,Table1[[#This Row],[WOS at WK26 Shoes]]*Table1[[#This Row],[Avg Shoes Q1 Weekly Sales]]*Table1[[#This Row],[Actual ASP Shoes per channel]]) -> 0 | BX19: =Table1[[#This Row],[WOC Apparel]]+'Hypotesis Panel'!$G$8-'Hypotesis Panel'!$F$3 -> 31 | BY19: =_xlfn.XLOOKUP(Table1[[#This Row],[WOS at WK26 Apparel]],Table2[Lower Bound],Table2[Action],,-1) -> Overstock | CA19: =ROUND(Table1[[#This Row],[% Budget share]]*'Available Stock'!$H$6,0) -> 18058 | CB19: =ROUND(Table1[[#This Row],[% Budget share]]*'Available Stock'!$I$6,0) -> 10835 | CC19: =Table1[[#This Row],[Net Sales (Units0]]/'Hypotesis Panel'!$G$8 -> 65.628571 | CD19: =ROUND(Table1[[#This Row],[% Budget share]]*'Available Stock'!$H$7,0) -> 2700 | CE19: =ROUND(Table1[[#This Row],[% Budget share]]*'Available Stock'!$I$7,0) -> 756 | CF19: =Table1[[#This Row],[Shoes Available Q2 Stock Current Season ]]/#REF! -> #REF! | CG19: =Table1[[#This Row],[Shoes Available Q2 Stock Old Season]]/#REF! -> #REF! | CH19: =SUM(Table1[[#This Row],[Q2 Shoes New Stock WOC based on Q1 Sales Velocity]:[Q2 Shoes Old Stock WOC based on Q1 Sales Velocity]]) -> #REF! | CI19: =IFERROR(Table1[[#This Row],[Apparel Q2 Available Stock Current Season 2]]/Table1[[#This Row],[Avg Apparel Q1 Weekly Sales2]],"") -> 41.140618 | CJ19: =IFERROR(Table1[[#This Row],[Apparel Q2Available Stock Old Season3]]/Table1[[#This Row],[Avg Apparel Q1 Weekly Sales2]],"") -> 11.519373 | CK19: =SUM(Table1[[#This Row],[Q2 Apparel New Stock WOC based on Q1 Sales Velocity]:[Q2 Apparel Old Stock WOC based on Q1 Sales Velocity]]) -> 52.659991
... A27: South | B27: Spain | C27: Agora Athletics | D27: =_xlfn.CONCAT(Table1[[#This Row],[Sub Region]:[Account]]) -> SouthSpainAgora Athletics | E27: =_xlfn.IFNA(VLOOKUP(Table1[[#This Row],[Account]],'Account Information'!$A$4:$B$18,2,FALSE),"") -> Sport | F27: 115984.4 | G27: 2000 | H27: =Table1[[#This Row],[Units]]/$G$2 -> 0.00081903436 | I27: =F27/G27 -> 57.9922 | J27: =Table1[[#This Row],[Units]]*(1-'Hypotesis Panel'!$F$46) -> 1835.667 | K27: =Table1[[#This Row],[Units]]-Table1[[#This Row],[Shoe Budget Units]] -> 164.33299 | L27: 59430 | M27: 1000 | N27: =Table1[[#This Row],[Pre-Orders Invoiced (units)]]-Table1[[#This Row],[Cancellations (units)]]+Table1[[#This Row],[Re-Orders Invoiced (units)]]+Table1[[#This Row],[Stock Clearance Invoiced (units)]]+Table1[[#This Row],[Returns Processed (units)]] -> 1000 | O27: =Table1[[#This Row],[Net Sales (€)]]/Table1[[#This Row],[Net Sales Units]] -> 59.43 | P27: 0 | Q27: =Table1[[#This Row],[Cancellations (units)]]/Table1[[#This Row],[Pre-Orders Invoiced (units)]] -> 0 | R27: 0 | S27: =Table1[[#This Row],[Re-Orders Invoiced (units)]]/Table1[[#This Row],[Pre-Orders Invoiced (units)]] -> 0 | T27: 0 | U27: =Table1[[#This Row],[Stock Clearance Invoiced (units)]]/Table1[[#This Row],[Pre-Orders Invoiced (units)]] -> 0 | V27: 0 | W27: =Table1[[#This Row],[Returns Processed (units)]]/Table1[[#This Row],[Pre-Orders Invoiced (units)]] -> 0 | X27: 5722.64 | Y27: =Table1[[#This Row],[Pre-Orders Invoiced (units)3]]-Table1[[#This Row],[Cancellations (units)4]]+Table1[[#This Row],[Re-Orders Invoiced (units)5]]+Table1[[#This Row],[Stock Clearance Invoiced (units)6]]+Table1[[#This Row],[Returns Processed (units)7]] -> 122 | Z27: =Table1[[#This Row],[Net Sales (€)2]]/Table1[[#This Row],[Net Sales (Units0]] -> 46.906885 | AA27: 110 | AB27: 0 | AC27: =IFERROR(Table1[[#This Row],[Cancellations (units)4]]/Table1[[#This Row],[Pre-Orders Invoiced (units)3]],0) -> 0 | AD27: 12 | AE27: =IFERROR(Table1[[#This Row],[Re-Orders Invoiced (units)5]]/Table1[[#This Row],[Pre-Orders Invoiced (units)3]],0) -> 0.10909091 | AF27: 0 | AG27: =IFERROR(Table1[[#This Row],[Stock Clearance Invoiced (units)6]]/Table1[[#This Row],[Pre-Orders Invoiced (units)3]],0) -> 0 | AH27: 0 | AI27: =IFERROR(Table1[[#This Row],[Returns Processed (units)7]]/Table1[[#This Row],[Pre-Orders Invoiced (units)3]],0) -> 0 | AJ27: =Table1[[#This Row],[Net Sales (€)2]]/Table1[[#This Row],[Net Sales (€)]] -> 0.096292108 | AK27: =Table1[[#This Row],[Net Sales (Units0]]+Table1[[#This Row],[Net Sales Units]] -> 1122 | AL27: =Table1[[#This Row],[Net Sales (€)2]]+Table1[[#This Row],[Net Sales (€)]] -> 65152.64 | AM27: 900 | AN27: 0 | AO27: =Table1[[#This Row],[Pre-Orders Invoiced (units)]]-Table1[[#This Row],[Cancellations (units)]]+Table1[[#This Row],[Re-Orders Invoiced (units)]]+Table1[[#This Row],[Stock Clearance Invoiced (units)]]+Table1[[#This Row],[Returns Processed (units)]] -> 1000 | AP27: =Table1[[#This Row],[Net Sales (€)]]/AO27 -> 59.43 | AQ27: =AA27-+AB27+Table1[[#This Row],[Re-Orders Invoiced (units)5]]+AF27+AH27 -> 122 | AR27: =IFERROR(Table1[[#This Row],[Net Sales (€)2]]/AQ27,"") -> 46.906885 | AT27: =L27+X27 -> 65152.64 | AU27: =F27*$AU$1 -> 75389.86 | AV27: =AT27/AU27-1 -> -0.13579041 | AW27: =AU27/$AU$2 -> 0.00078675624 | AX27: =ROUND(AW27*AV27*10000,0) -> -1 | AZ27: =AU27*(1-'SS24 Q2 Data'!$AB$5) -> 69195.339 | BA27: =L27/AZ27-1 -> -0.14112713 | BB27: =AZ27/$AZ$2 -> 0.00078675624 | BC27: =BB27*BA27*10000 -> -1.1103265 | BE27: =AU27*'SS24 Q2 Data'!$AB$5 -> 6194.5207 | BF27: =X27/BE27-1 -> -0.076177113 | BG27: =BE27/$BE$2 -> 0.00078675624 | BH27: =BG27*BF27*10000 -> -0.59932819 | BJ27: =Table1[[#This Row],[Net Sales Units]]/Table1[[#This Row],[Shoe Budget Units]] -> 0.54476111 | BK27: =Table1[[#This Row],[Net Sales (Units0]]/Table1[[#This Row],[Apparel Budget Units]] -> 0.74239504 | BL27: =Table1[[#This Row],[Net Sales Units total]]/Table1[[#This Row],[Units]] -> 0.561 | BM27: =ROUND(Table1[[#This Row],[Net Sales Units]]/'Hypotesis Panel'!$G$8,0) -> 71 | BN27: =ROUND('Hypotesis Panel'!$G$8/Table1[[#This Row],[ST% Shoes]],0) -> 26 | BO27: =Table1[[#This Row],[Net Sales (Units0]]/'Hypotesis Panel'!$G$8 -> 8.7142857 | BP27: =IFERROR(ROUND('Hypotesis Panel'!$G$8/Table1[[#This Row],[ST% Apparel]],0),"NoStock") -> 19 | BQ27: =IFERROR(ROUND('Hypotesis Panel'!$G$8/Table1[[#This Row],[ST% ToTal]],0),"") -> 25 | BR27: =Table1[[#This Row],[Expected WoOS Shoes]]-'Hypotesis Panel'!$G$8 -> 12 | BS27: =IFERROR(Table1[[#This Row],[Expected WoOS Apparel]]-'Hypotesis Panel'!$G$8,"") -> 5 | BT27: =Table1[[#This Row],[Expected WoOS Total]]-'Hypotesis Panel'!$G$8 -> 11 | BU27: =Table1[[#This Row],[WOCoverage Shoes]]+'Hypotesis Panel'!$G$8-'Hypotesis Panel'!$F$3 -> 0 | BV27: =_xlfn.XLOOKUP(Table1[[#This Row],[WOS at WK26 Shoes]],Table2[Lower Bound],Table2[Action],,-1) -> Monitor | BW27: =IF(Table1[[#This Row],[WOS at WK26 Shoes]]*Table1[[#This Row],[Avg Shoes Q1 Weekly Sales]]*Table1[[#This Row],[Actual ASP Shoes per channel]]>0,0,Table1[[#This Row],[WOS at WK26 Shoes]]*Table1[[#This Row],[Avg Shoes Q1 Weekly Sales]]*Table1[[#This Row],[Actual ASP Shoes per channel]]) -> 0 | BX27: =Table1[[#This Row],[WOC Apparel]]+'Hypotesis Panel'!$G$8-'Hypotesis Panel'!$F$3 -> -7 | BY27: =_xlfn.XLOOKUP(Table1[[#This Row],[WOS at WK26 Apparel]],Table2[Lower Bound],Table2[Action],,-1) -> Stock Out Risk | CA27: =ROUND(Table1[[#This Row],[% Budget share]]*'Available Stock'!$H$6,0) -> 797 | CB27: =ROUND(Table1[[#This Row],[% Budget share]]*'Available Stock'!$I$6,0) -> 478 | CC27: =Table1[[#This Row],[Net Sales (Units0]]/'Hypotesis Panel'!$G$8 -> 8.7142857 | CD27: =ROUND(Table1[[#This Row],[% Budget share]]*'Available Stock'!$H$7,0) -> 119 | CE27: =ROUND(Table1[[#This Row],[% Budget share]]*'Available Stock'!$I$7,0) -> 33 | CF27: =Table1[[#This Row],[Shoes Available Q2 Stock Current Season ]]/#REF! -> #REF! | CG27: =Table1[[#This Row],[Shoes Available Q2 Stock Old Season]]/#REF! -> #REF! | CH27: =SUM(Table1[[#This Row],[Q2 Shoes New Stock WOC based on Q1 Sales Velocity]:[Q2 Shoes Old Stock WOC based on Q1 Sales Velocity]]) -> #REF! | CI27: =IFERROR(Table1[[#This Row],[Apparel Q2 Available Stock Current Season 2]]/Table1[[#This Row],[Avg Apparel Q1 Weekly Sales2]],"") -> 13.655738 | CJ27: =IFERROR(Table1[[#This Row],[Apparel Q2Available Stock Old Season3]]/Table1[[#This Row],[Avg Apparel Q1 Weekly Sales2]],"") -> 3.7868852 | CK27: =SUM(Table1[[#This Row],[Q2 Apparel New Stock WOC based on Q1 Sales Velocity]:[Q2 Apparel Old Stock WOC based on Q1 Sales Velocity]]) -> 17.442623

Sheet SS25 Landing

Sheet Pivot
B1: Actuals Vs Phased Plan Top Contributors/Offenders
B3: Row Labels | C3: Sum of CTC (bps)
B4: Central | C4: 756
B5: Field Accounts | C5: 678
B6: Germany | C6: 362
B7: Austria | C7: 183
B8: Switzerland | C8: 133
B9: Lifestyle / Sport | C9: 78
B10: Germany | C10: 78
B11: Europe | C11: 70
B12: Lifestyle / Sport | C12: 94
B13: Europe | C13: 94
B14: Lifestyle | C14: -10
B15: Europe | C15: -10
... B40: Grand Total | C40: 722

Sheet Support Sheet (don't touch)
A2: 1
A3: 2
A4: 3
A5: 4
A6: 5
A7: 6
A8: 7
A9: 8
A10: 9
A11: 10
A12: 11
A13: 12
... A27: 26
